Workbook

Sheet Small Cap
A1: ( As on 14-08-26 ) | M1: 46082
A2: Scheme Name | B2: 1 Week | C2: 1 Month | D2: 3 Months | E2: 6 Months | F2: 1 Year | G2: 3 Years | H2: 5 Years | I2: Since Inception | K2: AUM ( June 26) | M2: Direct | N2: Regular
A3: Abakkus Small Cap Fund - Dir - Growth | B3: -0.2 | C3: 2.35 | D3: 14.04 | E3: -- | F3: -- | G3: -- | H3: -- | I3: 25.6 | K3: 1494.42 | M3: 1.09 | N3: 2.43
A4: Aditya Birla Sun Life Small Cap Fund - Dir - Growth | B4: 1.14 | C4: 5.19 | D4: 12.25 | E4: 19 | F4: 21.51 | G4: 17.67 | H4: 15.05 | I4: 17.19 | K4: 5731.31 | M4: 0.91 | N4: 1.9
A5: Axis Small Cap Fund - Dir - Growth | B5: 0.76 | C5: 3.12 | D5: 10.18 | E5: 14.55 | F5: 12.86 | G5: 17.76 | H5: 17.71 | I5: 22.83 | K5: 29393.79 | M5: 0.56 | N5: 1.61
A6: Bajaj Finserv Small Cap Fund - Dir - Growth | B6: 0.1 | C6: 3.28 | D6: 12.09 | E6: 18.73 | F6: 19.87 | G6: -- | H6: -- | I6: 11.76 | K6: 2210.9 | M6: 0.55 | N6: 2.05
A7: Bandhan Small Cap Fund - Dir - Growth | B7: -0.56 | C7: 2.02 | D7: 7.98 | E7: 12.49 | F7: 13.87 | G7: 27.16 | H7: 20.29 | I7: 30.75 | K7: 28466.18 | M7: 0.51 | N7: 1.64
A8: Bank of India Small Cap Fund - Dir - Growth | B8: 1.04 | C8: 5.31 | D8: 17.04 | E8: 30.97 | F8: 29.29 | G8: 24.04 | H8: 21.19 | I8: 27.72 | K8: 2572.4 | M8: 0.51 | N8: 1.95
A9: Baroda BNP Paribas Small Cap Fund - Dir - Growth | B9: -0.39 | C9: 1.65 | D9: 6 | E9: 12.74 | F9: 12.94 | G9: -- | H9: -- | I9: 14.8 | K9: 1258.55 | M9: 0.95 | N9: 2.18
A10: Canara Robeco Small Cap Fund - Dir - Growth | B10: 0.52 | C10: 2.52 | D10: 7.98 | E10: 10.5 | F10: 10.14 | G10: 15.21 | H10: 17.17 | I10: 22.67 | K10: 13967.05 | M10: 0.56 | N10: 1.71
A11: DSP Small Cap Fund - Dir - Growth | B11: 1.36 | C11: 3.29 | D11: 14.01 | E11: 17.85 | F11: 20.97 | G11: 19.32 | H11: 19 | I11: 21.64 | K11: 19634.9 | M11: 0.8 | N11: 1.71
A12: Edelweiss Small Cap Fund - Dir - Growth | B12: 0.45 | C12: 2.81 | D12: 9.26 | E12: 13.12 | F12: 13.78 | G12: 18.36 | H12: 18.91 | I12: 25.18 | K12: 6579.72 | M12: 0.47 | N12: 1.83
A13: Franklin India Small Cap Fund - Dir - Growth | B13: 0.15 | C13: 1.24 | D13: 6.89 | E13: 11.23 | F13: 10.03 | G13: 15.78 | H13: 17.84 | I13: 20.01 | K13: 14336.42 | M13: 0.96 | N13: 1.78
A14: Groww Small Cap Fund - Dir - Growth | B14: 1.33 | C14: 4.86 | D14: 15.57 | E14: 24.07 | F14: -- | G14: -- | H14: -- | I14: 25.64 | K14: 439.7 | M14: 0.52 | N14: 2.32
A15: HDFC Small Cap Fund - Dir - Growth | B15: -0.85 | C15: 1.68 | D15: 7.52 | E15: 5.27 | F15: 2.84 | G15: 13.49 | H15: 16.29 | I15: 18.59 | K15: 40416.8 | M15: 0.8 | N15: 1.57
A16: Helios Small Cap Fund - Dir - Growth | B16: 0.61 | C16: 3.51 | D16: 14.31 | E16: 22.09 | F16: -- | G16: -- | H16: -- | I16: 15 | K16: 1242.7 | M16: 0.7 | N16: 2.31
A17: HSBC Small Cap Fund - Dir - Growth | B17: 0.86 | C17: 3.53 | D17: 10.36 | E17: 18.42 | F17: 15.1 | G17: 17.07 | H17: 18.89 | I17: 20.73 | K17: 17830.2 | M17: 0.77 | N17: 1.72
A18: ICICI Prudential Smallcap Fund - Dir - Growth | B18: 0.14 | C18: 3.74 | D18: 8.32 | E18: 9.21 | F18: 7.31 | G18: 13.8 | H18: 15.62 | I18: 16.97 | K18: 9378.8 | M18: 0.81 | N18: 1.82
A19: Invesco India Smallcap Fund - Dir - Growth | B19: -0.18 | C19: 2.74 | D19: 13.53 | E19: 16.45 | F19: 17.53 | G19: 24.87 | H19: 21.06 | I19: 24.17 | K19: 13384.88 | M19: 0.52 | N19: 1.73
A20: ITI Small Cap Fund - Dir - Growth | B20: 1.06 | C20: 3.86 | D20: 14.1 | E20: 24.94 | F20: 22.24 | G20: 26.83 | H20: 19.39 | I20: 22.86 | K20: 3321.83 | M20: 0.39 | N20: 1.88
A21: JM Small Cap Fund - Dir - Growth | B21: 0.66 | C21: 2 | D21: 13.88 | E21: 23.72 | F21: 22.11 | G21: -- | H21: -- | I21: 8.73 | K21: 809.39 | M21: 0.79 | N21: 2.37
A22: Kotak Small Cap Fund - Dir - Growth | B22: 0.4 | C22: 3 | D22: 9.23 | E22: 12.94 | F22: 9 | G22: 14.27 | H22: 14.61 | I22: 19.07 | K22: 18690.79 | M22: 0.55 | N22: 1.68
A23: LIC MF Small Cap Fund - Dir - Growth | B23: 1.14 | C23: 3.81 | D23: 12 | E23: 21.43 | F23: 20.87 | G23: 20.49 | H23: 19.38 | I23: 16.17 | K23: 743.33 | M23: 1.05 | N23: 2.41
A24: Mahindra Manulife Small Cap Fund - Dir - Growth | B24: 0.85 | C24: 3.66 | D24: 12.26 | E24: 19.56 | F24: 19.56 | G24: 22.53 | H24: -- | I24: 26.14 | K24: 4930.36 | M24: 0.53 | N24: 1.86
A25: Mirae Asset Small Cap Fund - Dir - Growth | B25: -0.3 | C25: 2.6 | D25: 8.99 | E25: 11.11 | F25: 13.2 | G25: -- | H25: -- | I25: 17.24 | K25: 4842.22 | M25: 0.3 | N25: 1.85
A26: Motilal Oswal Small Cap Fund - Dir - Growth | B26: -0.17 | C26: 3.84 | D26: 16.23 | E26: 24.89 | F26: 25.64 | G26: -- | H26: -- | I26: 23.68 | K26: 7179.39 | M26: 0.81 | N26: 1.86
A27: Nippon India Small Cap Fund - Dir - Growth | B27: 0.44 | C27: 2.67 | D27: 8.12 | E27: 14.17 | F27: 12.85 | G27: 17.78 | H27: 20.23 | I27: 24.22 | K27: 78407.03 | M27: 0.67 | N27: 1.42
A28: PGIM India Small Cap Fund - Dir - Growth | B28: 1.11 | C28: 5.47 | D28: 12.77 | E28: 19.46 | F28: 15.84 | G28: 18.04 | H28: 14.9 | I28: 14.77 | K28: 1649.96 | M28: 0.61 | N28: 2.11
A29: Quant Small Cap Fund - Dir - Growth | B29: -0.72 | C29: -0.27 | D29: 9.2 | E29: 19.01 | F29: 15.77 | G29: 18.9 | H29: 19.82 | I29: 17.7 | K29: 33739.04 | M29: 0.83 | N29: 1.66
A30: Quantum Small Cap Fund - Dir - Growth | B30: 0.14 | C30: 1.86 | D30: 10.88 | E30: 10.65 | F30: 13.16 | G30: -- | H30: -- | I30: 13.64 | K30: 242.6 | M30: 0.7 | N30: 2.17
A31: Samco Small Cap Fund - Dir - Growth | B31: 1.04 | C31: 8.26 | D31: 13.19 | E31: 19.1 | F31: -- | G31: -- | H31: -- | I31: 16.7 | K31: 158.97 | M31: 0.85 | N31: 2.4
A32: SBI Small Cap Fund - Dir - Growth | B32: 1.1 | C32: 3.38 | D32: 12.88 | E32: 14.42 | F32: 10.85 | G32: 13.82 | H32: 15.75 | I32: 22.94 | K32: 40156.66 | M32: 0.79 | N32: 1.6
A33: Sundaram Small Cap Fund - Dir - Growth | B33: 0.2 | C33: 2.6 | D33: 8.93 | E33: 16.73 | F33: 19.66 | G33: 19.43 | H33: 18.21 | I33: 18.11 | K33: 3871.8 | M33: 0.86 | N33: 1.97
A34: Tata Small Cap Fund - Dir - Growth | B34: -0.27 | C34: 1.89 | D34: 11.16 | E34: 11.9 | F34: 0.65 | G34: 13.37 | H34: 15.47 | I34: 21.2 | K34: 12528.86 | M34: 0.4 | N34: 1.68
A35: The Wealth Company Small Cap Fund - Dir - Growth | B35: 0.04 | C35: 3.07 | D35: 9.41 | E35: -- | F35: -- | G35: -- | H35: -- | I35: 18.17 | K35: 87.8 | M35: 0.35 | N35: 2.1
A36: TRUSTMF Small Cap Fund - Dir - Growth | B36: 0.96 | C36: 3.48 | D36: 14.96 | E36: 27.58 | F36: 33.99 | G36: -- | H36: -- | I36: 19.3 | K36: 2476.03 | M36: 0.47 | N36: 2.08
A37: Union Small Cap Fund - Dir - Growth | B37: 1.49 | C37: 4.91 | D37: 12.51 | E37: 22.95 | F37: 26.23 | G37: 19.88 | H37: 18.64 | I37: 16.88 | K37: 2267.79 | M37: 1.08 | N37: 2.15
A38: UTI Small Cap Fund - Dir - Growth | B38: 0.69 | C38: 1.79 | D38: 8.15 | E38: 14.34 | F38: 10.14 | G38: 16.89 | H38: 17.01 | I38: 21.68 | K38: 5213.42 | M38: 0.65 | N38: 1.86
A39: Median | B39: =MEDIAN(B3:B38) -> 0.485 | C39: =MEDIAN(C3:C38) -> 3.095 | D39: =MEDIAN(D3:D38) -> 11.58 | E39: =MEDIAN(E3:E38) -> 17.29 | F39: =MEDIAN(F3:F38) -> 15.1 | G39: =MEDIAN(G3:G38) -> 17.91 | H39: =MEDIAN(H3:H38) -> 18.21 | I39: =MEDIAN(I3:I38) -> 19.655
A40: Index | B40: -- | C40: -- | D40: -- | E40: -- | F40: -- | G40: -- | H40: -- | I40: --
A41: Nifty Smallcap 250 | B41: -0.42 | C41: 1.69 | D41: 8.87 | E41: 14.25 | F41: 9.74 | G41: 17.36 | H41: 15.56
A42: Nifty Smallcap 250 TRI | B42: -0.39 | C42: 1.87 | D42: 9.2 | E42: 14.64 | F42: 10.37 | G42: 18.08 | H42: 16.41

Sheet Mid Cap
A1: ='Small Cap'!A1 -> ( As on 14-08-26 ) | M1: 46082
A2: Scheme Name | B2: 1 Week | C2: 1 Month | D2: 3 Months | E2: 6 Months | F2: 1 Year | G2: 3 Years | H2: 5 Years | I2: Since Inception | K2: AUM ( June 26) | M2: Direct | N2: Regular
A3: Aditya Birla Sun Life Mid Cap Fund - Plan A - Dir - Growth | B3: 0.66 | C3: 3.35 | D3: 8.15 | E3: 9.76 | F3: 12.43 | G3: 18.33 | H3: 15.97 | I3: 16.58 | K3: 6624.16 | M3: 1.02 | N3: 1.87
A4: Axis Midcap Fund - Dir - Growth | B4: 0.22 | C4: 2.35 | D4: 6.75 | E4: 9.12 | F4: 10.47 | G4: 18.64 | H4: 15.11 | I4: 18.85 | K4: 33803 | M4: 0.54 | N4: 1.58
A5: Bandhan Midcap Fund - Dir - Growth | B5: 0.94 | C5: 3.65 | D5: 9.84 | E5: 13.29 | F5: 13.52 | G5: 20.62 | H5: -- | I5: 19.7 | K5: 2324.7 | M5: 0.67 | N5: 2.07
A6: Bank of India Mid Cap Fund - Dir - Growth | B6: 1.52 | C6: 2.6 | D6: 3.7 | E6: 11.56 | F6: -- | G6: -- | H6: -- | I6: 6.6 | K6: 725.07 | M6: 1.12 | N6: 2.23
A7: Baroda BNP Paribas Midcap Fund - Dir - Growth | B7: 0.31 | C7: 1.71 | D7: 5.47 | E7: 8.58 | F7: 16.33 | G7: 19.72 | H7: 17.01 | I7: 19.24 | K7: 2513.23 | M7: 0.54 | N7: 1.98
A8: Canara Robeco Mid Cap Fund - Dir - Growth | B8: 0.51 | C8: 1.93 | D8: 7.42 | E8: 9.91 | F8: 9.65 | G8: 19.41 | H8: -- | I8: 19.84 | K8: 4835.69 | M8: 0.65 | N8: 1.89
A9: DSP Midcap Fund - Dir - Growth | B9: -0.02 | C9: 2.11 | D9: 6.07 | E9: 6.04 | F9: 10.26 | G9: 17.07 | H9: 13.47 | I9: 17.17 | K9: 20170.28 | M9: 0.74 | N9: 1.68
A10: Edelweiss Mid Cap Fund - Dir - Growth | B10: 0.46 | C10: 2.33 | D10: 5.56 | E10: 7.62 | F10: 12.16 | G10: 23.86 | H10: 20.11 | I10: 21.49 | K10: 17748.32 | M10: 0.49 | N10: 1.68
A11: Franklin India Mid Cap Fund - Dir - Growth | B11: -0.06 | C11: 2.53 | D11: 8.3 | E11: 5.41 | F11: 7.71 | G11: 18.73 | H11: 15.84 | I11: 18.23 | K11: 12489.74 | M11: 1.02 | N11: 1.8
A12: HDFC Mid Cap Fund - Dir - Growth | B12: -0.15 | C12: 2.77 | D12: 7.99 | E12: 5.73 | F12: 12.23 | G12: 20.36 | H12: 20.83 | I12: 20.42 | K12: 100858.31 | M12: 0.77 | N12: 1.37
A13: Helios Mid Cap Fund - Dir - Growth | B13: 0 | C13: 1.43 | D13: 9.1 | E13: 14.6 | F13: 17.74 | G13: -- | H13: -- | I13: 27.59 | K13: 1793.33 | M13: 0.58 | N13: 2.11
A14: HSBC Midcap Fund - Dir - Growth | B14: 0.45 | C14: 3.86 | D14: 9.34 | E14: 17.6 | F14: 23.02 | G14: 26.21 | H14: 20.03 | I14: 20.38 | K14: 15351.91 | M14: 0.66 | N14: 1.73
A15: ICICI Prudential MidCap Fund - Dir - Growth | B15: 0.67 | C15: 3 | D15: 3.29 | E15: 8.99 | F15: 19.11 | G15: 24.37 | H15: 18.94 | I15: 19.61 | K15: 7845.63 | M15: 1.05 | N15: 1.87
A16: Invesco India Midcap Fund - Dir - Growth | B16: -0.5 | C16: 0.81 | D16: 9.6 | E16: 10.62 | F16: 12.18 | G16: 25.97 | H16: 21.11 | I16: 21.2 | K16: 13766.86 | M16: 0.55 | N16: 1.72
A17: ITI Mid Cap Fund - Dir - Growth | B17: 0.16 | C17: 3.25 | D17: 7.24 | E17: 9.59 | F17: 16.5 | G17: 23.33 | H17: 17.72 | I17: 19.35 | K17: 1445.6 | M17: 0.28 | N17: 2.02
A18: JM Midcap Fund - Dir - Growth | B18: 0.33 | C18: 3.51 | D18: 9.73 | E18: 16.36 | F18: 15.05 | G18: 21.67 | H18: -- | I18: 24.74 | K18: 1274.52 | M18: 0.75 | N18: 2.21
A19: Kotak Midcap Fund - Dir - Growth | B19: -0.18 | C19: 0.91 | D19: 6.9 | E19: 8.69 | F19: 10.42 | G19: 20.12 | H19: 18.31 | I19: 20.29 | K19: 67611 | M19: 0.38 | N19: 1.4
A20: LIC MF Mid cap Fund - Dir - Growth | B20: 1.49 | C20: 3.38 | D20: 8.31 | E20: 10.51 | F20: 11.68 | G20: 19.05 | H20: 14.8 | I20: 14.19 | K20: 368.57 | M20: 1.44 | N20: 2.5
A21: Mahindra Manulife Mid Cap Fund - Dir - Growth | B21: 0.5 | C21: 2.52 | D21: 7.48 | E21: 11.38 | F21: 17.85 | G21: 22.4 | H21: 19.89 | I21: 18.56 | K21: 5075.66 | M21: 0.46 | N21: 1.85
A22: Mirae Asset Midcap Fund - Dir - Growth | B22: 0.17 | C22: 1.75 | D22: 8.02 | E22: 9.61 | F22: 15.43 | G22: 18.74 | H22: 17.09 | I22: 23.54 | K22: 19542.56 | M22: 0.58 | N22: 1.67
A23: Motilal Oswal Midcap Fund - Dir - Growth | B23: 1.69 | C23: 5.37 | D23: 14.72 | E23: 12.95 | F23: 3.17 | G23: 21.69 | H23: 23.43 | I23: 22.06 | K23: 37473.87 | M23: 0.85 | N23: 1.6
A24: Nippon India Growth Mid Cap Fund - Dir - Growth | B24: 0.28 | C24: 1.91 | D24: 5.4 | E24: 6.79 | F24: 12.62 | G24: 21.75 | H24: 20.28 | I24: 18.5 | K24: 49169.1 | M24: 0.78 | N24: 1.55
A25: PGIM India Midcap Fund - Dir - Growth | B25: 0.58 | C25: 2.48 | D25: 6.89 | E25: 7.03 | F25: 4.52 | G25: 13.77 | H25: 12.71 | I25: 17.62 | K25: 10981.47 | M25: 0.52 | N25: 1.73
A26: Quant Mid Cap Fund - Dir - Growth | B26: -1.45 | C26: -0.15 | D26: 3.59 | E26: 13.27 | F26: 7.16 | G26: 14.19 | H26: 17.36 | I26: 16.77 | K26: 8138.18 | M26: 0.85 | N26: 1.84
A27: Samco Mid Cap Fund - Dir - Growth | B27: 0.3 | C27: 1.41 | D27: 2.33 | E27: 3.15 | F27: -- | G27: -- | H27: -- | I27: 3.17 | K27: 78.64 | M27: 0.89 | N27: 2.41
A28: SBI Midcap Fund - Dir - Growth | B28: -0.13 | C28: 0.55 | D28: 4.14 | E28: 5.17 | F28: 9.56 | G28: 13.97 | H28: 15.28 | I28: 18.34 | K28: 24126.69 | M28: 0.86 | N28: 1.68
A29: Sundaram Mid Cap Fund - Dir - Growth | B29: 0.04 | C29: 2.83 | D29: 7.64 | E29: 7.76 | F29: 12.7 | G29: 21.94 | H29: 19.11 | I29: 18.14 | K29: 14026.07 | M29: 0.86 | N29: 1.73
A30: Tata Mid Cap Fund - Dir - Growth | B30: 0.82 | C30: 1.56 | D30: 5.76 | E30: 6.53 | F30: 12.48 | G30: 17.73 | H30: 16.68 | I30: 19.23 | K30: 5868.39 | M30: 0.68 | N30: 1.87
A31: Taurus Mid Cap Fund - Dir - Growth | B31: -1.21 | C31: 6.73 | D31: 10.31 | E31: 10.62 | F31: 8.97 | G31: 12.04 | H31: 13.28 | I31: 16.14 | K31: 125.16 | M31: 2.15 | N31: 2.58
A32: TRUSTMF Mid Cap Fund - Dir - Growth | B32: 1.4 | C32: 4.13 | D32: 12.27 | E32: -- | F32: -- | G32: -- | H32: -- | I32: 23.5 | K32: 312.27 | M32: 0.45 | N32: 2.3
A33: Union Midcap Fund - Dir - Growth | B33: 1.1 | C33: 3.16 | D33: 8.34 | E33: 11.03 | F33: 15.17 | G33: 19.83 | H33: 17.26 | I33: 31.65 | K33: 1846.92 | M33: 0.83 | N33: 2.13
A34: UTI Mid Cap Fund - Dir - Growth | B34: 1.42 | C34: 4.05 | D34: 7.8 | E34: 8.34 | F34: 9.26 | G34: 14.56 | H34: 14.09 | I34: 18.35 | K34: 12122.33 | M34: 0.93 | N34: 1.77
A35: WhiteOak Capital Mid Cap Fund - Dir - Growth | B35: 0.85 | C35: 2.49 | D35: 9.72 | E35: 14.93 | F35: 18.51 | G35: 24.45 | H35: -- | I35: 24.4 | K35: 6171.27 | M35: 0.64 | N35: 1.87
A36: Median | B36: =MEDIAN(B3:B35) -> 0.33 | C36: =MEDIAN(C3:C35) -> 2.52 | D36: =MEDIAN(D3:D35) -> 7.64 | E36: =MEDIAN(E3:E35) -> 9.6 | F36: =MEDIAN(F3:F35) -> 12.33 | G36: =MEDIAN(G3:G35) -> 19.83 | H36: =MEDIAN(H3:H35) -> 17.26 | I36: =MEDIAN(I3:I35) -> 19.24
A37: Index | B37: -- | C37: -- | D37: -- | E37: -- | F37: -- | G37: -- | H37: -- | I37: --
A38: Nifty Midcap 150 | B38: 0.24 | C38: 1.59 | D38: 4.75 | E38: 6.98 | F38: 11.43 | G38: 18.26 | H38: 17.54
A39: Nifty Midcap 150 TRI | B39: 0.26 | C39: 1.73 | D39: 5.04 | E39: 7.34 | F39: 12.12 | G39: 18.95 | H39: 18.36

Sheet Flexi Cap
A1: ='Small Cap'!A1 -> ( As on 14-08-26 ) | M1: 46082
A2: Scheme Name | B2: 1 Week | C2: 1 Month | D2: 3 Months | E2: 6 Months | F2: 1 Year | G2: 3 Years | H2: 5 Years | I2: Since Inception | K2: AUM ( June 26) | M2: Direct | N2: Regular
A3: 360 ONE Flexicap Fund - Dir - Growth | B3: -0.19 | C3: 4.1 | D3: 11.93 | E3: 10.64 | F3: 12.67 | G3: 19.67 | H3: -- | I3: 19 | K3: 2118.85 | M3: 0.48 | N3: 1.99
A4: Abakkus Flexi Cap Fund - Dir - Growth | B4: 0.28 | C4: 3.25 | D4: 10.87 | E4: 12.63 | F4: -- | G4: -- | H4: -- | I4: 13.39 | K4: 5300.95 | M4: 0.49 | N4: 1.89
A5: Aditya Birla Sun Life Flexi Cap Fund - Dir - Growth | B5: -0.38 | C5: 3.75 | D5: 8.31 | E5: 6.37 | F5: 12.94 | G5: 17.25 | H5: 13.34 | I5: 16.49 | K5: 26726.75 | M5: 0.85 | N5: 1.65
A6: Axis Flexi Cap Fund - Dir - Growth | B6: 0.38 | C6: 4.56 | D6: 11.3 | E6: 8.2 | F6: 8.76 | G6: 15.79 | H6: 10.86 | I6: 14.2 | K6: 13327.81 | M6: 0.7 | N6: 1.73
A7: Bajaj Finserv Flexi Cap Fund - Dir - Growth | B7: -0.57 | C7: 2.72 | D7: 8.17 | E7: 7.12 | F7: 11.25 | G7: 18.16 | H7: -- | I7: 18.16 | K7: 7768.94 | M7: 0.55 | N7: 1.79
A8: Bandhan Flexi Cap Fund - Dir - Growth | B8: -0.59 | C8: 1.61 | D8: 4.85 | E8: 1.21 | F8: 3.88 | G8: 13.51 | H8: 11.52 | I8: 13.78 | K8: 7417.4 | M8: 1.15 | N8: 1.89
A9: Bank of India Flexi Cap Fund - Dir - Growth | B9: 0.19 | C9: 3.43 | D9: 7.72 | E9: 11.58 | F9: 17.21 | G9: 22.19 | H9: 18.01 | I9: 26.66 | K9: 2615.05 | M9: 0.52 | N9: 1.92
A10: Baroda BNP Paribas Flexi Cap Fund - Dir - Growth | B10: 0 | C10: 3.12 | D10: 6.56 | E10: 4.91 | F10: 7.43 | G10: 14.85 | H10: -- | I10: 14.53 | K10: 1239.4 | M10: 1.02 | N10: 2.19
A11: Canara Robeco Flexi Cap Fund - Dir - Growth | B11: -0.09 | C11: 2.6 | D11: 6.36 | E11: 1.93 | F11: 3.83 | G11: 13.81 | H11: 11.52 | I11: 14.25 | K11: 13327.72 | M11: 0.57 | N11: 1.71
A12: Capitalmind Flexi Cap Fund - Dir - Growth | B12: -0.41 | C12: 2.33 | D12: 2.99 | E12: 1.49 | F12: 4.78 | G12: -- | H12: -- | I12: 3.49 | K12: 443.6 | M12: 0.94 | N12: 2.34
A13: DSP Flexi Cap Fund - Dir - Growth | B13: -0.47 | C13: 1.57 | D13: 6.86 | E13: 1.6 | F13: 6.39 | G13: 13.91 | H13: 11.42 | I13: 14.78 | K13: 12235.93 | M13: 0.7 | N13: 1.74
A14: Edelweiss Flexi Cap Fund - Dir - Growth | B14: -0.18 | C14: 3.06 | D14: 5.1 | E14: 1.89 | F14: 7.54 | G14: 16.76 | H14: 14.51 | I14: 14.26 | K14: 3483.69 | M14: 0.46 | N14: 1.91
A15: Franklin India Flexi Cap Fund - Dir - Growth | B15: -0.4 | C15: 1.68 | D15: 5.6 | E15: -0.63 | F15: 1.47 | G15: 13.72 | H15: 13.72 | I15: 15.59 | K15: 19274.14 | M15: 0.91 | N15: 1.71
A16: HDFC Flexi Cap Fund - Dir - Growth | B16: -0.24 | C16: 2.87 | D16: 7.54 | E16: 0.71 | F16: 6.29 | G16: 17.73 | H16: 18.64 | I16: 16.18 | K16: 106495.63 | M16: 0.68 | N16: 1.35
A17: Helios Flexi Cap Fund - Dir - Growth | B17: 0.49 | C17: 0.74 | D17: 7.39 | E17: 6.93 | F17: 10.91 | G17: -- | H17: -- | I17: 19.34 | K17: 7577.33 | M17: 0.51 | N17: 1.78
A18: HSBC Flexi Cap Fund - Dir - Growth | B18: 0.45 | C18: 4.67 | D18: 7.83 | E18: 8.57 | F18: 9.94 | G18: 17.8 | H18: 14.65 | I18: 15.27 | K18: 5633.43 | M18: 1.22 | N18: 1.95
A19: ICICI Prudential Flexicap Fund - Dir - Growth | B19: -0.36 | C19: 6.6 | D19: 12.91 | E19: 7.84 | F19: 15.48 | G19: 19.17 | H19: 16.78 | I19: 17.1 | K19: 22506.87 | M19: 0.8 | N19: 1.69
A20: Invesco India Flexi Cap Fund - Dir - Growth | B20: 0.66 | C20: 3.06 | D20: 11.39 | E20: 9.49 | F20: 6.1 | G20: 20.39 | H20: -- | I20: 18.22 | K20: 5273.59 | M20: 0.53 | N20: 1.85
A21: ITI Flexi Cap Fund - Dir - Growth | B21: 0.35 | C21: 3.27 | D21: 11.48 | E21: 11.47 | F21: 16.08 | G21: 20.33 | H21: -- | I21: 24.08 | K21: 1412.22 | M21: 0.36 | N21: 2
A22: JioBlackRock Flexi Cap Fund - Dir - Growth | B22: -0.48 | C22: 2.09 | D22: 5.11 | E22: -0.04 | F22: -- | G22: -- | H22: -- | I22: 1.56 | K22: 3211.24 | M22: 0.5 | N22: 1.85
A23: JM Flexicap Fund - Dir - Growth | B23: 0.53 | C23: 4.37 | D23: 8.66 | E23: 8.35 | F23: 7.77 | G23: 17.26 | H23: 17.7 | I23: 17.05 | K23: 5177.87 | M23: 0.68 | N23: 1.86
A24: Kotak Flexicap Fund - Dir - Growth | B24: -0.23 | C24: 1.6 | D24: 4.15 | E24: -1.36 | F24: 4.05 | G24: 14.02 | H24: 12.33 | I24: 15.76 | K24: 55850.29 | M24: 0.59 | N24: 1.46
A25: LIC MF Flexi Cap Fund - Dir - Growth | B25: 0.99 | C25: 5.2 | D25: 14.95 | E25: 11.24 | F25: 15.04 | G25: 14.51 | H25: 11.97 | I25: 11.54 | K25: 1052.66 | M25: 1.65 | N25: 2.39
A26: Mahindra Manulife Flexi Cap Fund - Dir - Growth | B26: 0.37 | C26: 2.61 | D26: 5.29 | E26: 0.24 | F26: 3.74 | G26: 12.66 | H26: -- | I26: 12.15 | K26: 1559.38 | M26: 0.56 | N26: 2.09
A27: Mirae Asset Flexi Cap Fund - Dir - Growth | B27: -0.07 | C27: 1.43 | D27: 4.75 | E27: 1.99 | F27: 6.69 | G27: 13.97 | H27: -- | I27: 16.85 | K27: 4262.03 | M27: 0.51 | N27: 1.9
A28: Motilal Oswal Flexi Cap Fund - Dir - Growth | B28: -0.03 | C28: 6.13 | D28: 14.69 | E28: 10 | F28: 5.69 | G28: 21.03 | H28: 13.45 | I28: 17.28 | K28: 13294.42 | M28: 0.82 | N28: 1.72
A29: Navi Flexi Cap Fund - Dir - Growth | B29: -0.06 | C29: 3.29 | D29: 9.79 | E29: 8.62 | F29: 16.28 | G29: 13.56 | H29: 13.13 | I29: 14.35 | K29: 280.7 | M29: 0.53 | N29: 2.2
A30: Nippon India Flexi Cap Fund - Dir - Growth | B30: -0.15 | C30: 2.2 | D30: 6.67 | E30: 3.54 | F30: 5.18 | G30: 12.84 | H30: 12.72 | I30: 12.72 | K30: 9590.17 | M30: 0.46 | N30: 1.74
A31: NJ Flexi Cap Fund - Dir - Growth | B31: -0.14 | C31: 3.03 | D31: 5.44 | E31: 3.01 | F31: 1.75 | G31: -- | H31: -- | I31: 12.01 | K31: 2591.73 | M31: 0.53 | N31: 1.99
A32: Parag Parikh Flexi Cap Fund - Dir - Growth | B32: -0.7 | C32: 0.9 | D32: 1.46 | E32: -0.41 | F32: -0.6 | G32: 14.52 | H32: 13.43 | I32: 18.23 | K32: 143388.43 | M32: 0.62 | N32: 1.27
A33: PGIM India Flexi Cap Fund - Dir - Growth | B33: 0.18 | C33: 3.26 | D33: 7.07 | E33: 4.45 | F33: 5.09 | G33: 12.27 | H33: 9.63 | I33: 13.9 | K33: 5817.78 | M33: 0.49 | N33: 1.82
A34: Quant Flexi Cap Fund - Dir - Growth | B34: -0.13 | C34: 1.09 | D34: 6.66 | E34: 14.98 | F34: 19.05 | G34: 18 | H34: 16.48 | I34: 18.78 | K34: 7140.12 | M34: 0.74 | N34: 1.86
A35: Samco Flexi Cap Fund-Dir-Growth | B35: 1.14 | C35: 2.9 | D35: 1.43 | E35: 3.08 | F35: -0.37 | G35: -0.53 | H35: -- | I35: 1.4 | K35: 281.9 | M35: 0.91 | N35: 2.41
A36: SBI Flexicap Fund - Dir - Growth | B36: -0.32 | C36: 1.95 | D36: 4.17 | E36: -0.5 | F36: 3.2 | G36: 10.15 | H36: 9.47 | I36: 14.72 | K36: 22685.08 | M36: 0.86 | N36: 1.68
A37: Shriram Flexi Cap Fund - Dir - Growth | B37: -0.82 | C37: 1.36 | D37: 5.17 | E37: 0.82 | F37: 2.78 | G37: 10.11 | H37: 9.45 | I37: 11.19 | K37: 132.5 | M37: 0.46 | N37: 2.35
A38: Sundaram Flexicap Fund - Dir - Growth | B38: -0.65 | C38: 1.8 | D38: 4.12 | E38: -1.92 | F38: 0.26 | G38: 11.3 | H38: -- | I38: 11.75 | K38: 1990.15 | M38: 0.75 | N38: 2.06
A39: Tata Flexi Cap Fund - Dir - Growth | B39: -0.9 | C39: 0.63 | D39: 2.27 | E39: -1.2 | F39: 1.53 | G39: 12.19 | H39: 10.84 | I39: 13.25 | K39: 3638.77 | M39: 0.59 | N39: 1.86
A40: Taurus Flexi Cap Fund - Dir - Growth | B40: -1.53 | C40: 4.16 | D40: 8.69 | E40: 7.62 | F40: 7.51 | G40: 12.81 | H40: 10.77 | I40: 10.4 | K40: 348.79 | M40: 2.63 | N40: 2.67
A41: The Wealth Company Flexi Cap Fund - Dir - Growth | B41: -0.22 | C41: 0.95 | D41: 2.4 | E41: 2.18 | F41: -- | G41: -- | H41: -- | I41: 2.13 | K41: 240.53 | M41: 0.39 | N41: 2.34
A42: TRUSTMF Flexi Cap Fund - Dir - Growth | B42: 0.94 | C42: 6.09 | D42: 11.8 | E42: 9.93 | F42: 13.17 | G42: -- | H42: -- | I42: 11.66 | K42: 976.22 | M42: 0.49 | N42: 2.11
A43: Unifi Flexi Cap Fund - Dir - Growth | B43: 0.42 | C43: 2.16 | D43: 7.33 | E43: 5.8 | F43: 7.99 | G43: -- | H43: -- | I43: 6.94 | K43: 199.92 | M43: 1.08 | N43: 2.38
A44: Union Flexi Cap Fund - Dir - Growth | B44: 0.75 | C44: 3.21 | D44: 7.87 | E44: 4.62 | F44: 7.47 | G44: 13.41 | H44: 12.15 | I44: 13.36 | K44: 2375.89 | M44: 1 | N44: 2.09
A45: UTI Flexi Cap Fund - Dir - Growth | B45: 1.06 | C45: 5.81 | D45: 13.4 | E45: 8.22 | F45: 4.87 | G45: 10.41 | H45: 7.06 | I45: 13.64 | K45: 22881.63 | M45: 1.05 | N45: 1.68
A46: WhiteOak Capital Flexi Cap Fund - Dir - Growth | B46: 0.21 | C46: 2.66 | D46: 8.82 | E46: 6.8 | F46: 8.77 | G46: 17.06 | H46: -- | I46: 17.92 | K46: 8582.39 | M46: 0.62 | N46: 1.79
A47: Median | B47: =MEDIAN(B3:B46) -> -0.11 | C47: =MEDIAN(C3:C46) -> 2.885 | D47: =MEDIAN(D3:D46) -> 7.2 | E47: =MEDIAN(E3:E46) -> 4.765 | F47: =MEDIAN(F3:F46) -> 6.69 | G47: =MEDIAN(G3:G46) -> 14.265 | H47: =MEDIAN(H3:H46) -> 12.525 | I47: =MEDIAN(I3:I46) -> 14.305
A48: Index | B48: -- | C48: -- | D48: -- | E48: -- | F48: -- | G48: -- | H48: -- | I48: --
A49: Nifty 500 | B49: -0.49 | C49: 1.7 | D49: 4.34 | E49: 1.2 | F49: 4.03 | G49: 11.92 | H49: 10.89
A50: Nifty 500 TRI | B50: -0.48 | C50: 1.92 | D50: 4.93 | E50: 1.85 | F50: 4.99 | G50: 13 | H50: 12.02

Sheet Large Cap
A1: ='Small Cap'!A1 -> ( As on 14-08-26 ) | M1: 46082
A2: Scheme Name | B2: 1 Week | C2: 1 Month | D2: 3 Months | E2: 6 Months | F2: 1 Year | G2: 3 Years | H2: 5 Years | I2: Since Inception | K2: AUM ( June 26) | M2: Direct | N2: Regular
A3: Aditya Birla Sun Life Large Cap Fund - Dir - Growth | B3: -0.7 | C3: 2.59 | D3: 6.01 | E3: -0.93 | F3: 1.96 | G3: 11.79 | H3: 10.89 | I3: 13.85 | K3: 29029.31 | M3: 0.97 | N3: 1.63
A4: Axis Large Cap Fund - Dir - Growth | B4: -0.21 | C4: 3.12 | D4: 7.64 | E4: 0.18 | F4: 2.78 | G4: 11.23 | H4: 7.88 | I4: 13.81 | K4: 30912.59 | M4: 0.72 | N4: 1.6
A5: Bajaj Finserv Large Cap Fund - Dir - Growth | B5: -0.85 | C5: 2.82 | D5: 5.81 | E5: 0.7 | F5: 7.19 | G5: -- | H5: -- | I5: 2.85 | K5: 1606.7 | M5: 0.61 | N5: 2.11
A6: Bandhan Large Cap Fund - Dir - Growth | B6: -0.58 | C6: 2.34 | D6: 6.52 | E6: 1.42 | F6: 5.37 | G6: 14.63 | H6: 12.3 | I6: 13.14 | K6: 2060.88 | M6: 0.89 | N6: 2.05
A7: Bank of India Large Cap Fund - Dir - Growth | B7: 0.22 | C7: 1.97 | D7: 4.99 | E7: 2.08 | F7: 9.7 | G7: 15.16 | H7: 11.5 | I7: 12.25 | K7: 220.36 | M7: 0.87 | N7: 2.3
A8: Baroda BNP Paribas Large Cap Fund - Dir - Growth | B8: 0.5 | C8: 3.87 | D8: 5.43 | E8: 1.74 | F8: 5.46 | G8: 13.85 | H8: 12.48 | I8: 14.87 | K8: 2570.57 | M8: 0.82 | N8: 1.98
A9: Canara Robeco Large Cap Fund - Dir - Growth | B9: -0.37 | C9: 2.53 | D9: 5.67 | E9: -0.99 | F9: 1.59 | G9: 12.44 | H9: 10.83 | I9: 14.13 | K9: 16692.31 | M9: 0.57 | N9: 1.68
A10: DSP Large Cap Fund - Dir - Growth | B10: -0.56 | C10: 1.31 | D10: 2.92 | E10: -2.15 | F10: 0.24 | G10: 12.61 | H10: 10.85 | I10: 11.76 | K10: 7190.45 | M10: 0.86 | N10: 1.83
A11: Edelweiss Large Cap Fund - Dir- Growth | B11: -0.42 | C11: 2.41 | D11: 5.58 | E11: -0.91 | F11: 3.66 | G11: 12.12 | H11: 11.7 | I11: 14.11 | K11: 1434.27 | M11: 0.59 | N11: 2.12
A12: Franklin India Large Cap Fund - Dir - Growth | B12: -0.3 | C12: 3.05 | D12: 6.84 | E12: 0.07 | F12: 2.75 | G12: 11.85 | H12: 9.74 | I12: 12.3 | K12: 7255.73 | M12: 1.17 | N12: 1.88
A13: Groww Large Cap Fund - Dir- Growth | B13: -0.32 | C13: 2.12 | D13: 5.37 | E13: -0.54 | F13: 3.88 | G13: 13.06 | H13: 10.9 | I13: 12.45 | K13: 132.25 | M13: 1.26 | N13: 2.46
A14: HDFC Large Cap Fund - Dir - Growth | B14: -0.4 | C14: 1.45 | D14: 6.01 | E14: -1.59 | F14: 2.62 | G14: 11.33 | H14: 12.72 | I14: 13.25 | K14: 39023.69 | M14: 1.03 | N14: 1.61
A15: HSBC Large Cap Fund - Dir - Growth | B15: -0.52 | C15: 3.06 | D15: 6.78 | E15: -1.34 | F15: 4.33 | G15: 12.25 | H15: 10.86 | I15: 12.66 | K15: 1814.23 | M15: 1.29 | N15: 2.16
A16: ICICI Prudential Large Cap Fund - Dir - Growth | B16: -0.47 | C16: 1.43 | D16: 3.9 | E16: -2.49 | F16: 0.76 | G16: 13.15 | H16: 12.91 | I16: 14.77 | K16: 79420.74 | M16: 0.87 | N16: 1.42
A17: Invesco India Largecap Fund - Dir - Growth | B17: 0.17 | C17: 3.18 | D17: 9.41 | E17: 5.82 | F17: 9.2 | G17: 15.96 | H17: 13.05 | I17: 15.17 | K17: 1847.38 | M17: 0.72 | N17: 2.04
A18: ITI Large Cap Fund - Dir - Growth | B18: -0.43 | C18: 2.21 | D18: 5.88 | E18: 0.39 | F18: 3.32 | G18: 11.96 | H18: 10.54 | I18: 12.7 | K18: 370.31 | M18: 0.52 | N18: 2.36
A19: JioBlackRock Large Cap Fund - Dir - Growth | B19: -0.66 | C19: 2.18 | D19: 4.05 | E19: -- | F19: -- | G19: -- | H19: -- | I19: 1.59 | K19: 42
A20: JM Large Cap Fund - Dir - Growth | B20: 0.03 | C20: 3.23 | D20: 6.65 | E20: 0.95 | F20: 5.81 | G20: 13.24 | H20: 12.4 | I20: 12.59 | K20: 409.12 | M20: 0.93 | N20: 2.42
A21: Kotak Large Cap Fund - Dir - Growth | B21: -0.49 | C21: 2.17 | D21: 5.56 | E21: -1.54 | F21: 3 | G21: 12.53 | H21: 11.24 | I21: 14.09 | K21: 10772.29 | M21: 0.63 | N21: 1.74
A22: LIC MF Large Cap Fund - Dir - Growth | B22: -0.02 | C22: 3.23 | D22: 5.9 | E22: -1.65 | F22: -0.14 | G22: 9.86 | H22: 8.46 | I22: 12 | K22: 1362.49 | M22: 1.14 | N22: 2.2
A23: Mahindra Manulife Large Cap Fund - Dir - Growth | B23: -0.35 | C23: 2.36 | D23: 5.14 | E23: -2.91 | F23: 1.23 | G23: 11.32 | H23: 10.51 | I23: 13.6 | K23: 699.82 | M23: 0.78 | N23: 2.35
A24: Mirae Asset Large Cap Fund - Dir - Growth | B24: -0.41 | C24: 2.15 | D24: 6.47 | E24: -0.02 | F24: 3.18 | G24: 10.71 | H24: 9.88 | I24: 15.23 | K24: 38379.27 | M24: 0.58 | N24: 1.54
A25: Motilal Oswal Large Cap Fund - Dir - Growth | B25: -0.9 | C25: 0.73 | D25: 5.32 | E25: -0.3 | F25: 1.12 | G25: -- | H25: -- | I25: 14.86 | K25: 3189.13 | M25: 0.84 | N25: 1.97
A26: Nippon India Large Cap Fund - Dir - Growth | B26: -0.75 | C26: 1.45 | D26: 4.01 | E26: -1.75 | F26: 1.41 | G26: 13.29 | H26: 15.1 | I26: 15.41 | K26: 53227.04 | M26: 0.71 | N26: 1.5
A27: Parag Parikh Large Cap Fund - Dir - Growth | B27: -0.71 | C27: 2 | D27: 4.27 | E27: -1.4 | F27: -- | G27: -- | H27: -- | I27: -2.15 | K27: 767.23 | M27: 0.14 | N27: 0.48
A28: PGIM India Large Cap Fund - Dir - Growth | B28: -0.58 | C28: 2.13 | D28: 5.42 | E28: -0.39 | F28: 1.33 | G28: 9.22 | H28: 8.43 | I28: 12.88 | K28: 539.47 | M28: 0.86 | N28: 2.42
A29: Quant Large Cap Fund - Dir - Growth | B29: -0.09 | C29: 0.57 | D29: 8.04 | E29: 8.28 | F29: 11.22 | G29: 16.25 | H29: -- | I29: 14.38 | K29: 3388.27 | M29: 0.57 | N29: 1.96
A30: Samco Large Cap Fund - Dir - Growth | B30: -0.65 | C30: 0.33 | D30: -1.39 | E30: -1.17 | F30: -5.42 | G30: -- | H30: -- | I30: -5.53 | K30: 102.45 | M30: 0.74 | N30: 2.38
A31: SBI Large Cap Fund - Dir - Growth | B31: -0.66 | C31: 1.14 | D31: 4.21 | E31: -0.31 | F31: 4.35 | G31: 11.1 | H31: 10.95 | I31: 14.47 | K31: 55063.96 | M31: 0.84 | N31: 1.52
A32: Sundaram Large Cap Fund - Dir - Growth | B32: -0.49 | C32: 3.12 | D32: 6.3 | E32: -0.67 | F32: 2.49 | G32: 9.72 | H32: 9.87 | I32: 15.37 | K32: 3062.98 | M32: 0.73 | N32: 1.95
A33: Tata Large Cap Fund - Dir - Growth | B33: -0.45 | C33: 1.65 | D33: 5.54 | E33: 0.66 | F33: 6.94 | G33: 12.5 | H33: 11.38 | I33: 13.36 | K33: 2721.33 | M33: 1.02 | N33: 2.04
A34: Taurus Large Cap Fund - Dir - Growth | B34: -1.05 | C34: 5.01 | D34: 8.41 | E34: 4.95 | F34: 7.95 | G34: 14.34 | H34: 11.06 | I34: 10.72 | K34: 51.88 | M34: 2.32 | N34: 2.59
A35: Union Largecap Fund - Dir - Growth | B35: -0.12 | C35: 1.94 | D35: 4.61 | E35: -0.71 | F35: 1.98 | G35: 9.98 | H35: 9.33 | I35: 10.48 | K35: 436.67 | M35: 1.75 | N35: 2.56
A36: UTI Large Cap Fund - Dir - Growth | B36: -0.2 | C36: 2.33 | D36: 5.07 | E36: -2.11 | F36: 0.44 | G36: 9.59 | H36: 8.78 | I36: 12.75 | K36: 11975.72 | M36: 0.93 | N36: 1.76
A37: WhiteOak Capital Large Cap Fund - Dir - Growth | B37: -0.23 | C37: 2.22 | D37: 6.22 | E37: 0.95 | F37: 5.02 | G37: 15.47 | H37: -- | I37: 13.76 | K37: 1210.12 | M37: 0.7 | N37: 2.2
A38: Median | B38: =MEDIAN(B3:B37) -> -0.43 | C38: =MEDIAN(C3:C37) -> 2.21 | D38: =MEDIAN(D3:D37) -> 5.58 | E38: =MEDIAN(E3:E37) -> -0.465 | F38: =MEDIAN(F3:F37) -> 3 | G38: =MEDIAN(G3:G37) -> 12.345 | H38: =MEDIAN(H3:H37) -> 10.895 | I38: =MEDIAN(I3:I37) -> 13.25
A39: Index | B39: -- | C39: -- | D39: -- | E39: -- | F39: -- | G39: -- | H39: -- | I39: --
A40: Nifty 100 | B40: -0.73 | C40: 1.74 | D40: 3.53 | E40: -2.16 | F40: 1.18 | G40: 9.7 | H40: 8.82
A41: Nifty 50 | B41: -0.83 | C41: 1.31 | D41: 2.86 | E41: -4.31 | F41: -1.08 | G41: 7.82 | H41: 8.06

Sheet Contra Fund
A1: ='Small Cap'!A1 -> ( As on 14-08-26 ) | M1: 46174
A2: Scheme Name | B2: 1 Week | C2: 1 Month | D2: 3 Months | E2: 6 Months | F2: 1 Year | G2: 3 Years | H2: 5 Years | I2: Since Inception | K2: AUM ( June 26) | M2: Direct | N2: Regular
A3: Invesco India Contra Fund - Dir - Growth | B3: -0.24 | C3: 3.03 | D3: 8.09 | E3: 3.06 | F3: 3.68 | G3: 17.04 | H3: 14.6 | I3: 17.79 | K3: 19995.66 | M3: 0.48 | N3: 1.41
A4: Kotak Contra Fund - Dir - Growth | B4: -0.67 | C4: 1.79 | D4: 6.09 | E4: 0.53 | F4: 6.13 | G4: 17.81 | H4: 15.94 | I4: 16.42 | K4: 5331.37 | M4: 0.65 | N4: 1.88
A5: Motilal Oswal Contra Fund - Dir - Growth | B5: -0.02 | C5: 0.78 | D5: -- | E5: -- | F5: -- | G5: -- | H5: -- | I5: 5.55 | K5: 315.79 | M5: 0.69 | N5: 2.1
A6: SBI Contra Fund - Dir - Growth | B6: -0.53 | C6: 1.35 | D6: 3.05 | E6: -1.71 | F6: 2.25 | G6: 13.48 | H6: 16.85 | I6: 15.47 | K6: 47361.68 | M6: 0.85 | N6: 1.6
A7: Median | B7: =MEDIAN(B3:B6) -> -0.385 | C7: =MEDIAN(C3:C6) -> 1.57 | D7: =MEDIAN(D3:D6) -> 6.09 | E7: =MEDIAN(E3:E6) -> 0.53 | F7: =MEDIAN(F3:F6) -> 3.68 | G7: =MEDIAN(G3:G6) -> 17.04 | H7: =MEDIAN(H3:H6) -> 15.94 | I7: =MEDIAN(I3:I6) -> 15.945
A8: Index | B8: -- | C8: -- | D8: -- | E8: -- | F8: -- | G8: -- | H8: -- | I8: --
A9: Nifty 500 TRI | B9: -0.48 | C9: 1.92 | D9: 4.93 | E9: 1.85 | F9: 4.99 | G9: 13 | H9: 12.02

Sheet Dividend Yield Funds
A1: ='Small Cap'!A1 -> ( As on 14-08-26 ) | M1: 46082
A2: Scheme Name | B2: 1 Week | C2: 1 Month | D2: 3 Months | E2: 6 Months | F2: 1 Year | G2: 3 Years | H2: 5 Years | I2: Since Inception | K2: AUM ( June 26) | M2: Direct | N2: Regular
A3: Aditya Birla Sun Life Dividend Yield Fund - Dir - Growth | B3: -0.14 | C3: 3.72 | D3: 2.63 | E3: 1.87 | F3: 8.03 | G3: 15.21 | H3: 14.72 | I3: 13.16 | K3: 1436.81 | M3: 1.35 | N3: 2.2
A4: Baroda BNP Paribas Dividend Yield Fund (BBNPPDYF) - Dir - Growth | B4: -0.47 | C4: 3.25 | D4: 4.99 | E4: 2.58 | F4: 7.11 | G4: -- | H4: -- | I4: 0.83 | K4: 613.16 | M4: 1.14 | N4: 2.35
A5: Franklin India Dividend Yield Fund - Dir - Growth | B5: 0.17 | C5: 2.89 | D5: 2.3 | E5: -1 | F5: 3.75 | G5: 13.74 | H5: 13.77 | I5: 14.79 | K5: 2285.23 | M5: 1.28 | N5: 2.12
A6: HDFC Dividend Yield Fund - Dir - Growth | B6: -0.52 | C6: 2.21 | D6: 4.82 | E6: 2.33 | F6: 4.41 | G6: 13.71 | H6: 15.58 | I6: 19.36 | K6: 5655.56 | M6: 0.8 | N6: 1.86
A7: ICICI Prudential Dividend Yield Equity Fund - Dir - Growth | B7: -0.66 | C7: 0.67 | D7: 2.61 | E7: -1.15 | F7: 4.33 | G7: 18.45 | H7: 18.48 | I7: 15.82 | K7: 6629.59 | M7: 0.59 | N7: 1.82
A8: Kotak Dividend Yield Fund - Dir - Growth | B8: -0.58 | C8: 1.89 | D8: 4.23 | E8: -0.77 | F8: -- | G8: -- | H8: -- | I8: -0.79 | K8: 235.47 | M8: 0.92 | N8: 2.42
A9: LIC MF Dividend Yield Fund - Dir - Growth | B9: 0.64 | C9: 2.96 | D9: 7.95 | E9: 9.26 | F9: 12.58 | G9: 21.43 | H9: 16.99 | I9: 18.42 | K9: 718.28 | M9: 0.8 | N9: 2.36
A10: SBI Dividend Yield Fund - Dir - Growth | B10: -0.36 | C10: 3.38 | D10: 6.83 | E10: 2.9 | F10: 8.95 | G10: 13.46 | H10: -- | I10: 15.69 | K10: 8473.81 | M10: 0.85 | N10: 1.81
A11: Sundaram Dividend Yield Fund - Dir - Growth | B11: -0.52 | C11: 1.91 | D11: 1.62 | E11: -2.58 | F11: 1.79 | G11: 12.15 | H11: 11.11 | I11: 13.41 | K11: 819.54 | M11: 1.1 | N11: 2.31
A12: Tata Dividend Yield Fund - Dir - Growth | B12: 0.27 | C12: 2.9 | D12: 5.79 | E12: 8.46 | F12: 16.26 | G12: 17.05 | H12: 15.46 | I12: 16.23 | K12: 1097.65 | M12: 0.65 | N12: 2.22
A13: UTI Dividend Yield Fund - Dir - Growth | B13: -0.47 | C13: 1.59 | D13: 3.1 | E13: -0.91 | F13: 3.41 | G13: 15.16 | H13: 12.5 | I13: 13.45 | K13: 3749.04 | M13: 1.46 | N13: 2.03
A14: Median | B14: =MEDIAN(B3:B13) -> -0.47 | C14: =MEDIAN(C3:C13) -> 2.89 | D14: =MEDIAN(D3:D13) -> 4.23 | E14: =MEDIAN(E3:E13) -> 1.87 | F14: =MEDIAN(F3:F13) -> 5.76 | G14: =MEDIAN(G3:G13) -> 15.16 | H14: =MEDIAN(H3:H13) -> 15.09 | I14: =MEDIAN(I3:I13) -> 14.79
A15: Index | B15: -- | C15: -- | D15: -- | E15: -- | F15: -- | G15: -- | H15: -- | I15: --
A16: Nifty 500 | B16: -0.49 | C16: 1.7 | D16: 4.34 | E16: 1.2 | F16: 4.03 | G16: 11.92 | H16: 10.89
A17: Nifty 500 TRI | B17: -0.48 | C17: 1.92 | D17: 4.93 | E17: 1.85 | F17: 4.99 | G17: 13 | H17: 12.02

Sheet ELSS
A1: ='Small Cap'!A1 -> ( As on 14-08-26 ) | M1: 46082
A2: Scheme Name | B2: 1 Week | C2: 1 Month | D2: 3 Months | E2: 6 Months | F2: 1 Year | G2: 3 Years | H2: 5 Years | I2: Since Inception | K2: AUM ( June 26) | M2: Direct | N2: Regular
A3: Aditya Birla Sun Life ELSS Tax Saver Fund - Dir - Growth | B3: -0.44 | C3: 1.48 | D3: 5.84 | E3: 1.78 | F3: 5.11 | G3: 13.25 | H3: 9.64 | I3: 13.9 | K3: 14466.88 | M3: 0.96 | N3: 1.69
A4: Axis ELSS Tax Saver Fund - Dir - Growth | B4: -0.27 | C4: 3.18 | D4: 7.59 | E4: 2.86 | F4: 4.3 | G4: 13.15 | H4: 8.16 | I4: 15.99 | K4: 31869.32 | M4: 0.84 | N4: 1.57
A5: Bajaj Finserv ELSS Tax Saver Fund - Dir - Growth | B5: -1.09 | C5: 0.77 | D5: 3.63 | E5: 4.47 | F5: 8.76 | G5: -- | H5: -- | I5: 12.27 | K5: 87.4 | M5: 0.7 | N5: 2.35
A6: Bandhan ELSS Tax saver Fund - Dir - Growth | B6: -0.46 | C6: 2.09 | D6: 4.61 | E6: 1.21 | F6: 6.14 | G6: 11.71 | H6: 13.07 | I6: 16.66 | K6: 6911.29 | M6: 0.69 | N6: 1.78
A7: Bank of India ELSS Tax Saver - Dir - Growth | B7: -0.07 | C7: 2.2 | D7: 3.61 | E7: 4.85 | F7: 9.12 | G7: 15.05 | H7: 12.91 | I7: 16.94 | K7: 1406.09 | M7: 0.77 | N7: 1.97
A8: Baroda BNP Paribas ELSS Tax Saver Fund - Dir - Growth | B8: 0.2 | C8: 4.25 | D8: 8.12 | E8: 5.36 | F8: 10.34 | G8: 17.79 | H8: 13.59 | I8: 15.21 | K8: 896.55 | M8: 1.01 | N8: 2.23
A9: Canara Robeco ELSS Tax Saver - Dir - Growth | B9: -0.43 | C9: 2.16 | D9: 6.03 | E9: 2.4 | F9: 5.97 | G9: 13.75 | H9: 11.85 | I9: 15.14 | K9: 8636.82 | M9: 0.64 | N9: 1.73
A10: DSP ELSS Tax Saver Fund - Dir - Growth | B10: -0.75 | C10: 0.77 | D10: 4.34 | E10: -2.16 | F10: 3.8 | G10: 15.59 | H10: 13.32 | I10: 16.73 | K10: 16562.43 | M10: 0.7 | N10: 1.65
A11: Edelweiss ELSS Tax saver Fund - Dir- Growth | B11: -0.13 | C11: 3.21 | D11: 6.12 | E11: 4.58 | F11: 10.71 | G11: 15.82 | H11: 13.63 | I11: 14.8 | K11: 442.51 | M11: 0.67 | N11: 2.34
A12: Franklin India ELSS Tax Saver Fund - Dir - Growth | B12: -0.37 | C12: 1.56 | D12: 6.2 | E12: -0.77 | F12: 0.39 | G12: 13.38 | H12: 13.33 | I12: 15.01 | K12: 6166.26 | M12: 1.1 | N12: 1.86
A13: Groww ELSS Tax Savings Fund - Dir - Growth | B13: -0.54 | C13: 2.02 | D13: 4.27 | E13: -1.54 | F13: -1.94 | G13: 11.66 | H13: 10.27 | I13: 9.68 | K13: 50.59 | M13: 0.94 | N13: 2.39
A14: HDFC ELSS Taxsaver Fund - Dir - Growth | B14: -0.44 | C14: 2.13 | D14: 5.47 | E14: -2.77 | F14: 0.3 | G14: 15.41 | H14: 16.05 | I14: 14.26 | K14: 15685.17 | M14: 1.1 | N14: 1.72
A15: HSBC ELSS Tax saver Fund - Dir - Growth | B15: -0.46 | C15: 2.98 | D15: 8.1 | E15: 6.59 | F15: 9.83 | G15: 18.33 | H15: 14.36 | I15: 14.94 | K15: 4080.58 | M15: 1.16 | N15: 1.94
A16: ICICI Prudential ELSS Tax Saver Fund - Dir - Growth | B16: -0.81 | C16: 2.22 | D16: 5.6 | E16: 0.39 | F16: 3.41 | G16: 13.27 | H16: 11.72 | I16: 14.93 | K16: 14064.46 | M16: 1.11 | N16: 1.74
A17: Invesco India ELSS Tax Saver Fund - Dir - Growth | B17: 0.2 | C17: 2.99 | D17: 10.09 | E17: 6.16 | F17: 4.65 | G17: 14.28 | H17: 11.32 | I17: 16.16 | K17: 2645.94 | M17: 0.88 | N17: 1.99
... A25: Nippon India ELSS Tax Saver Fund - Dir - Growth | B25: -0.44 | C25: 1.11 | D25: 3.86 | E25: 1.9 | F25: 4.57 | G25: 14.67 | H25: 13.6 | I25: 13.97 | K25: 14879.95 | M25: 1.04 | N25: 1.72
A26: NJ ELSS Tax Saver Scheme - Dir - Growth | B26: -0.2 | C26: 3.2 | D26: 6.46 | E26: 5.54 | F26: 1.27 | G26: 12.08 | H26: -- | I26: 14.08 | K26: 332.4 | M26: 0.66 | N26: 2.34
A27: Parag Parikh ELSS Tax Saver Fund - Dir - Growth | B27: -0.79 | C27: 0.76 | D27: 2.63 | E27: -2.85 | F27: -5.39 | G27: 11.63 | H27: 12.99 | I27: 18.02 | K27: 5599.5 | M27: 0.63 | N27: 1.73
A28: PGIM India ELSS Tax Saver Fund - Dir - Growth | B28: -0.07 | C28: 2.67 | D28: 7.93 | E28: 3.72 | F28: 3.06 | G28: 10.61 | H28: 11.23 | I28: 14.07 | K28: 713.35 | M28: 0.78 | N28: 2.3
A29: Quant ELSS Tax Saver Fund - Dir - Growth | B29: -0.3 | C29: 1.83 | D29: 7.05 | E29: 12.96 | F29: 17.35 | G29: 17.31 | H29: 16.51 | I29: 19.99 | K29: 13143.38 | M29: 0.81 | N29: 1.72
A30: Quantum ELSS Tax Saver Fund - Dir - Growth | B30: -0.56 | C30: 1.05 | D30: 3.47 | E30: -2.23 | F30: -1.51 | G30: 12.04 | H30: 11 | I30: 15.5 | K30: 207.3 | M30: 0.89 | N30: 2.09
A31: Samco ELSS Tax Saver Fund - Dir - Growth | B31: 1.17 | C31: 4.99 | D31: 6.85 | E31: 8.56 | F31: 2.06 | G31: 6.04 | H31: -- | I31: 9.41 | K31: 106.75 | M31: 0.97 | N31: 2.37
A32: SBI ELSS Tax Saver Fund - Dir - Growth | B32: -0.8 | C32: -0.36 | D32: 2.77 | E32: -1.68 | F32: 2.12 | G32: 16.47 | H32: 16.44 | I32: 15.38 | K32: 31839.34 | M32: 0.99 | N32: 1.6
A33: Shriram ELSS Tax Saver Fund - Dir - Growth | B33: -0.77 | C33: 1.44 | D33: 5.3 | E33: 1.14 | F33: 3.19 | G33: 9.83 | H33: 9.32 | I33: 12.33 | K33: 46.95 | M33: 0.74 | N33: 2.32
A34: Sundaram ELSS Tax Saver Fund - Dir | B34: -0.65 | C34: 1.74 | D34: 3.95 | E34: -2.33 | F34: -0.6 | G34: 10.62 | H34: 11.17 | I34: 14.5 | K34: 1280.74 | M34: 1.57 | N34: 2.23
A35: Tata ELSS Fund - Dir - Growth | B35: 0.39 | C35: 3.41 | D35: 7.41 | E35: 4.84 | F35: 11.7 | G35: 14.74 | H35: 14.09 | I35: 15.58 | K35: 4597.26 | M35: 0.75 | N35: 1.83
A36: Taurus ELSS Tax Saver Fund - Dir - Growth | B36: -0.31 | C36: 3.68 | D36: 5.42 | E36: 4.18 | F36: -0.37 | G36: 12.08 | H36: 11.75 | I36: 12.87 | K36: 70.4 | M36: 2.22 | N36: 2.52
A37: Union ELSS Tax Saver Fund - Dir - Growth | B37: 0.37 | C37: 2.56 | D37: 6.98 | E37: 3.13 | F37: 5.23 | G37: 12.79 | H37: 12.23 | I37: 13.46 | K37: 856.82 | M37: 1.39 | N37: 2.35
A38: UTI ELSS Tax Saver Fund - Dir - Growth | B38: -0.2 | C38: 1.41 | D38: 5.54 | E38: 0.09 | F38: 2.81 | G38: 10.93 | H38: 9.26 | I38: 13.31 | K38: 3473.99 | M38: 0.96 | N38: 1.91
A39: WhiteOak Capital ELSS Tax Saver Fund - Dir - Growth | B39: 0.3 | C39: 3.32 | D39: 9.76 | E39: 7.93 | F39: 8.3 | G39: 18.61 | H39: -- | I39: 19.11 | K39: 473.58 | M39: 0.64 | N39: 2.33
A40: Median | B40: =MEDIAN(B3:B39) -> -0.37 | C40: =MEDIAN(C3:C39) -> 2.16 | D40: =MEDIAN(D3:D39) -> 6.03 | E40: =MEDIAN(E3:E39) -> 2.4 | F40: =MEDIAN(F3:F39) -> 4.57 | G40: =MEDIAN(G3:G39) -> 13.425 | H40: =MEDIAN(H3:H39) -> 12.91 | I40: =MEDIAN(I3:I39) -> 15.01
A41: Index | B41: -- | C41: -- | D41: -- | E41: -- | F41: -- | G41: -- | H41: -- | I41: --
A42: Nifty 500 TRI | B42: -0.48 | C42: 1.92 | D42: 4.93 | E42: 1.85 | F42: 4.99 | G42: 13 | H42: 12.02

Sheet Focused Funds
A1: ='Small Cap'!A1 -> ( As on 14-08-26 ) | M1: 46082
A2: Scheme Name | B2: 1 Week | C2: 1 Month | D2: 3 Months | E2: 6 Months | F2: 1 Year | G2: 3 Years | H2: 5 Years | I2: Since Inception | K2: AUM ( June 26) | M2: Direct | N2: Regular
A3: 360 ONE Focused Fund - Dir - Growth | B3: 0 | C3: 2.1 | D3: 9.05 | E3: 4.74 | F3: 8.54 | G3: 13.96 | H3: 12.67 | I3: 15.78 | K3: 6644.68 | M3: 0.8 | N3: 1.79
A4: Aditya Birla Sun Life Focused Fund - Dir - Growth | B4: -0.44 | C4: 2.68 | D4: 7.72 | E4: 1.51 | F4: 9.57 | G4: 15.1 | H4: 12.53 | I4: 14.72 | K4: 7854.74 | M4: 0.88 | N4: 1.81
A5: Axis Focused Fund - Dir - Growth | B5: 0.71 | C5: 6.39 | D5: 12.29 | E5: 7.95 | F5: 5.18 | G5: 12.47 | H5: 6.79 | I5: 13.64 | K5: 11078.39 | M5: 0.84 | N5: 1.78
A6: Bandhan Focused Fund - Direct - Growth | B6: -1.13 | C6: 0.34 | D6: 2.32 | E6: 2.04 | F6: 2.91 | G6: 16 | H6: 12.94 | I6: 12.99 | K6: 2066.71 | M6: 0.8 | N6: 2.09
A7: Baroda BNP Paribas Focused Fund - Dir - Growth | B7: 0.37 | C7: 3.19 | D7: 4.77 | E7: 0.96 | F7: 2.18 | G7: 11.3 | H7: 11.36 | I7: 10.84 | K7: 647.97 | M7: 0.47 | N7: 2.28
A8: Canara Robeco Focused Fund - Dir - Growth | B8: -0.41 | C8: 2.84 | D8: 6.94 | E8: -0.09 | F8: 1.83 | G8: 14.95 | H8: 13.64 | I8: 15.94 | K8: 2768.51 | M8: 0.61 | N8: 1.97
A9: DSP Focused Fund - Dir - Growth | B9: -0.39 | C9: 1.12 | D9: 8.38 | E9: 1.68 | F9: 7.92 | G9: 15.4 | H9: 11.91 | I9: 13.52 | K9: 2600.92 | M9: 0.97 | N9: 2.05
A10: Edelweiss Focused Fund - Dir - Growth | B10: 0.09 | C10: 3.81 | D10: 5.49 | E10: 1.48 | F10: 7.01 | G10: 15.4 | H10: -- | I10: 15.93 | K10: 1030.2 | M10: 0.68 | N10: 2.23
A11: Franklin India Focused Equity Fund - Dir - Growth | B11: -0.16 | C11: 1.27 | D11: 3.77 | E11: -4.07 | F11: -3.44 | G11: 10.6 | H11: 11.83 | I11: 16.5 | K11: 11408.91 | M11: 1.02 | N11: 1.8
A12: HDFC Focused Fund - Dir - Growth | B12: -0.39 | C12: 1.91 | D12: 6.96 | E12: -1.19 | F12: 4.47 | G12: 17.54 | H12: 19.57 | I12: 14.99 | K12: 27303.27 | M12: 0.65 | N12: 1.62
A13: HSBC Focused Fund - Dir - Growth | B13: 1.04 | C13: 4.45 | D13: 8.75 | E13: 7.66 | F13: 11.66 | G13: 16.63 | H13: 14.27 | I13: 19.75 | K13: 1723.44 | M13: 1.01 | N13: 2.14
A14: ICICI Prudential Focused Equity Fund - Dir - Growth | B14: -0.72 | C14: 0.78 | D14: 7.45 | E14: -0.07 | F14: 6.99 | G14: 18.85 | H14: 16.87 | I14: 15.69 | K14: 17011.76 | M14: 0.59 | N14: 1.69
A15: Invesco India Focused Fund - Dir - Growth | B15: 0.68 | C15: 3.26 | D15: 14.03 | E15: 14.52 | F15: 5.76 | G15: 23.47 | H15: 16.65 | I15: 22.11 | K15: 5706.62 | M15: 0.49 | N15: 1.82
A16: ITI Focused Fund - Dir - Growth | B16: 0.3 | C16: 3.59 | D16: 5.53 | E16: 8.41 | F16: 13.6 | G16: 21.07 | H16: -- | I16: 19.95 | K16: 596.76 | M16: 0.58 | N16: 2.37
A17: JM Focused Fund - Dir - Growth | B17: 0.72 | C17: 4.06 | D17: 9.61 | E17: 6.1 | F17: 10.96 | G17: 15.27 | H17: 15.42 | I17: 14.56 | K17: 286.3 | M17: 0.84 | N17: 2.41
A18: Kotak Focused Fund - Dir - Growth | B18: -0.13 | C18: 3.04 | D18: 8.8 | E18: 3.34 | F18: 12.74 | G18: 17.35 | H18: 14.32 | I18: 17.44 | K18: 4298.8 | M18: 0.54 | N18: 1.88
A19: LIC MF Focused Fund - Dir - Growth | B19: 0.59 | C19: 4.92 | D19: 14.01 | E19: 9.54 | F19: 9.9 | G19: 11.63 | H19: 10.74 | I19: 11.09 | K19: 170.66 | M19: 0.54 | N19: 2.35
A20: Mahindra Manulife Focused Fund - Dir - Growth | B20: -0.34 | C20: 1.02 | D20: 1.91 | E20: -1.08 | F20: 5.61 | G20: 15.99 | H20: 15.42 | I20: 20.99 | K20: 2197.89 | M20: 0.52 | N20: 2.01
A21: Mirae Asset Focused Fund - Dir - Growth | B21: 0.86 | C21: 4.1 | D21: 10.93 | E21: 5.08 | F21: 1.18 | G21: 9.08 | H21: 7.95 | I21: 15.24 | K21: 6575.73 | M21: 0.63 | N21: 1.8
A22: Motilal Oswal Focused Fund - Dir - Growth | B22: 1.3 | C22: 7.28 | D22: 15.71 | E22: 23.11 | F22: 27.44 | G22: 14.85 | H22: 11.35 | I22: 14.82 | K22: 1635.12 | M22: 0.99 | N22: 2.16
A23: Nippon India Focused Fund - Dir - Growth | B23: -0.34 | C23: 1.83 | D23: 5.98 | E23: 1.9 | F23: 5.08 | G23: 11.95 | H23: 12.11 | I23: 16.53 | K23: 8531.15 | M23: 1.13 | N23: 1.86
A24: Old Bridge Focused Fund - Dir - Growth | B24: -1.11 | C24: 5.26 | D24: 10.25 | E24: 12.36 | F24: 22.84 | G24: -- | H24: -- | I24: 14.7 | K24: 3669.65 | M24: 0.97 | N24: 2.02
A25: Quant Focused Fund - Dir - Growth | B25: 0.35 | C25: 1.05 | D25: 8.46 | E25: 12.55 | F25: 13.79 | G25: 15.57 | H25: 14.28 | I25: 16.95 | K25: 845.84 | M25: 0.87 | N25: 2.36
A26: SBI Focused Fund - Dir - Growth | B26: 0.43 | C26: 2.6 | D26: 5.54 | E26: 7.39 | F26: 16.51 | G26: 17.15 | H26: 13.65 | I26: 15.82 | K26: 47274.19 | M26: 0.77 | N26: 1.56
A27: Sundaram Focused Fund - Dir - Growth | B27: 0.23 | C27: 4.71 | D27: 10.33 | E27: 5.59 | F27: 7.59 | G27: 12.26 | H27: 11.34 | I27: 14.18 | K27: 1053.04 | M27: 1.26 | N27: 2.3
A28: Tata Focused Fund - Dir - Growth | B28: -0.95 | C28: 0.39 | D28: 2.9 | E28: -0.44 | F28: 1.44 | G28: 12.01 | H28: 11.62 | I28: 15.24 | K28: 1760.25 | M28: 0.72 | N28: 2.09
A29: Union Focused Fund - Dir - Growth | B29: 0.9 | C29: 3.57 | D29: 8.81 | E29: 10.59 | F29: 12.5 | G29: 13.73 | H29: 11.6 | I29: 16.99 | K29: 439.85 | M29: 1.55 | N29: 2.53
A30: UTI Focused Fund - Dir - Growth | B30: 0.13 | C30: 3.82 | D30: 7.95 | E30: 2 | F30: 5.53 | G30: 12.59 | H30: -- | I30: 11.2 | K30: 2413.44 | M30: 0.66 | N30: 2
A31: Median | B31: =MEDIAN(B3:B30) -> 0.11 | C31: =MEDIAN(C3:C30) -> 3.115 | D31: =MEDIAN(D3:D30) -> 8.165 | E31: =MEDIAN(E3:E30) -> 4.04 | F31: =MEDIAN(F3:F30) -> 7.3 | G31: =MEDIAN(G3:G30) -> 15.1 | H31: =MEDIAN(H3:H30) -> 12.6 | I31: =MEDIAN(I3:I30) -> 15.465
A32: Index | B32: -- | C32: -- | D32: -- | E32: -- | F32: -- | G32: -- | H32: -- | I32: --
A33: Nifty 500 | B33: -0.49 | C33: 1.7 | D33: 4.34 | E33: 1.2 | F33: 4.03 | G33: 11.92 | H33: 10.89
A34: Nifty 500 TRI | B34: -0.48 | C34: 1.92 | D34: 4.93 | E34: 1.85 | F34: 4.99 | G34: 13 | H34: 12.02

Sheet Large&Mid
A1: ='Small Cap'!A1 -> ( As on 14-08-26 ) | M1: 46082
A2: Scheme Name | B2: 1 Week | C2: 1 Month | D2: 3 Months | E2: 6 Months | F2: 1 Year | G2: 3 Years | H2: 5 Years | I2: Since Inception | K2: AUM ( June 26) | M2: Direct | N2: Regular
A3: Aditya Birla Sun Life Large & Mid Cap Fund - Dir - Growth | B3: 0.34 | C3: 4.36 | D3: 8.38 | E3: 5.64 | F3: 10.75 | G3: 13.78 | H3: 9.99 | I3: 14.92 | K3: 5783.95 | M3: 1.09 | N3: 1.9
A4: Axis Large & Mid Cap Fund - Dir - Growth | B4: 0.33 | C4: 3.14 | D4: 7.91 | E4: 7.49 | F4: 10.57 | G4: 17.59 | H4: 14.26 | I4: 19.19 | K4: 16469.27 | M4: 0.61 | N4: 1.69
A5: Bajaj Finserv Large and Mid Cap Fund - Dir - Growth | B5: -0.7 | C5: 2.35 | D5: 6.3 | E5: 2.39 | F5: 6.27 | G5: -- | H5: -- | I5: 11.15 | K5: 2403.17 | M5: 0.61 | N5: 2.02
A6: Bandhan Large & Mid Cap Fund - Dir - Growth | B6: 0.26 | C6: 1.24 | D6: 3.09 | E6: 3.75 | F6: 8.6 | G6: 20.02 | H6: 17.86 | I6: 15.75 | K6: 18783.25 | M6: 0.54 | N6: 1.68
A7: Bank of India Large & Mid Cap Fund - Dir - Growth | B7: 0.16 | C7: 1.99 | D7: 5.07 | E7: 5.41 | F7: 11.45 | G7: 16.03 | H7: 13.3 | I7: 13.92 | K7: 491.08 | M7: 1.05 | N7: 2.3
A8: Baroda BNP Paribas Large & Mid Cap Fund - Dir - Growth | B8: 0.29 | C8: 3.32 | D8: 6.54 | E8: 3.65 | F8: 8.18 | G8: 16.42 | H8: 14.86 | I8: 20.69 | K8: 1794.44 | M8: 0.84 | N8: 2.09
A9: Canara Robeco Large and Mid Cap Fund - Dir - Growth | B9: 0.35 | C9: 3.31 | D9: 8.04 | E9: 5.39 | F9: 3.63 | G9: 14.97 | H9: 12.5 | I9: 19.14 | K9: 25251.41 | M9: 0.65 | N9: 1.63
A10: DSP Large & Mid Cap Fund - Dir - Growth | B10: -0.63 | C10: 0.4 | D10: 4.3 | E10: -1.19 | F10: 4.92 | G10: 16.07 | H10: 13.37 | I10: 16.19 | K10: 17905.88 | M10: 0.65 | N10: 1.69
A11: Edelweiss Large & Mid Cap Fund - Dir - Growth | B11: 0.17 | C11: 2.58 | D11: 6.03 | E11: 4.66 | F11: 9.23 | G11: 16.72 | H11: 14.74 | I11: 16.13 | K11: 4683.36 | M11: 0.45 | N11: 1.86
A12: Franklin India Large & Mid Cap Fund - Dir - Growth | B12: 0.13 | C12: 2.84 | D12: 7.32 | E12: 3.32 | F12: 3.99 | G12: 13.87 | H12: 11.77 | I12: 14.15 | K12: 3450.48 | M12: 1.36 | N12: 2.05
A13: HDFC Large and Mid Cap Fund - Dir - Growth | B13: -0.36 | C13: 2.18 | D13: 6.6 | E13: 3.33 | F13: 6.55 | G13: 15.61 | H13: 16.4 | I13: 13.47 | K13: 29284.71 | M13: 0.88 | N13: 1.64
A14: Helios Large & Mid Cap Fund - Dir - Growth | B14: 0.43 | C14: 0.77 | D14: 6.15 | E14: 5.27 | F14: 9.73 | G14: -- | H14: -- | I14: 9.33 | K14: 1303.79 | M14: 0.72 | N14: 2.32
A15: HSBC Large & Mid Cap Fund - Dir - Growth | B15: 0.47 | C15: 3.05 | D15: 7.58 | E15: 10.34 | F15: 15.13 | G15: 20.16 | H15: 16.27 | I15: 17.67 | K15: 5343.7 | M15: 0.78 | N15: 1.9
A16: ICICI Prudential Large & Mid Cap Fund - Dir - Growth | B16: -0.55 | C16: 2.7 | D16: 7.12 | E16: 2.75 | F16: 9.49 | G16: 18.09 | H16: 18.03 | I16: 16.22 | K16: 30971.14 | M16: 0.8 | N16: 1.64
A17: Invesco India Large & Mid Cap Fund - Dir - Growth | B17: -0.12 | C17: 2.06 | D17: 11.72 | E17: 11.47 | F17: 11.26 | G17: 24.93 | H17: 18.66 | I17: 18.12 | K17: 11164.32 | M17: 0.61 | N17: 1.76
A18: ITI Large & Mid Cap Fund - Dir - Growth | B18: 0.02 | C18: 2.27 | D18: 7.12 | E18: 8.08 | F18: 8.16 | G18: -- | H18: -- | I18: 1.72 | K18: 743.86 | M18: 0.44 | N18: 2.24
A19: JM Large and Mid Cap Fund - Dir - Growth | B19: -0.05 | C19: 3.72 | D19: 9.25 | E19: 7.17 | F19: 10.07 | G19: -- | H19: -- | I19: 9.69 | K19: 435.38 | M19: 0.67 | N19: 2.38
A20: Kotak Large & Midcap Fund - Dir - Growth | B20: -0.5 | C20: 1.45 | D20: 6.12 | E20: 0.44 | F20: 7.54 | G20: 16.18 | H20: 15.13 | I20: 16.66 | K20: 31262.73 | M20: 0.55 | N20: 1.59
A21: LIC MF Large & Mid Cap Fund - Dir - Growth | B21: 0.11 | C21: 2.36 | D21: 7.86 | E21: 4.11 | F21: 6.26 | G21: 16.53 | H21: 13.45 | I21: 14.32 | K21: 3092.95 | M21: 0.9 | N21: 1.99
A22: Mahindra Manulife Large & Mid Cap Fund - Dir - Growth | B22: 0.89 | C22: 3.28 | D22: 8.39 | E22: 5.68 | F22: 9.5 | G22: 15.04 | H22: 14.73 | I22: 19.02 | K22: 2763.07 | M22: 0.58 | N22: 1.96
A23: Mirae Asset Large & Midcap Fund - Dir - Growth | B23: -0.34 | C23: 1.54 | D23: 6.19 | E23: 3.27 | F23: 9.17 | G23: 14.59 | H23: 12.46 | I23: 20.64 | K23: 44048.03 | M23: 0.63 | N23: 1.54
A24: Motilal Oswal Large and Midcap Fund (MOFLM) - Dir - Growth | B24: 1.6 | C24: 3.7 | D24: 6.3 | E24: 13.44 | F24: 13.61 | G24: 24.32 | H24: 19.78 | I24: 22.83 | K24: 18413.16 | M24: 0.76 | N24: 1.7
A25: Navi Large & Midcap Fund - Dir - Growth | B25: 0.07 | C25: 2.71 | D25: 7.05 | E25: 6.24 | F25: 9.43 | G25: 12.27 | H25: 12.95 | I25: 15.18 | K25: 310.12 | M25: 0.51 | N25: 2.25
A26: Nippon India Vision Large & Mid Cap Fund - Dir - Growth | B26: -0.13 | C26: 2.81 | D26: 5.29 | E26: 2.92 | F26: 6.89 | G26: 17.47 | H26: 15 | I26: 14.23 | K26: 7459.12 | M26: 1.14 | N26: 1.89
A27: PGIM India Large and Midcap Fund - Dir - Growth | B27: 0.6 | C27: 3.37 | D27: 8.01 | E27: 5.61 | F27: 5.56 | G27: -- | H27: -- | I27: 12.67 | K27: 807.22 | M27: 0.65 | N27: 2.31
A28: Quant Large and Mid Cap Fund - Dir - Growth | B28: -1.3 | C28: 1.03 | D28: 5.8 | E28: 18.53 | F28: 14.8 | G28: 17.56 | H28: 17.47 | I28: 18.13 | K28: 3449.51 | M28: 0.81 | N28: 1.99
A29: Samco Large and Mid Cap Fund - Dir - Growth | B29: 0.11 | C29: 1.67 | D29: 0 | E29: -0.43 | F29: -5.2 | G29: -- | H29: -- | I29: -7.78 | K29: 113.87 | M29: 0.79 | N29: 2.39
A30: SBI Large & Midcap Fund - Dir - Growth | B30: -0.77 | C30: 1.25 | D30: 5.37 | E30: 1.6 | F30: 8.14 | G30: 15.21 | H30: 14.92 | I30: 16.64 | K30: 40849.93 | M30: 0.74 | N30: 1.57
A31: Sundaram Large and Mid Cap Fund - Dir - Growth | B31: 0.92 | C31: 5.18 | D31: 14 | E31: 9.59 | F31: 14.73 | G31: 17.3 | H31: 14.33 | I31: 15.42 | K31: 6990.73 | M31: 0.7 | N31: 1.81
A32: Tata Large & Mid Cap Fund - Dir - Growth | B32: -1.61 | C32: 0.58 | D32: 5.44 | E32: 0.8 | F32: -1.16 | G32: 8.99 | H32: 11 | I32: 14.79 | K32: 7887.02 | M32: 0.7 | N32: 1.76
A33: Union Large & Midcap Fund - Dir - Growth | B33: 0.6 | C33: 4.03 | D33: 8.94 | E33: 7.42 | F33: 10.63 | G33: 15.25 | H33: 13.83 | I33: 17.82 | K33: 965.21 | M33: 1.08 | N33: 2.33
A34: UTI Large & Mid Cap Fund - Dir - Growth | B34: 0.05 | C34: 1.61 | D34: 4.94 | E34: 2.32 | F34: 7.97 | G34: 17.45 | H34: 15.54 | I34: 14.68 | K34: 6217.83 | M34: 0.88 | N34: 1.84
A35: WhiteOak Capital Large & Mid Cap Fund - Dir - Growth | B35: 0.16 | C35: 2.52 | D35: 7.72 | E35: 6.4 | F35: 10.63 | G35: -- | H35: -- | I35: 15.67 | K35: 2325.5 | M35: 0.67 | N35: 2.05
A36: Median | B36: =MEDIAN(B3:B35) -> 0.11 | C36: =MEDIAN(C3:C35) -> 2.52 | D36: =MEDIAN(D3:D35) -> 6.6 | E36: =MEDIAN(E3:E35) -> 5.27 | F36: =MEDIAN(F3:F35) -> 9.17 | G36: =MEDIAN(G3:G35) -> 16.3 | H36: =MEDIAN(H3:H35) -> 14.735 | I36: =MEDIAN(I3:I35) -> 15.67
A37: Index | B37: -- | C37: -- | D37: -- | E37: -- | F37: -- | G37: -- | H37: -- | I37: --
A38: NIFTY Large Midcap 250 | B38: -0.24 | C38: 1.66 | D38: 4.14 | E38: 2.37 | F38: 6.25 | G38: 14.03 | H38: 13.22
A39: NIFTY Large Midcap 250 TRI | B39: -0.23 | C39: 1.85 | D39: 4.64 | E39: 2.94 | F39: 7.14 | G39: 15 | H39: 14.25

Sheet Multi Cap
A1: ='Small Cap'!A1 -> ( As on 14-08-26 ) | M1: 46082
A2: Scheme Name | B2: 1 Week | C2: 1 Month | D2: 3 Months | E2: 6 Months | F2: 1 Year | G2: 3 Years | H2: 5 Years | I2: Since Inception | K2: AUM ( June 26) | M2: Direct | N2: Regular
A3: Aditya Birla Sun Life Multi-Cap Fund - Dir - Growth | B3: 0.57 | C3: 4.53 | D3: 10.75 | E3: 9.49 | F3: 12.98 | G3: 16.3 | H3: 14.41 | I3: 17.18 | K3: 7029.63 | M3: 0.76 | N3: 1.82
A4: Axis Multicap Fund - Dir - Growth | B4: 0.63 | C4: 5.13 | D4: 11.59 | E4: 11 | F4: 13.41 | G4: 21.89 | H4: -- | I4: 17.13 | K4: 10457.27 | M4: 0.57 | N4: 1.76
A5: Bajaj Finserv Multi Cap Fund - Dir - Growth | B5: -0.68 | C5: 2.42 | D5: 7.24 | E5: 9.39 | F5: 14.17 | G5: -- | H5: -- | I5: 16.89 | K5: 1429.44 | M5: 0.81 | N5: 2.2
A6: Bandhan Multi Cap Fund - Dir - Growth | B6: -0.22 | C6: 2.02 | D6: 5.51 | E6: 4.72 | F6: 7.46 | G6: 15.25 | H6: -- | I6: 14.77 | K6: 3005.59 | M6: 0.6 | N6: 1.98
A7: Bank of India Multi Cap Fund - Dir - Growth | B7: 0.58 | C7: 1.51 | D7: 7.53 | E7: 10.56 | F7: 17.47 | G7: 20.35 | H7: -- | I7: 23.7 | K7: 1186.47 | M7: 0.78 | N7: 2.1
A8: Baroda BNP Paribas Multi Cap Fund - Dir - Growth | B8: 0.16 | C8: 2.42 | D8: 6.14 | E8: 7.06 | F8: 8.66 | G8: 16.74 | H8: 15.1 | I8: 15 | K8: 3339.44 | M8: 0.9 | N8: 1.96
A9: Canara Robeco Multi Cap Fund - Direct - Growth | B9: 0.13 | C9: 3.12 | D9: 7.82 | E9: 4.94 | F9: 7.09 | G9: 16.58 | H9: -- | I9: 16.3 | K9: 5500.41 | M9: 0.55 | N9: 1.85
A10: DSP Multicap Fund - Dir - Growth | B10: 0.23 | C10: 0.13 | D10: 6.08 | E10: 6.75 | F10: 5.38 | G10: -- | H10: -- | I10: 10.48 | K10: 2925.15 | M10: 0.56 | N10: 1.97
A11: Edelweiss Multi Cap Fund - Dir - Growth | B11: 0.04 | C11: 3.28 | D11: 7.08 | E11: 6.96 | F11: 11.2 | G11: -- | H11: -- | I11: 20.28 | K11: 3338.02 | M11: 0.47 | N11: 1.92
A12: Franklin India Multi Cap Fund - Dir - Growth | B12: 0.12 | C12: 3.66 | D12: 9.45 | E12: 6.43 | F12: 12.13 | G12: -- | H12: -- | I12: 6.55 | K12: 5029.48 | M12: 0.5 | N12: 1.86
A13: Groww Multicap Fund - Dir - Growth | B13: 0.94 | C13: 4.42 | D13: 10.93 | E13: 15.9 | F13: 21.01 | G13: -- | H13: -- | I13: 14.27 | K13: 708.92 | M13: 0.51 | N13: 2.36
A14: HDFC Multi Cap Fund - Dir - Growth | B14: -0.49 | C14: 1.91 | D14: 5.96 | E14: 2.27 | F14: 3.86 | G14: 14.37 | H14: -- | I14: 16.15 | K14: 20216.88 | M14: 0.8 | N14: 1.69
A15: HSBC Multi Cap Fund - Dir - Growth | B15: 0.97 | C15: 4.05 | D15: 8.3 | E15: 10.01 | F15: 13.24 | G15: 21.14 | H15: -- | I15: 23.99 | K15: 5914 | M15: 0.63 | N15: 1.86
A16: ICICI Prudential Multicap Fund - Dir - Growth | B16: -0.63 | C16: 3.03 | D16: 5.33 | E16: 8.47 | F16: 12.19 | G16: 18.42 | H16: 16.41 | I16: 16.46 | K16: 18193.89 | M16: 0.96 | N16: 1.75
A17: Invesco India Multicap Fund - Dir - Growth | B17: 0.16 | C17: 2.28 | D17: 8.95 | E17: 7.51 | F17: 4.29 | G17: 15.44 | H17: 13.21 | I17: 17.49 | K17: 4301.86 | M17: 0.69 | N17: 1.91
A18: ITI Multi Cap Fund - Dir - Growth | B18: 1.11 | C18: 3.7 | D18: 9.45 | E18: 11.72 | F18: 15.81 | G18: 19.56 | H18: 15.58 | I18: 16.51 | K18: 1470.48 | M18: 0.33 | N18: 1.98
A19: Kotak Multicap Fund - Dir - Growth | B19: -0.59 | C19: 1.5 | D19: 5.1 | E19: 3.68 | F19: 11.19 | G19: 19.58 | H19: -- | I19: 17.36 | K19: 28074.19 | M19: 0.45 | N19: 1.6
A20: LIC MF Multi Cap Fund - Dir - Growth | B20: 0.37 | C20: 2.59 | D20: 9.92 | E20: 9.62 | F20: 13.99 | G20: 20.27 | H20: -- | I20: 19.79 | K20: 2042.49 | M20: 0.85 | N20: 2.09
A21: Mahindra Manulife Multi Cap Fund - Dir - Growth | B21: 0.94 | C21: 3.97 | D21: 8.78 | E21: 11.14 | F21: 15.86 | G21: 19.47 | H21: 17.5 | I21: 18.06 | K21: 6926.02 | M21: 0.48 | N21: 1.8
A22: Mirae Asset Multicap Fund - Dir - Growth | B22: -0.24 | C22: 1.39 | D22: 6.9 | E22: 3.88 | F22: 7.59 | G22: -- | H22: -- | I22: 15.98 | K22: 5278.04 | M22: 0.4 | N22: 1.84
A23: Motilal Oswal Multi Cap Fund - Dir - Growth | B23: 1.78 | C23: 9.04 | D23: 19.36 | E23: 20.92 | F23: 13.69 | G23: -- | H23: -- | I23: 21.73 | K23: 4225.5 | M23: 1 | N23: 1.95
A24: Nippon India Multi Cap Fund - Dir - Growth | B24: -0.3 | C24: 1.59 | D24: 4.45 | E24: 3.38 | F24: 3.95 | G24: 15.93 | H24: 19.34 | I24: 16.11 | K24: 54584.58 | M24: 0.73 | N24: 1.5
A25: PGIM India Multi Cap Fund - Dir - Growth | B25: -0.09 | C25: 3.75 | D25: 9.5 | E25: 10.32 | F25: 11.72 | G25: -- | H25: -- | I25: 5.37 | K25: 430.86 | M25: 0.71 | N25: 2.39
A26: Quant Multi Cap Fund - Dir - Growth | B26: -0.82 | C26: -0.27 | D26: 4.97 | E26: 14.26 | F26: 11.28 | G26: 12.02 | H26: 13.01 | I26: 18.34 | K26: 7761.45 | M26: 0.74 | N26: 1.83
A27: Samco Multi Cap Fund - Dir - Growth | B27: 0 | C27: 2.48 | D27: 5.7 | E27: 4.22 | F27: -4.32 | G27: -- | H27: -- | I27: -5.19 | K27: 243.98 | M27: 0.78 | N27: 2.4
A28: SBI Multicap Fund - Dir - Growth | B28: -0.11 | C28: 1.88 | D28: 5.57 | E28: 5.04 | F28: 3.58 | G28: 14.93 | H28: -- | I28: 14.23 | K28: 23693.4 | M28: 0.86 | N28: 1.68
A29: Sundaram Multi cap Fund - Dir - Growth | B29: 0.22 | C29: 3.02 | D29: 9.06 | E29: 4.87 | F29: 6.75 | G29: 15.63 | H29: 14.04 | I29: 16.16 | K29: 2914.87 | M29: 0.91 | N29: 2
A30: Tata Multicap Fund - Dir - Growth | B30: -0.85 | C30: 1.21 | D30: 6.2 | E30: 7.38 | F30: 13.1 | G30: 12.61 | H30: -- | I30: 15.22 | K30: 3455.43 | M30: 0.5 | N30: 1.92
A31: TRUSTMF Multi Cap Fund - Dir - Growth | B31: 1.34 | C31: 5.13 | D31: 12.14 | E31: 14.94 | F31: 20.76 | G31: -- | H31: -- | I31: 19.59 | K31: 603.07 | M31: 0.5 | N31: 2.35
A32: Union Multicap Fund - Dir - Growth | B32: 1.03 | C32: 4.49 | D32: 10.12 | E32: 11.04 | F32: 15.3 | G32: 17.32 | H32: -- | I32: 18.52 | K32: 1420.1 | M32: 1.06 | N32: 2.22
A33: UTI Multi Cap Fund - Dir - Growth | B33: 0.1 | C33: 2.81 | D33: 7.56 | E33: 4.47 | F33: 7.99 | G33: -- | H33: -- | I33: 7.33 | K33: 2041.55 | M33: 0.66 | N33: 1.99
A34: WhiteOak Capital Multi Cap Fund - Dir - Growth | B34: 0.41 | C34: 2.53 | D34: 9.19 | E34: 10.01 | F34: 11.74 | G34: -- | H34: -- | I34: 20.43 | K34: 3850.09 | M34: 0.74 | N34: 1.96
A35: Median | B35: =MEDIAN(B3:B34) -> 0.145 | C35: =MEDIAN(C3:C34) -> 2.7 | D35: =MEDIAN(D3:D34) -> 7.69 | E35: =MEDIAN(E3:E34) -> 7.99 | F35: =MEDIAN(F3:F34) -> 11.73 | G35: =MEDIAN(G3:G34) -> 16.66 | H35: =MEDIAN(H3:H34) -> 15.1 | I35: =MEDIAN(I3:I34) -> 16.485
A36: Index | B36: -- | C36: -- | D36: -- | E36: -- | F36: -- | G36: -- | H36: -- | I36: --
A37: Nifty 500 | B37: -0.49 | C37: 1.7 | D37: 4.34 | E37: 1.2 | F37: 4.03 | G37: 11.92 | H37: 10.89
A38: Nifty 500 TRI | B38: -0.48 | C38: 1.92 | D38: 4.93 | E38: 1.85 | F38: 4.99 | G38: 13 | H38: 12.02

Sheet Value Funds
A1: ='Small Cap'!A1 -> ( As on 14-08-26 ) | M1: 46082
A2: Scheme Name | B2: 1 Week | C2: 1 Month | D2: 3 Months | E2: 6 Months | F2: 1 Year | G2: 3 Years | H2: 5 Years | I2: Since Inception | K2: AUM ( June 26) | M2: Direct | N2: Regular
A3: Aditya Birla Sun Life Value Fund - Dir - Growth | B3: -0.07 | C3: 1.69 | D3: 6.7 | E3: 8.63 | F3: 15.63 | G3: 17.34 | H3: 15.47 | I3: 17.01 | K3: 6603.13 | M3: 1.02 | N3: 1.87
A4: Axis Value Fund - Dir - Growth | B4: 0.14 | C4: 4.22 | D4: 8.65 | E4: 6.33 | F4: 13.24 | G4: 20.22 | H4: -- | I4: 17.18 | K4: 1668.17 | M4: 0.65 | N4: 2.12
A5: Bandhan Value Fund - Dir - Growth | B5: -0.42 | C5: 1.9 | D5: 3.46 | E5: 0.23 | F5: 4.12 | G5: 12.34 | H5: 14.36 | I5: 16.28 | K5: 9985.03 | M5: 0.74 | N5: 1.77
A6: Baroda BNP Paribas Value Fund - Dir - Growth | B6: -0.32 | C6: 2.03 | D6: 2.01 | E6: 0.41 | F6: 4.3 | G6: 11.1 | H6: -- | I6: 12.28 | K6: 1023.46 | M6: 1.17 | N6: 2.23
A7: Canara Robeco Value Fund - Dir - Growth | B7: 0.15 | C7: 2.38 | D7: 4.55 | E7: 1.33 | F7: 3.29 | G7: 13.59 | H7: -- | I7: 14.75 | K7: 1272.22 | M7: 0.74 | N7: 2.17
A8: DSP Value Fund - Dir - Growth | B8: -0.33 | C8: 1.02 | D8: 2.98 | E8: 3.94 | F8: 13.65 | G8: 17.87 | H8: 14.03 | I8: 17.58 | K8: 1975.27 | M8: 0.96 | N8: 1.82
A9: Groww Value Fund - Dir - Growth | B9: -0.49 | C9: 1.18 | D9: 6.28 | E9: 3.36 | F9: 4.76 | G9: 15.54 | H9: 12.87 | I9: 11.71 | K9: 70.77 | M9: 1.05 | N9: 2.45
A10: HDFC Value Fund - Dir - Growth | B10: -0.16 | C10: 3 | D10: 8.63 | E10: 4.81 | F10: 10.4 | G10: 18.15 | H10: 15.41 | I10: 16.12 | K10: 7583.27 | M10: 1.01 | N10: 1.86
A11: HSBC Value Fund - Dir - Growth | B11: -0.12 | C11: 1.92 | D11: 4 | E11: 2.23 | F11: 7.28 | G11: 18.86 | H11: 17.4 | I11: 18.92 | K11: 14828.3 | M11: 0.7 | N11: 1.72
A12: ICICI Prudential Value Fund - Dir - Growth | B12: -0.55 | C12: 0.65 | D12: 2.18 | E12: -3.75 | F12: 0.57 | G12: 14.24 | H12: 16.06 | I12: 17.37 | K12: 60198.25 | M12: 0.99 | N12: 1.51
A13: ITI Value Fund - Dir - Growth | B13: -0.24 | C13: 1.66 | D13: 3.61 | E13: 2.15 | F13: 9.3 | G13: 15.27 | H13: 14.09 | I13: 13.3 | K13: 359.52 | M13: 0.57 | N13: 2.37
A14: JM Value Fund - Dir - Growth | B14: -0.02 | C14: 3.59 | D14: 6.71 | E14: 4.75 | F14: 4.01 | G14: 14.85 | H14: 16.05 | I14: 16.08 | K14: 823.4 | M14: 1.25 | N14: 2.4
A15: LIC MF Value Fund - Dir - Growth | B15: 0.26 | C15: 5.96 | D15: 13.8 | E15: 17.5 | F15: 27.38 | G15: 19.37 | H15: 15.32 | I15: 15.59 | K15: 234.78 | M15: 1.35 | N15: 2.48
A16: Mahindra Manulife Value Fund - Dir - Growth | B16: 0.22 | C16: 1.7 | D16: 5.98 | E16: 6.88 | F16: 17.4 | G16: -- | H16: -- | I16: 20.27 | K16: 892.62 | M16: 0.64 | N16: 2.32
A17: Nippon India Value Fund - Dir - Growth | B17: -0.84 | C17: 0.61 | D17: 2.67 | E17: -0.85 | F17: 3.82 | G17: 16.45 | H17: 15.28 | I17: 15.77 | K17: 8962.36 | M17: 1.07 | N17: 1.84
A18: Quant Value Fund - Dir - Growth | B18: -0.27 | C18: -3.04 | D18: 2.01 | E18: 17.56 | F18: 19.18 | G18: 22.31 | H18: -- | I18: 20.62 | K18: 1952.19 | M18: 0.59 | N18: 2.1
A19: Quantum Value Fund -Dir- Growth | B19: -0.55 | C19: 1.02 | D19: 3.46 | E19: -2.34 | F19: -1.74 | G19: 11.94 | H19: 10.89 | I19: 13.26 | K19: 1107.77 | M19: 1.1 | N19: 2.13
A20: Tata Value Fund - Dir - Growth | B20: -0.01 | C20: 1.97 | D20: 3.82 | E20: 0.25 | F20: 5.17 | G20: 14.7 | H20: 14.9 | I20: 16.43 | K20: 8341.71 | M20: 0.82 | N20: 1.8
A21: Templeton India Value Fund - Dir - Growth | B21: -1.08 | C21: -0.74 | D21: 1.37 | E21: -3.82 | F21: 0.78 | G21: 11.85 | H21: 14.82 | I21: 14.39 | K21: 2053.59 | M21: 0.95 | N21: 2.1
A22: Union Value Fund - Dir - Growth | B22: -0.16 | C22: 1.49 | D22: 5.65 | E22: 1.71 | F22: 6.98 | G22: 14.63 | H22: 14.24 | I22: 16.04 | K22: 393.65 | M22: 1.23 | N22: 2.48
A23: UTI Value Fund - Dir - Growth | B23: -0.38 | C23: 0.95 | D23: 4.95 | E23: -1.26 | F23: 2.04 | G23: 14.55 | H23: 12.57 | I23: 13.67 | K23: 9439.61 | M23: 1.22 | N23: 1.85
A24: Median | B24: =MEDIAN(B3:B23) -> -0.24 | C24: =MEDIAN(C3:C23) -> 1.69 | D24: =MEDIAN(D3:D23) -> 4 | E24: =MEDIAN(E3:E23) -> 2.15 | F24: =MEDIAN(F3:F23) -> 5.17 | G24: =MEDIAN(G3:G23) -> 15.06 | H24: =MEDIAN(H3:H23) -> 14.86 | I24: =MEDIAN(I3:I23) -> 16.08
A25: Index | B25: -- | C25: -- | D25: -- | E25: -- | F25: -- | G25: -- | H25: -- | I25: --
A26: Nifty 500 | B26: -0.49 | C26: 1.7 | D26: 4.34 | E26: 1.2 | F26: 4.03 | G26: 11.92 | H26: 10.89
A27: Nifty 500 TRI | B27: -0.48 | C27: 1.92 | D27: 4.93 | E27: 1.85 | F27: 4.99 | G27: 13 | H27: 12.02

Sheet Arbitrage Funds
A1: ='Small Cap'!A1 -> ( As on 14-08-26 ) | M1: 46082
A2: Scheme Name | B2: 1 Week | C2: 1 Month | D2: 3 Months | E2: 6 Months | F2: 1 Year | G2: 3 Years | H2: 5 Years | I2: Since Inception | K2: AUM ( June 26) | M2: Direct | N2: Regular
A3: Aditya Birla Sun Life Arbitrage Fund - Dir - Growth | B3: 0.09 | C3: 0.49 | D3: 1.74 | E3: 3.2 | F3: 6.6 | G3: 7.51 | H3: 6.72 | I3: 6.99 | K3: 26645.65 | M3: 0.31 | N3: 1.03
A4: Axis Arbitrage Fund - Dir - Growth | B4: 0.08 | C4: 0.51 | D4: 1.71 | E4: 3.21 | F4: 6.57 | G4: 7.45 | H4: 6.75 | I4: 6.71 | K4: 10362.38 | M4: 0.31 | N4: 1
A5: Bajaj Finserv Arbitrage Fund - Dir - Growth | B5: 0.09 | C5: 0.44 | D5: 1.66 | E5: 3.18 | F5: 6.49 | G5: -- | H5: -- | I5: 7.06 | K5: 1208.65 | M5: 0.33 | N5: 1.03
A6: Bandhan Arbitrage Fund - Dir - Growth | B6: 0.1 | C6: 0.5 | D6: 1.68 | E6: 3.1 | F6: 6.35 | G6: 7.4 | H6: 6.66 | I6: 6.93 | K6: 8189.71 | M6: 0.34 | N6: 1.07
A7: Bank of India Arbitrage Fund - Dir - Growth | B7: 0.02 | C7: 0.45 | D7: 1.42 | E7: 2.86 | F7: 6 | G7: 6.85 | H7: 5.78 | I7: 5.41 | K7: 47.83 | M7: 0.37 | N7: 0.88
A8: Baroda BNP Paribas Arbitrage Fund - Dir - Growth | B8: 0.12 | C8: 0.48 | D8: 1.62 | E8: 3.02 | F8: 6.32 | G8: 7.36 | H8: 6.56 | I8: 6.4 | K8: 1146.77 | M8: 0.31 | N8: 1.11
A9: Capitalmind Arbitrage Fund - Dir - Growth | B9: 0.18 | C9: 0.49 | D9: 1.49 | E9: -- | F9: -- | G9: -- | H9: -- | I9: 2.57 | K9: 21.2 | M9: 0.18 | N9: 0.98
A10: DSP Arbitrage Fund - Dir - Growth | B10: 0.07 | C10: 0.5 | D10: 1.67 | E10: 3.12 | F10: 6.41 | G10: 7.3 | H10: 6.56 | I10: 6.23 | K10: 6529.13 | M10: 0.33 | N10: 0.94
A11: Edelweiss Arbitrage Fund - Dir - Growth | B11: 0.07 | C11: 0.48 | D11: 1.73 | E11: 3.22 | F11: 6.54 | G11: 7.5 | H11: 6.82 | I11: 6.85 | K11: 15062.34 | M11: 0.37 | N11: 1.05
A12: Franklin India Arbitrage Fund - Dir - Growth | B12: 0.09 | C12: 0.52 | D12: 1.75 | E12: 3.35 | F12: 6.86 | G12: -- | H12: -- | I12: 7.06 | K12: 1425.23 | M12: 0.27 | N12: 0.98
A13: HDFC Arbitrage Fund - Dir - Growth | B13: 0.11 | C13: 0.5 | D13: 1.71 | E13: 3.18 | F13: 6.49 | G13: 7.38 | H13: 6.59 | I13: 6.45 | K13: 23772.01 | M13: 0.42 | N13: 0.92
A14: Helios Arbitrage Fund - Dir - Growth | B14: 0 | C14: 0.39 | D14: 1.49 | E14: -- | F14: -- | G14: -- | H14: -- | I14: 2.4 | K14: 146.1 | M14: 0.49 | N14: 1.04
A15: HSBC Arbitrage Fund - Dir - Growth | B15: 0.09 | C15: 0.53 | D15: 1.71 | E15: 3.18 | F15: 6.5 | G15: 7.31 | H15: 6.54 | I15: 6.64 | K15: 2944.22 | M15: 0.29 | N15: 0.91
A16: ICICI Prudential Arbitrage Fund - Dir - Growth | B16: 0.09 | C16: 0.51 | D16: 1.72 | E16: 3.2 | F16: 6.48 | G16: 7.42 | H16: 6.66 | I16: 7.02 | K16: 33423.34 | M16: 0.4 | N16: 0.88
A17: Invesco India Arbitrage Fund - Dir - Growth | B17: 0.13 | C17: 0.5 | D17: 1.75 | E17: 3.25 | F17: 6.68 | G17: 7.54 | H17: 6.96 | I17: 6.96 | K17: 28526.49 | M17: 0.4 | N17: 1.06
A18: ITI Arbitrage Fund - Dir - Growth | B18: -0.04 | C18: 0.34 | D18: 1.34 | E18: 2.84 | F18: 6.32 | G18: 7.32 | H18: 6.08 | I18: 5.49 | K18: 71.61 | M18: 0.21 | N18: 0.93
A19: JioBlackRock Arbitrage Fund - Dir - Growth | B19: 0.06 | C19: 0.46 | D19: 1.67 | E19: 3.33 | F19: -- | G19: -- | H19: -- | I19: 4.57 | K19: 559.2 | M19: 0.22 | N19: --
A20: JM Arbitrage Fund - Dir - Growth | B20: 0.04 | C20: 0.38 | D20: 1.52 | E20: 2.96 | F20: 6.22 | G20: 7.05 | H20: 6.29 | I20: 6.41 | K20: 382.55 | M20: 0.41 | N20: 1.08
A21: Kotak Arbitrage Fund - Dir - Growth | B21: 0.07 | C21: 0.5 | D21: 1.7 | E21: 3.25 | F21: 6.57 | G21: 7.55 | H21: 6.85 | I21: 7.08 | K21: 72409.42 | M21: 0.37 | N21: 0.97
A22: LIC MF Arbitrage Fund - Dir - Growth | B22: 0.07 | C22: 0.43 | D22: 1.66 | E22: 3.21 | F22: 6.46 | G22: 7.16 | H22: 6.49 | I22: 5.97 | K22: 243.08 | M22: 0.29 | N22: 0.99
A23: Mahindra Manulife Arbitrage Fund - Dir - Growth | B23: 0.03 | C23: 0.35 | D23: 1.48 | E23: 2.86 | F23: 6.08 | G23: 6.46 | H23: 5.73 | I23: 5.43 | K23: 126.38 | M23: 0.36 | N23: 1.12
A24: Mirae Asset Arbitrage Fund - Dir - Growth | B24: 0.08 | C24: 0.44 | D24: 1.69 | E24: 3.13 | F24: 6.57 | G24: 7.45 | H24: 6.67 | I24: 6.23 | K24: 3737.48 | M24: 0.13 | N24: 0.93
A25: Motilal Oswal Arbitrage Fund - Dir - Growth | B25: 0.06 | C25: 0.48 | D25: 1.7 | E25: 3.29 | F25: 6.8 | G25: -- | H25: -- | I25: 7.25 | K25: 2847.65 | M25: 0.1 | N25: 1
A26: Nippon India Arbitrage Fund - Dir - Growth | B26: 0.1 | C26: 0.49 | D26: 1.72 | E26: 3.22 | F26: 6.58 | G26: 7.4 | H26: 6.71 | I26: 7.07 | K26: 16638.21 | M26: 0.31 | N26: 1.01
A27: NJ Arbitrage Fund - Dir - Growth | B27: -0.02 | C27: 0.38 | D27: 1.52 | E27: 2.99 | F27: 6.14 | G27: 6.91 | H27: -- | I27: 6.87 | K27: 272.83 | M27: 0.26 | N27: 1
A28: Old Bridge Arbitrage Fund - Dir - Growth | B28: 0.03 | C28: 0.4 | D28: 1.66 | E28: 3.07 | F28: -- | G28: -- | H28: -- | I28: 4.82 | K28: 188.48 | M28: 0.14 | N28: 0.99
A29: Parag Parikh Arbitrage Fund - Dir - Growth | B29: 0.07 | C29: 0.46 | D29: 1.64 | E29: 3.13 | F29: 6.33 | G29: -- | H29: -- | I29: 7.04 | K29: 2631.73 | M29: 0.29 | N29: 0.64
A30: PGIM India Arbitrage Fund - Dir - Growth | B30: 0.08 | C30: 0.41 | D30: 1.62 | E30: 3.23 | F30: 6.3 | G30: 7.15 | H30: 6.37 | I30: 6.4 | K30: 94.3 | M30: 0.36 | N30: 1.04
A31: quant Arbitrage Fund - Dir - Growth | B31: 0.04 | C31: 0.52 | D31: 1.89 | E31: 3.68 | F31: 7.48 | G31: -- | H31: -- | I31: 7.43 | K31: 553.39 | M31: 0.22 | N31: 0.88
A32: Samco Arbitrage Fund - Dir - Growth | B32: 0 | C32: 0.18 | D32: 1.11 | E32: 2.33 | F32: 5 | G32: -- | H32: -- | I32: 5.22 | K32: 30.2 | M32: 0.38 | N32: 1.63
A33: SBI Arbitrage Opportunities Fund - Dir - Growth | B33: 0.08 | C33: 0.46 | D33: 1.62 | E33: 3.12 | F33: 6.39 | G33: 7.36 | H33: 6.77 | I33: 6.83 | K33: 45923.07 | M33: 0.4 | N33: 0.9
A34: Sundaram Arbitrage Fund - Dir - Growth | B34: 0.12 | C34: 0.42 | D34: 1.69 | E34: 3.31 | F34: 6.66 | G34: 7.31 | H34: 6.28 | I34: 4.9 | K34: 649.72 | M34: 0.3 | N34: 1.01
A35: Tata Arbitrage Fund - Dir - Growth | B35: 0.08 | C35: 0.5 | D35: 1.69 | E35: 3.23 | F35: 6.62 | G35: 7.57 | H35: 6.78 | I35: 6.54 | K35: 24026 | M35: 0.31 | N35: 1.09
A36: The Wealth Company Arbitrage Fund - Dir - Growth | B36: 0.09 | C36: 0.4 | D36: 1.6 | E36: 3.08 | F36: -- | G36: -- | H36: -- | I36: 5.37 | K36: 131.14 | M36: 0.24 | N36: 0.91
A37: TRUSTMF Arbitrage Fund - Dir - Growth | B37: 0.02 | C37: 0.38 | D37: 1.55 | E37: 2.95 | F37: -- | G37: -- | H37: -- | I37: 6.1 | K37: 123.25 | M37: 0.2 | N37: 1
A38: Union Arbitrage Fund - Dir - Growth | B38: 0.1 | C38: 0.53 | D38: 1.72 | E38: 3.22 | F38: 6.38 | G38: 7.28 | H38: 6.46 | I38: 6.1 | K38: 245.94 | M38: 0.37 | N38: 0.98
A39: UTI Arbitrage Fund - Dir - Growth | B39: 0.09 | C39: 0.5 | D39: 1.69 | E39: 3.16 | F39: 6.5 | G39: 7.42 | H39: 6.63 | I39: 6.78 | K39: 11324.06 | M39: 0.25 | N39: 0.78
A40: WhiteOak Capital Arbitrage Fund - Dir - Growth | B40: 0.12 | C40: 0.47 | D40: 1.81 | E40: 3.48 | F40: 6.98 | G40: -- | H40: -- | I40: 7.3 | K40: 1595.93 | M40: 0.38 | N40: 1.1
A41: Median | B41: =MEDIAN(B3:B40) -> 0.08 | C41: =MEDIAN(C3:C40) -> 0.475 | D41: =MEDIAN(D3:D40) -> 1.675 | E41: =MEDIAN(E3:E40) -> 3.18 | F41: =MEDIAN(F3:F40) -> 6.49 | G41: =MEDIAN(G3:G40) -> 7.36 | H41: =MEDIAN(H3:H40) -> 6.61 | I41: =MEDIAN(I3:I40) -> 6.495
A42: Index | B42: -- | C42: -- | D42: -- | E42: -- | F42: -- | G42: -- | H42: -- | I42: --
A43: Nifty 500 TRI | B43: -0.48 | C43: 1.92 | D43: 4.93 | E43: 1.85 | F43: 4.99 | G43: 13 | H43: 12.02

Sheet BAF
A1: ='Small Cap'!A1 -> ( As on 14-08-26 ) | M1: 46082
A2: Scheme Name | B2: 1 Week | C2: 1 Month | D2: 3 Months | E2: 6 Months | F2: 1 Year | G2: 3 Years | H2: 5 Years | I2: Since Inception | K2: AUM ( June 26) | M2: Direct | N2: Regular
A3: Aditya Birla Sun Life Balanced Advantage Fund - Dir - Growth | B3: -0.14 | C3: 2.47 | D3: 6.14 | E3: 4.88 | F3: 9.79 | G3: 13.05 | H3: 11.09 | I3: 12.21 | K3: 9489.56 | M3: 0.66 | N3: 1.77
A4: Axis Balanced Advantage Fund - Dir - Growth | B4: -0.2 | C4: 1.57 | D4: 4.52 | E4: 1.82 | F4: 5.92 | G4: 13.32 | H4: 10.73 | I4: 10.43 | K4: 3814.4 | M4: 0.61 | N4: 1.9
A5: Bajaj Finserv Balanced Advantage Fund - Dir - Growth | B5: -0.31 | C5: 2.56 | D5: 5.73 | E5: 2.97 | F5: 8.35 | G5: -- | H5: -- | I5: 8.27 | K5: 1238.84 | M5: 0.56 | N5: 2.1
A6: Bandhan Balanced Advantage Fund - Dir - Growth | B6: -0.02 | C6: 1.4 | D6: 4.8 | E6: 4.03 | F6: 7.47 | G6: 11.23 | H6: 9.03 | I6: 9.68 | K6: 2236.44 | M6: 0.79 | N6: 2.06
A7: Bank of India Balanced Advantage Fund - Dir - Growth | B7: -0.37 | C7: 1.85 | D7: 3.08 | E7: 3.32 | F7: 8.95 | G7: 10.66 | H7: 11.34 | I7: 8.92 | K7: 169.8 | M7: 1.15 | N7: 2.3
A8: Baroda BNP Paribas Balanced Advantage Fund - Dir - Growth | B8: 0.56 | C8: 2.76 | D8: 4.63 | E8: 5.04 | F8: 10.23 | G8: 13.84 | H8: 12.43 | I8: 14.74 | K8: 5002.59 | M8: 0.76 | N8: 1.89
A9: Canara Robeco Balanced Advantage Fund - Dir - Growth | B9: -0.19 | C9: 2.3 | D9: 5.01 | E9: 1.32 | F9: 3.48 | G9: -- | H9: -- | I9: 3.34 | K9: 1125.26 | M9: 0.93 | N9: 2.21
A10: DSP Dynamic Asset Allocation Fund - Dir - Growth | B10: 0.11 | C10: 0.98 | D10: 3.74 | E10: 2.68 | F10: 6.74 | G10: 11.82 | H10: 9.46 | I10: 10.17 | K10: 3749.13 | M10: 0.66 | N10: 1.89
A11: Edelweiss Balanced Advantage Fund - Dir - Growth | B11: -0.23 | C11: 2.55 | D11: 4.9 | E11: 3.46 | F11: 8.29 | G11: 11.88 | H11: 10.48 | I11: 12.32 | K11: 13031.23 | M11: 0.49 | N11: 1.64
A12: Franklin India Balanced Advantage Fund - Dir - Growth | B12: -0.23 | C12: 1.27 | D12: 4.01 | E12: 1.23 | F12: 3.65 | G12: 11.39 | H12: -- | I12: 11.85 | K12: 2819 | M12: 0.53 | N12: 1.96
A13: HDFC Balanced Advantage Fund - Dir - Growth | B13: -0.52 | C13: 1.47 | D13: 4.16 | E13: 0.26 | F13: 3.69 | G13: 13.67 | H13: 15.63 | I13: 14.15 | K13: 106456.16 | M13: 0.75 | N13: 1.36
A14: Helios Balanced Advantage Fund - Dir - Growth | B14: 0.42 | C14: 0.75 | D14: 3.34 | E14: 1.08 | F14: 5.98 | G14: -- | H14: -- | I14: 8.18 | K14: 290.9 | M14: 0.93 | N14: 2.43
A15: HSBC Balanced Advantage Fund - Dir - Growth | B15: -0.27 | C15: 2.14 | D15: 4.69 | E15: 2.8 | F15: 4.21 | G15: 10.63 | H15: 9.38 | I15: 11.4 | K15: 1518.1 | M15: 0.81 | N15: 2.12
A16: ICICI Prudential Balanced Advantage Fund - Dir - Growth | B16: -0.04 | C16: 3.3 | D16: 6.48 | E16: 3.65 | F16: 9.42 | G16: 12.95 | H16: 11.78 | I16: 12.86 | K16: 72486.28 | M16: 0.88 | N16: 1.45
A17: Invesco India Balanced Advantage Fund - Dir - Growth | B17: -0.44 | C17: 1.38 | D17: 4.08 | E17: -0.09 | F17: 0.44 | G17: 10.37 | H17: 9.25 | I17: 11.92 | K17: 996.48 | M17: 0.75 | N17: 2.09
A18: ITI Balanced Advantage Fund - Dir - Growth | B18: 0.02 | C18: 1.96 | D18: 4.28 | E18: 0.1 | F18: 3.22 | G18: 10.65 | H18: 9.45 | I18: 7.81 | K18: 355.1 | M18: 0.65 | N18: 2.39
A19: Kotak Balanced Advantage Fund - Dir - Growth | B19: 0.06 | C19: 1.96 | D19: 5.41 | E19: 2.74 | F19: 6.22 | G19: 11.03 | H19: 10.08 | I19: 11.21 | K19: 17371.73 | M19: 0.57 | N19: 1.67
A20: LIC MF Balanced Advantage Fund - Dir - Growth | B20: 0.73 | C20: 3.72 | D20: 7.41 | E20: 4.31 | F20: 5.41 | G20: 9.52 | H20: -- | I20: 9.15 | K20: 684.91 | M20: 1.25 | N20: 2.42
A21: Mahindra Manulife Balanced Advantage Fund - Dir - Growth | B21: 0.26 | C21: 1.67 | D21: 5.45 | E21: 4.06 | F21: 7.63 | G21: 12.65 | H21: -- | I21: 11.17 | K21: 903.94 | M21: 0.68 | N21: 2.26
A22: Mirae Asset Balanced Advantage Fund - Dir - Growth | B22: -0.12 | C22: 1.58 | D22: 3.85 | E22: 2.44 | F22: 7.02 | G22: 11.41 | H22: -- | I22: 11.81 | K22: 2128.89 | M22: 0.68 | N22: 2.05
A23: Motilal Oswal Balance Advantage Fund - Dir - Growth | B23: 0.79 | C23: 6.56 | D23: 9.3 | E23: 8.31 | F23: 1.07 | G23: 4.26 | H23: 6.21 | I23: 8.34 | K23: 732.54 | M23: 1.1 | N23: 2.37
A24: Nippon India Balanced Advantage Fund - Dir - Growth | B24: 0.02 | C24: 1.72 | D24: 5.21 | E24: 3.09 | F24: 7.35 | G24: 12.27 | H24: 10.63 | I24: 12.17 | K24: 9796.34 | M24: 0.56 | N24: 1.74
A25: NJ Balanced Advantage Fund - Dir - Growth | B25: -0.07 | C25: 2.15 | D25: 4.09 | E25: 3.34 | F25: 3.65 | G25: 10.15 | H25: -- | I25: 8.46 | K25: 3393.51 | M25: 0.62 | N25: 1.92
A26: Parag Parikh Dynamic Asset Allocation Fund - Dir - Growth | B26: 0.03 | C26: 0.57 | D26: 1.99 | E26: 2.46 | F26: 4.46 | G26: -- | H26: -- | I26: 7.3 | K26: 2655.99 | M26: 0.34 | N26: 0.64
A27: PGIM India Balanced Advantage Fund - Dir - Growth | B27: -0.41 | C27: 1.45 | D27: 4.28 | E27: 0.96 | F27: 1.82 | G27: 8.53 | H27: 8.44 | I27: 9.84 | K27: 770.48 | M27: 0.6 | N27: 2.28
A28: Quant Dynamic Asset Allocation Fund - Dir - Growth | B28: 0.11 | C28: -1.27 | D28: 0.7 | E28: 4.34 | F28: 2.42 | G28: 16.09 | H28: -- | I28: 18 | K28: 905.22 | M28: 0.8 | N28: 2.29
A29: Samco Dynamic Asset Allocation Fund - Dir - Growth | B29: -0.28 | C29: -0.47 | D29: 0.95 | E29: 0 | F29: -0.84 | G29: -- | H29: -- | I29: 2.42 | K29: 190.3 | M29: 0.87 | N29: 2.41
A30: SBI Balanced Advantage Fund - Dir - Growth | B30: -0.24 | C30: 0.73 | D30: 2.4 | E30: 0.58 | F30: 6.08 | G30: 11.24 | H30: -- | I30: 11.01 | K30: 41512.85 | M30: 0.7 | N30: 1.55
A31: Shriram Balanced Advantage Fund - Dir - Growth | B31: -0.46 | C31: 1.73 | D31: 3.56 | E31: 0.03 | F31: 2.84 | G31: 8.29 | H31: 7.81 | I31: 9.57 | K31: 42.88 | M31: 0.36 | N31: 2.34
A32: Sundaram Balanced Advantage Fund - Dir - Growth | B32: 0.19 | C32: 2.35 | D32: 4.3 | E32: 1.15 | F32: 4.13 | G32: 10.1 | H32: 9.46 | I32: 10.07 | K32: 1663.71 | M32: 0.65 | N32: 2.08
A33: Tata Balanced Advantage Fund - Dir - Growth | B33: -0.2 | C33: 0.47 | D33: 3.89 | E33: 2.39 | F33: 6.19 | G33: 10.12 | H33: 10.12 | I33: 12.22 | K33: 8834.19 | M33: 0.5 | N33: 1.72
A34: The Wealth Company Balanced Advantage Fund - Dir - Growth | B34: 0.1 | C34: 1.69 | D34: 2.68 | E34: -- | F34: -- | G34: -- | H34: -- | I34: 1.93 | K34: 47.96 | M34: 0.37 | N34: 2.33
A35: Unifi Dynamic Asset Allocation Fund - Dir - Growth | B35: 0.16 | C35: 0.85 | D35: 2.53 | E35: 4.08 | F35: 8.22 | G35: -- | H35: -- | I35: 8.39 | K35: 1290.08 | M35: 0.93 | N35: 1.52
A36: Union Balanced Advantage Fund - Dir - Growth | B36: 0.26 | C36: 2.02 | D36: 4.94 | E36: 1.42 | F36: 4.8 | G36: 9.67 | H36: 8.59 | I36: 9.98 | K36: 1236.69 | M36: 1.11 | N36: 2.23
A37: UTI Balanced Advantage Fund - Dir - Growth | B37: -0.14 | C37: 1.74 | D37: 4.27 | E37: -0.29 | F37: 2.99 | G37: 9.76 | H37: -- | I37: 9.76 | K37: 3021.97 | M37: 0.6 | N37: 1.92
A38: WhiteOak Capital Balanced Advantage Fund - Dir - Growth | B38: 0.08 | C38: 2.46 | D38: 6.17 | E38: 4.18 | F38: 6.51 | G38: 13.11 | H38: -- | I38: 13.94 | K38: 2201.72 | M38: 0.75 | N38: 2.06
A39: Median | B39: =MEDIAN(B3:B38) -> -0.055 | C39: =MEDIAN(C3:C38) -> 1.725 | D39: =MEDIAN(D3:D38) -> 4.28 | E39: =MEDIAN(E3:E38) -> 2.68 | F39: =MEDIAN(F3:F38) -> 5.92 | G39: =MEDIAN(G3:G38) -> 11.23 | H39: =MEDIAN(H3:H38) -> 9.77 | I39: =MEDIAN(I3:I38) -> 10.12
A40: Index | B40: -- | C40: -- | D40: -- | E40: -- | F40: -- | G40: -- | H40: -- | I40: --
A41: Nifty 500 TRI | B41: -0.48 | C41: 1.92 | D41: 4.93 | E41: 1.85 | F41: 4.99 | G41: 13 | H41: 12.02

Sheet Equity Saving
A1: ='Small Cap'!A1 -> ( As on 14-08-26 ) | M1: 46082
A2: Scheme Name | B2: 1 Week | C2: 1 Month | D2: 3 Months | E2: 6 Months | F2: 1 Year | G2: 3 Years | H2: 5 Years | I2: Since Inception | K2: AUM ( June 26) | M2: Direct | N2: Regular
A3: Aditya Birla Sun Life Equity Savings Fund - Dir - Growth | B3: -0.11 | C3: 1 | D3: 2.91 | E3: 2.9 | F3: 6.74 | G3: 8.66 | H3: 7.36 | I3: 8.55 | K3: 1122.37 | M3: 0.52 | N3: 1.02
A4: Axis Equity Savings Fund - Dir - Growth | B4: 0 | C4: 1.79 | D4: 4.65 | E4: 3.62 | F4: 7.29 | G4: 10.38 | H4: 8.64 | I4: 9.36 | K4: 875.02 | M4: 1.06 | N4: 2.3
A5: Bajaj Finserv Equity Savings Fund - Dir - Growth | B5: -0.24 | C5: 1.06 | D5: 1.32 | E5: 3.04 | F5: -- | G5: -- | H5: -- | I5: 5.7 | K5: 37.27 | M5: 0.3 | N5: 1.3
A6: Bandhan Equity Savings Fund - Dir - Growth | B6: -0.14 | C6: 1.03 | D6: 2.72 | E6: 2.82 | F6: 5.36 | G6: 7.7 | H6: 7.16 | I6: 7.53 | K6: 401.02 | M6: 0.19 | N6: 1.11
A7: Baroda BNP Paribas Equity Savings Fund - Dir - Growth | B7: 0.46 | C7: 2.04 | D7: 3.67 | E7: 3.47 | F7: 7.27 | G7: 10.4 | H7: 9.02 | I7: 9.47 | K7: 278.47 | M7: 1.4 | N7: 2.5
A8: DSP Equity Savings Fund - Dir - Growth | B8: -0.17 | C8: 0.1 | D8: 1.33 | E8: 1.19 | F8: 3.53 | G8: 8.86 | H8: 8.03 | I8: 9.34 | K8: 3512.51 | M8: 0.7 | N8: 1.5
A9: Edelweiss Equity Savings Fund - Dir - Growth | B9: 0.24 | C9: 1.56 | D9: 3.95 | E9: 4.98 | F9: 9.04 | G9: 11.76 | H9: 10.02 | I9: 9.86 | K9: 1443.86 | M9: 0.63 | N9: 1.58
A10: Franklin India Equity Savings Fund - Dir - Growth | B10: 0.09 | C10: 0.88 | D10: 2.42 | E10: 2.01 | F10: 4.95 | G10: 7.86 | H10: 7.61 | I10: 8.26 | K10: 618.95 | M10: 0.4 | N10: 1.12
A11: HDFC Equity Savings Fund - Dir - Growth | B11: -0.08 | C11: 1.17 | D11: 3.01 | E11: 1.09 | F11: 4.9 | G11: 9.24 | H11: 8.89 | I11: 10 | K11: 5639.52 | M11: 0.95 | N11: 1.89
A12: HSBC Equity Savings Fund - Dir - Growth | B12: 0.18 | C12: 0.84 | D12: 3.45 | E12: 6.96 | F12: 10.96 | G12: 14.05 | H12: 11.52 | I12: 10.13 | K12: 1126.77 | M12: 0.67 | N12: 1.52
A13: ICICI Prudential Equity Savings Fund - Dir - Growth | B13: 0 | C13: 0.68 | D13: 2.15 | E13: 1.48 | F13: 3.91 | G13: 7.14 | H13: 7.68 | I13: 8.23 | K13: 16499.92 | M13: 0.49 | N13: 0.96
A14: Invesco India Equity Savings Fund - Dir - Growth | B14: 0.18 | C14: 1.25 | D14: 4.1 | E14: 1.98 | F14: 1.42 | G14: 9.23 | H14: 8.06 | I14: 9.01 | K14: 294.41 | M14: 0.74 | N14: 2.3
A15: Kotak Equity Savings Fund - Dir - Growth | B15: 0.06 | C15: 1.74 | D15: 3.07 | E15: 2.97 | F15: 7.56 | G15: 11.07 | H15: 10.71 | I15: 9.98 | K15: 10223.48 | M15: 0.69 | N15: 1.75
A16: LIC MF Equity Savings Fund - Dir - Growth | B16: 0.39 | C16: 2.21 | D16: 2.32 | E16: 4.27 | F16: 5.14 | G16: 9.66 | H16: 8.19 | I16: 7.94 | K16: 36.37 | M16: 1.33 | N16: 2.35
A17: Mahindra Manulife Equity Savings Fund - Dir - Growth | B17: 0.3 | C17: 1.25 | D17: 3.92 | E17: 3.07 | F17: 8.37 | G17: 10.5 | H17: 9.46 | I17: 10.45 | K17: 530.48 | M17: 0.83 | N17: 2.38
... A20: PGIM India Equity Savings Fund - Dir - Growth | B20: 0.08 | C20: 1.11 | D20: 3.28 | E20: 2.42 | F20: 5.04 | G20: 7.24 | H20: 6.7 | I20: 8.67 | K20: 60.21 | M20: 0.59 | N20: 1.32
A21: quant Equity Savings Fund - Dir - Growth | B21: 0.15 | C21: -0.07 | D21: 4.77 | E21: 6.07 | F21: 8.67 | G21: -- | H21: -- | I21: 8.58 | K21: 51.85 | M21: 0.56 | N21: 2.33
A22: SBI Equity Savings Fund - Dir - Growth | B22: -0.1 | C22: 0.85 | D22: 2.15 | E22: 1.87 | F22: 4.69 | G22: 9.11 | H22: 8.7 | I22: 9.44 | K22: 5610.15 | M22: 0.94 | N22: 1.53
A23: Sundaram Equity Savings Fund - Dir - Growth | B23: 0.12 | C23: 1.47 | D23: 2.92 | E23: 1.04 | F23: 3.75 | G23: 10.11 | H23: 10.31 | I23: 9.64 | K23: 1044.03 | M23: 0.77 | N23: 2.19
A24: Union Equity Savings Fund - Dir - Growth | B24: 0.27 | C24: 0.88 | D24: 3.39 | E24: 2.33 | F24: 4.93 | G24: 7.64 | H24: 6.71 | I24: 7.83 | K24: 141.45 | M24: 1.53 | N24: 1.95
A25: UTI Equity Savings Fund - Dir - Growth | B25: -0.19 | C25: 1.14 | D25: 2.55 | E25: 0.85 | F25: 5.83 | G25: 9.19 | H25: 9.34 | I25: 9.42 | K25: 853.03 | M25: 0.65 | N25: 1.65
A26: WhiteOak Capital Equity Savings Fund - Dir - Growth | B26: 0.21 | C26: 1.21 | D26: 3.82 | E26: 3.42 | F26: 8.58 | G26: -- | H26: -- | I26: 12.55 | K26: 273.31 | M26: 0.78 | N26: 2.11
A27: Median | B27: =MEDIAN(B3:B26) -> 0.07 | C27: =MEDIAN(C3:C26) -> 1.125 | D27: =MEDIAN(D3:D26) -> 3.04 | E27: =MEDIAN(E3:E26) -> 2.715 | F27: =MEDIAN(F3:F26) -> 5.36 | G27: =MEDIAN(G3:G26) -> 9.23 | H27: =MEDIAN(H3:H26) -> 8.64 | I27: =MEDIAN(I3:I26) -> 9.35
A28: Index | B28: -- | C28: -- | D28: -- | E28: -- | F28: -- | G28: -- | H28: -- | I28: --
A29: Nifty 500 TRI | B29: -0.48 | C29: 1.92 | D29: 4.93 | E29: 1.85 | F29: 4.99 | G29: 13 | H29: 12.02

Sheet BenchMark Returns
A1: Index | B1: 1 Week | C1: 1 Month | D1: 3 Months | E1: 6 Months | F1: 1 Year | G1: 3 Years | H1: 5 Years
A2: Nifty 100 | B2: -0.73 | C2: 1.74 | D2: 3.53 | E2: -2.16 | F2: 1.18 | G2: 9.7 | H2: 8.82
A3: NIFTY 100 Alpha 30 Index | B3: -1.13 | C3: 1.86 | D3: 3.32 | E3: 1.06 | F3: 0.83 | G3: 15.67 | H3: 10.03
A4: Nifty 100 Low Volatility 30 | B4: -0.92 | C4: 2.64 | D4: 4.56 | E4: -0.11 | F4: 2.89 | G4: 11.15 | H4: 10.11
A5: NIFTY 100 Quality 30 Index | B5: -0.26 | C5: 5.43 | D5: 5.06 | E5: 3.07 | F5: 5.31 | G5: 9.97 | H5: 9.21
A6: Nifty 200 Momentum 30 Index | B6: 0.05 | C6: 1.23 | D6: 2.21 | E6: -1.09 | F6: 2.77 | G6: 12.57 | H6: 10.3
A7: Nifty 200 Quality 30 Index | B7: -0.58 | C7: 4.7 | D7: 4.08 | E7: 3.09 | F7: 3.74 | G7: 9.44 | H7: 8.37
A8: Nifty 50 | B8: -0.83 | C8: 1.31 | D8: 2.86 | E8: -4.31 | F8: -1.08 | G8: 7.82 | H8: 8.06
A9: Nifty 500 | B9: -0.49 | C9: 1.7 | D9: 4.34 | E9: 1.2 | F9: 4.03 | G9: 11.92 | H9: 10.89
A10: Nifty 500 TRI | B10: -0.48 | C10: 1.92 | D10: 4.93 | E10: 1.85 | F10: 4.99 | G10: 13 | H10: 12.02
A11: Nifty Auto | B11: -1.48 | C11: 10.02 | D11: 12.12 | E11: 3.43 | F11: 21.1 | G11: 23.95 | H11: 23.44
A12: Nifty Bank | B12: -0.44 | C12: 0.05 | D12: 6.21 | E12: -4.45 | F12: 3.88 | G12: 9.24 | H12: 9.7
A13: Nifty Capital Markets | B13: 1.63 | C13: -3.81 | D13: -3.92 | E13: 10.41 | F13: 19.99 | G13: 52.36 | H13: 28.02
... A37: Nifty Smallcap250 Momentum Quality 100 | B37: 0.21 | C37: 2.63 | D37: 8.02 | E37: 14.72 | F37: 8.91 | G37: 12.58 | H37: 12.2

Sheet Consumption
A1: ='Small Cap'!A1 -> ( As on 14-08-26 ) | M1: 46082
A2: Scheme Name | B2: 1 Week | C2: 1 Month | D2: 3 Months | E2: 6 Months | F2: 1 Year | G2: 3 Years | H2: 5 Years | I2: Since Inception | K2: AUM ( June 26) | M2: Direct | N2: Regular
A3: Aditya Birla Sun Life Consumption Fund - Dir - Growth | B3: -0.13 | C3: 3.55 | D3: 6.39 | E3: 0.43 | F3: -0.12 | G3: 11.22 | H3: 11.92 | I3: 16.06 | K3: 5989.79 | M3: 0.78 | N3: 1.83
A4: Axis Consumption Fund - Dir - Growth | B4: -0.2 | C4: 5.13 | D4: 8.74 | E4: 3.24 | F4: 2.5 | G4: -- | H4: -- | I4: -0.89 | K4: 2750.01 | M4: 0.66 | N4: 1.97
A5: Bajaj Finserv Consumption Fund - Dir - Growth | B5: -0.33 | C5: 2.58 | D5: 8.34 | E5: 6.11 | F5: 1.82 | G5: -- | H5: -- | I5: -1.8 | K5: 608.45 | M5: 0.74 | N5: 2.37
A6: Bank of India Consumption Fund - Dir - Growth | B6: 0.61 | C6: 4.4 | D6: 9.82 | E6: 7.15 | F6: 8.29 | G6: -- | H6: -- | I6: 9.59 | K6: 360.83 | M6: 1.08 | N6: 2.3
A7: Baroda BNP Paribas India Consumption Fund - Dir - Growth | B7: -0.22 | C7: 4.95 | D7: 7.39 | E7: 2.08 | F7: 2.51 | G7: 12.55 | H7: 12.95 | I7: 17.19 | K7: 1413.2 | M7: 0.65 | N7: 2.09
A8: Canara Robeco Consumption Fund - Dir - Growth | B8: 0.2 | C8: 4.11 | D8: 8.26 | E8: 2.45 | F8: 1.91 | G8: 13.48 | H8: 13.61 | I8: 16.21 | K8: 1932.42 | M8: 0.87 | N8: 2.1
A9: Edelweiss Consumption Fund - Dir - Growth | B9: -0.14 | C9: 4.32 | D9: 7.11 | E9: 3.82 | F9: 5.29 | G9: -- | H9: -- | I9: 11.06 | K9: 483.35 | M9: 0.75 | N9: 2.4
A10: HSBC Consumption Fund - Dir - Growth | B10: 0.47 | C10: 5.38 | D10: 10.84 | E10: 9.63 | F10: 7.55 | G10: -- | H10: -- | I10: 17.47 | K10: 1703 | M10: 1.03 | N10: 2.15
A11: ICICI Prudential Bharat Consumption Fund - Dir - Growth | B11: -0.57 | C11: 5.17 | D11: 7.72 | E11: 4.86 | F11: 3.68 | G11: 12.93 | H11: 15.67 | I11: 14.99 | K11: 3150.45 | M11: 1.14 | N11: 2.04
A12: ICICI Prudential FMCG - Dir - Growth | B12: -1.39 | C12: 0.48 | D12: -2.92 | E12: -4.71 | F12: -11.11 | G12: -1.17 | H12: 7.59 | I12: 11.32 | K12: 1590.67 | M12: 1.38 | N12: 2.21
A13: ITI Bharat Consumption Fund - Dir - Growth | B13: 0.18 | C13: 5.65 | D13: 10.89 | E13: 8.22 | F13: 8.43 | G13: -- | H13: -- | I13: 15.19 | K13: 357.39 | M13: 0.77 | N13: 2.41
A14: Invesco India Consumption Fund - Dir - Growth | B14: -0.54 | C14: 3.69 | D14: 13.47 | E14: 13.99 | F14: -- | G14: -- | H14: -- | I14: 9.5 | K14: 565.28 | M14: 0.73 | N14: 2.37
A15: Kotak Consumption Fund - Dir - Growth | B15: -0.83 | C15: 3.26 | D15: 8.61 | E15: 5.36 | F15: 6.85 | G15: -- | H15: -- | I15: 16.12 | K15: 1711.26 | M15: 0.57 | N15: 2.07
A16: LIC MF Consumption Fund - Dir - Growth | B16: -0.3 | C16: 2.66 | D16: 5.97 | E16: 3.5 | F16: -- | G16: -- | H16: -- | I16: 0.45 | K16: 476.09 | M16: 1.56 | N16: 2.51
A17: Mahindra Manulife Consumption Fund - Dir - Growth | B17: 0.66 | C17: 5.11 | D17: 7.77 | E17: 3.04 | F17: 3.13 | G17: 12.76 | H17: 13.06 | I17: 13 | K17: 494 | M17: 0.78 | N17: 2.41
A18: Mirae Asset Great Consumer Fund - Dir - Growth | B18: 0.08 | C18: 5.83 | D18: 10.54 | E18: 5.68 | F18: 4.46 | G18: 13.98 | H18: 15.18 | I18: 17.11 | K18: 4550.04 | M18: 0.44 | N18: 1.85
A19: Motilal Oswal Consumption Fund - Dir - Growth | B19: 1.34 | C19: 8.22 | D19: 22.13 | E19: 23.41 | F19: -- | G19: -- | H19: -- | I19: 13.28 | K19: 1057.64 | M19: 0.56 | N19: 2.22
A20: Nippon India Consumption Fund - Dir - Growth | B20: -0.38 | C20: 5.9 | D20: 9.35 | E20: 5.65 | F20: 2.18 | G20: 12.67 | H20: 15.13 | I20: 13.78 | K20: 2422.04 | M20: 0.69 | N20: 2.03
A21: Quant Consumption Fund - Dir - Growth | B21: 0.58 | C21: -0.91 | D21: 7.03 | E21: 11.77 | F21: 6.21 | G21: -- | H21: -- | I21: 2.13 | K21: 201.35 | M21: 0.89 | N21: 2.43
A22: SBI Consumption Opportunities Fund - Dir - Growth | B22: -0.7 | C22: 3.14 | D22: 3.3 | E22: -0.11 | F22: -2.28 | G22: 8.3 | H22: 14.31 | I22: 14.98 | K22: 2906.21 | M22: 0.95 | N22: 2.01
A23: Sundaram Consumption Fund - Dir - Growth | B23: 0.61 | C23: 7.64 | D23: 11.02 | E23: 5.93 | F23: 2.2 | G23: 12.45 | H23: 13.47 | I23: 14.36 | K23: 1422.23 | M23: 1.23 | N23: 2.2
A24: Tata India Consumer Fund - Dir - Growth | B24: 0.65 | C24: 5.2 | D24: 10.77 | E24: 13.8 | F24: 10.8 | G24: 17.06 | H24: 16.16 | I24: 17.72 | K24: 2703.34 | M24: 0.8 | N24: 2.04
A25: UTI India Consumer Fund - Dir - Growth | B25: 0.24 | C25: 5.8 | D25: 9.68 | E25: 4.99 | F25: 6.34 | G25: 13.45 | H25: 11.39 | I25: 11.93 | K25: 688.68 | M25: 1.61 | N25: 2.47
A26: Union Consumption Fund - Dir - Growth | B26: 0.6 | C26: 3.93 | D26: 9.59 | E26: 5.64 | F26: -- | G26: -- | H26: -- | I26: 0.6 | K26: 328.62 | M26: 0.95 | N26: 2.43
A27: WhiteOak Capital Consumption Opportunities Fund - Dir - Growth | B27: -0.42 | C27: 3.76 | D27: 9.93 | E27: 8.11 | F27: -- | G27: -- | H27: -- | I27: 5.95 | K27: 113.47 | M27: 0.71 | N27: 2.36
A28: Median | B28: =MEDIAN(B3:B27) -> -0.13 | C28: =MEDIAN(C3:C27) -> 4.4 | D28: =MEDIAN(D3:D27) -> 8.74 | E28: =MEDIAN(E3:E27) -> 5.64 | F28: =MEDIAN(F3:F27) -> 3.405 | G28: =MEDIAN(G3:G27) -> 12.715 | H28: =MEDIAN(H3:H27) -> 13.54 | I28: =MEDIAN(I3:I27) -> 13.28
A29: Index | B29: -- | C29: -- | D29: -- | E29: -- | F29: -- | G29: -- | H29: -- | I29: --
A30: Nifty 500 TRI | B30: ='BenchMark Returns'!B10 -> -0.48 | C30: ='BenchMark Returns'!C10 -> 1.92 | D30: ='BenchMark Returns'!D10 -> 4.93 | E30: ='BenchMark Returns'!E10 -> 1.85 | F30: ='BenchMark Returns'!F10 -> 4.99 | G30: ='BenchMark Returns'!G10 -> 13 | H30: ='BenchMark Returns'!H10 -> 12.02
A31: Nifty India Consumption | B31: ='BenchMark Returns'!B19 -> -0.45 | C31: ='BenchMark Returns'!C19 -> 4.58 | D31: ='BenchMark Returns'!D19 -> 6.64 | E31: ='BenchMark Returns'!E19 -> 3.05 | F31: ='BenchMark Returns'!F19 -> 2.56 | G31: ='BenchMark Returns'!G19 -> 13.86 | H31: ='BenchMark Returns'!H19 -> 13.16

Sheet Financials
A1: ='Small Cap'!A1 -> ( As on 14-08-26 ) | M1: 46082
A2: Scheme Name | B2: 1 Week | C2: 1 Month | D2: 3 Months | E2: 6 Months | F2: 1 Year | G2: 3 Years | H2: 5 Years | I2: Since Inception | K2: AUM ( June 26) | M2: Direct | N2: Regular
A3: Aditya Birla Sun Life Banking and Financial Services Fund - Dir - Growth | B3: -0.18 | C3: -0.51 | D3: 5.33 | E3: -1.47 | F3: 6.9 | G3: 12.01 | H3: 12.15 | I3: 16.82 | K3: 3675.7 | M3: 1 | N3: 1.96
A4: Bajaj Finserv Banking and Financial Services Fund - Dir - Growth | B4: -0.98 | C4: -0.61 | D4: 6.21 | E4: -1.27 | F4: -- | G4: -- | H4: -- | I4: 0.35 | K4: 463.88 | M4: 0.66 | N4: 2.36
A5: Bandhan Financial Services Fund - Dir - Growth | B5: 0.16 | C5: -0.63 | D5: 6.25 | E5: -0.44 | F5: 5.52 | G5: 17.08 | H5: -- | I5: 16.19 | K5: 1107.29 | M5: 0.7 | N5: 2.23
A6: Bank of India Banking & Financial Services Fund - Dir - Growth | B6: 0.1 | C6: -0.6 | D6: 3.24 | E6: -2.93 | F6: -- | G6: -- | H6: -- | I6: -1.3 | K6: 282.25 | M6: 1.13 | N6: 2.3
A7: Baroda BNP Paribas Banking & Financial Services Fund - Dir - Growth | B7: 0.35 | C7: 1.49 | D7: 7.46 | E7: -0.01 | F7: 7.44 | G7: 16.19 | H7: 13.41 | I7: 12 | K7: 421.34 | M7: 0.76 | N7: 2.4
A8: Canara Robeco Banking and Financial Services Fund - Dir - Growth | B8: 0.36 | C8: 1.46 | D8: 7.03 | E8: -- | F8: -- | G8: -- | H8: -- | I8: 11.2 | K8: 615.96 | M8: 0.67 | N8: 2.36
A9: DSP Banking and Financial Services Fund - Dir - Growth | B9: 0.37 | C9: 1.88 | D9: 8.23 | E9: 4.82 | F9: 17.91 | G9: -- | H9: -- | I9: 18.17 | K9: 2012.45 | M9: 0.63 | N9: 2.08
A10: Edelweiss Financial Services Fund - Dir - Growth | B10: -0.49 | C10: -0.54 | D10: 3.74 | E10: -- | F10: -- | G10: -- | H10: -- | I10: -4.08 | K10: 274.48 | M10: 0.74 | N10: 2.39
A11: Groww Banking & Financial Services Fund - Dir - Growth | B11: 0.8 | C11: -0.03 | D11: 7.9 | E11: 7.4 | F11: 13.78 | G11: -- | H11: -- | I11: 12.88 | K11: 75.51 | M11: 0.41 | N11: 2.35
A12: HDFC Banking & Financial Services Fund - Dir - Growth | B12: -0.32 | C12: -1.08 | D12: 5.82 | E12: -1.47 | F12: 8.74 | G12: 14.21 | H12: 13.37 | I12: 13.71 | K12: 4582.3 | M12: 0.82 | N12: 1.92
A13: HSBC Financial Services Fund - Dir - Growth | B13: 0.13 | C13: 0.01 | D13: 5.12 | E13: 2.91 | F13: 13.42 | G13: -- | H13: -- | I13: 18.81 | K13: 926.56 | M13: 0.52 | N13: 2.29
A14: Helios Financial Services Fund - Dir - Growth | B14: 0.76 | C14: -0.33 | D14: 4.44 | E14: -0.33 | F14: 3.72 | G14: -- | H14: -- | I14: 8.89 | K14: 200.28 | M14: 0.84 | N14: 2.42
A15: ICICI Prudential Banking and Financial Services Fund - Dir - Growth | B15: -0.48 | C15: -2.06 | D15: 2.57 | E15: -4.72 | F15: -1.33 | G15: 10.92 | H15: 10.2 | I15: 14.59 | K15: 11034.17 | M15: 1.05 | N15: 1.82
A16: ITI Banking and Financial Services Fund - Dir - Growth | B16: -0.09 | C16: -0.11 | D16: 6.35 | E16: -1.03 | F16: 11.2 | G16: 13.7 | H16: -- | I16: 12.94 | K16: 381.16 | M16: 0.4 | N16: 2.34
A17: Invesco India Financial Services Fund - Dir - Growth | B17: 0.22 | C17: -1.32 | D17: 4.16 | E17: 0.89 | F17: 8.94 | G17: 19.83 | H17: 15.25 | I17: 15.79 | K17: 1811 | M17: 0.81 | N17: 2.11
A18: Kotak Banking & Financial Services Fund - Dir - Growth | B18: -0.63 | C18: -0.64 | D18: 6.45 | E18: -0.51 | F18: 9.26 | G18: 14.9 | H18: -- | I18: 17.01 | K18: 1486.94 | M18: 0.68 | N18: 2.12
A19: LIC MF Banking & Financial Services Fund - Dir - Growth | B19: 0.21 | C19: -0.16 | D19: 5.44 | E19: -2.13 | F19: 6.37 | G19: 9.49 | H19: 11.39 | I19: 8.31 | K19: 269.21 | M19: 1.2 | N19: 2.46
A20: Mahindra Manulife Banking and Financial Services Fund - Dir - Growth | B20: 0.58 | C20: 0.66 | D20: 6.68 | E20: 0.19 | F20: 12.16 | G20: -- | H20: -- | I20: 9.52 | K20: 450.83 | M20: 0.55 | N20: 2.36
A21: Mirae Asset Banking and Financial Services Fund - Dir - Growth | B21: -0.52 | C21: -0.7 | D21: 5.53 | E21: -2.87 | F21: 7.34 | G21: 14.25 | H21: 13.76 | I21: 16.2 | K21: 2304.89 | M21: 0.61 | N21: 2.05
A22: Motilal Oswal Financial Services Fund - Dir - Growth | B22: 0.43 | C22: 2.5 | D22: 10.05 | E22: -- | F22: -- | G22: -- | H22: -- | I22: 8.61 | K22: 191.37 | M22: 1 | N22: 2.43
A23: Nippon India Banking & Financial Services Fund - Dir - Growth | B23: -0.09 | C23: -1.53 | D23: 3.99 | E23: -2.84 | F23: 5.15 | G23: 13.72 | H23: 14.15 | I23: 13.94 | K23: 7788.58 | M23: 0.97 | N23: 1.85
A24: Quant BFSI Fund - Dir - Growth | B24: -1.11 | C24: -3.19 | D24: 6.92 | E24: 6.96 | F24: 18.05 | G24: 23.87 | H24: -- | I24: 27.07 | K24: 837.94 | M24: 0.75 | N24: 2.35
A25: SBI Banking & Financial Services Fund - Dir - Growth | B25: -0.46 | C25: -0.71 | D25: 2.67 | E25: -5.44 | F25: 3.88 | G25: 17.16 | H25: 13.55 | I25: 14.9 | K25: 10844.85 | M25: 0.74 | N25: 1.77
A26: Sundaram Financial Services Opportunities Fund - Dir - Growth | B26: -0.3 | C26: -0.45 | D26: 5.7 | E26: -0.77 | F26: 10.54 | G26: 14.92 | H26: 14.95 | I26: 13.78 | K26: 1681.38 | M26: 0.79 | N26: 2.11
A27: Tata Banking And Financial Services Fund - Dir - Growth | B27: 0.19 | C27: -0.33 | D27: 5.58 | E27: -1.91 | F27: 6.71 | G27: 13.28 | H27: 13.28 | I27: 16.84 | K27: 3170.66 | M27: 0.56 | N27: 1.94
A28: Taurus Banking & Financial Services Fund - Dir - Growth | B28: -1.11 | C28: -1.64 | D28: 2.25 | E28: -4.13 | F28: -0.72 | G28: 9.54 | H28: 10.39 | I28: 11.42 | K28: 11.69 | M28: 2.49 | N28: 2.57
A29: UTI Banking and Financial Services Fund - Dir - Growth | B29: -0.18 | C29: 0.05 | D29: 6 | E29: -2.14 | F29: 6.81 | G29: 14.48 | H29: 12.73 | I29: 11.85 | K29: 1429.59 | M29: 1.08 | N29: 2.16
A30: WhiteOak Capital Banking & Financial Services Fund - Dir - Growth | B30: -0.26 | C30: 0.28 | D30: 6.9 | E30: 0.5 | F30: 7.18 | G30: -- | H30: -- | I30: 13.22 | K30: 633.39 | M30: 0.72 | N30: 2.39
A31: Median | B31: =MEDIAN(B3:B30) -> -0.09 | C31: =MEDIAN(C3:C30) -> -0.48 | D31: =MEDIAN(D3:D30) -> 5.76 | E31: =MEDIAN(E3:E30) -> -1.03 | F31: =MEDIAN(F3:F30) -> 7.34 | G31: =MEDIAN(G3:G30) -> 14.25 | H31: =MEDIAN(H3:H30) -> 13.37 | I31: =MEDIAN(I3:I30) -> 13.465
A32: Index | B32: -- | C32: -- | D32: -- | E32: -- | F32: -- | G32: -- | H32: -- | I32: --
A33: Nifty 500 TRI | B33: ='BenchMark Returns'!B10 -> -0.48 | C33: ='BenchMark Returns'!C10 -> 1.92 | D33: ='BenchMark Returns'!D10 -> 4.93 | E33: ='BenchMark Returns'!E10 -> 1.85 | F33: ='BenchMark Returns'!F10 -> 4.99 | G33: ='BenchMark Returns'!G10 -> 13 | H33: ='BenchMark Returns'!H10 -> 12.02
A34: Nifty Financial Services | B34: ='BenchMark Returns'!B17 -> -0.95 | C34: ='BenchMark Returns'!C17 -> -1.22 | D34: ='BenchMark Returns'!D17 -> 2.91 | E34: ='BenchMark Returns'!E17 -> -6.76 | F34: ='BenchMark Returns'!F17 -> -0.45 | G34: ='BenchMark Returns'!G17 -> 10.07 | H34: ='BenchMark Returns'!H17 -> 8.59

Sheet Digital
A1: ='Small Cap'!A1 -> ( As on 14-08-26 ) | M1: 46082
A2: Scheme Name | B2: 1 Week | C2: 1 Month | D2: 3 Months | E2: 6 Months | F2: 1 Year | G2: 3 Years | H2: 5 Years | I2: Since Inception | K2: AUM ( June 26) | M2: Direct | N2: Regular
A3: Aditya Birla Sun Life Digital India Fund - Dir - Growth | B3: 0.31 | C3: 8.33 | D3: 15.36 | E3: 2.96 | F3: -1.37 | G3: 7.21 | H3: 5.99 | I3: 18.46 | K3: 3589.29 | M3: 0.83 | N3: 1.91
A4: Edelweiss Technology Fund - Dir - Growth | B4: 0.89 | C4: 7.74 | D4: 14.01 | E4: 15.66 | F4: 13.71 | G4: -- | H4: -- | I4: 13.23 | K4: 707.62 | M4: 0.64 | N4: 2.34
A5: Franklin India Technology Fund - Dir - Growth | B5: 0.76 | C5: 7.28 | D5: 12.42 | E5: 3.5 | F5: -1.75 | G5: 12.15 | H5: 9.29 | I5: 17.42 | K5: 1583.05 | M5: 1.13 | N5: 2.12
A6: HDFC Technology Fund - Dir - Growth | B6: 0.41 | C6: 6.82 | D6: 15.07 | E6: 0.23 | F6: -5.91 | G6: -- | H6: -- | I6: 8.17 | K6: 1278.73 | M6: 0.99 | N6: 2.19
A7: ICICI Prudential Technology Fund - Dir - Growth | B7: 0.57 | C7: 6.93 | D7: 13.67 | E7: 0.47 | F7: -3.02 | G7: 8.93 | H7: 5.8 | I7: 19.01 | K7: 12547.28 | M7: 1.03 | N7: 1.78
A8: Invesco India Technology Fund - Dir - Growth | B8: 1.28 | C8: 6.42 | D8: 13.61 | E8: 12.54 | F8: 6.98 | G8: -- | H8: -- | I8: 1.42 | K8: 302.32 | M8: 0.82 | N8: 2.39
A9: Kotak Technology Fund - Dir - Growth | B9: 0.27 | C9: 7.02 | D9: 13.84 | E9: -0.13 | F9: -3.54 | G9: -- | H9: -- | I9: 3.82 | K9: 505.35 | M9: 0.88 | N9: 2.38
A10: LIC MF Technology Fund - Dir - Growth | B10: 1.15 | C10: 5.53 | D10: 11.28 | E10: -- | F10: -- | G10: -- | H10: -- | I10: 15.13 | K10: 85.99 | M10: 0.61 | N10: 2.37
A11: Motilal Oswal Digital India Fund - Dir - Growth | B11: 1.79 | C11: 4.14 | D11: 19.39 | E11: 13.47 | F11: 1.71 | G11: -- | H11: -- | I11: 1.67 | K11: 804.53 | M11: 1.04 | N11: 2.37
A12: Quant Teck Fund - Dir - Growth | B12: -0.07 | C12: 0.99 | D12: 11.07 | E12: 21.46 | F12: -1.15 | G12: -- | H12: -- | I12: 6.23 | K12: 250.5 | M12: 0.89 | N12: 2.43
A13: SBI Technology Opportunities Fund - Dir - Growth | B13: 0.11 | C13: 8.71 | D13: 14.22 | E13: 1.87 | F13: -2.11 | G13: 11.37 | H13: 8.79 | I13: 18.71 | K13: 4017.71 | M13: 0.94 | N13: 1.93
A14: Tata Digital India Fund - Dir - Growth | B14: 0.13 | C14: 6.78 | D14: 14.26 | E14: 0.61 | F14: -5.62 | G14: 8.13 | H14: 6.13 | I14: 16.43 | K14: 9196.15 | M14: 0.56 | N14: 1.74
A15: WhiteOak Capital Digital Bharat Fund - Dir - Growth | B15: 1.86 | C15: 5.96 | D15: 19.39 | E15: 11.02 | F15: 4.31 | G15: -- | H15: -- | I15: 4.26 | K15: 428.16 | M15: 0.64 | N15: 2.39
A16: Median | B16: =MEDIAN(B3:B15) -> 0.57 | C16: =MEDIAN(C3:C15) -> 6.82 | D16: =MEDIAN(D3:D15) -> 14.01 | E16: =MEDIAN(E3:E15) -> 3.23 | F16: =MEDIAN(F3:F15) -> -1.56 | G16: =MEDIAN(G3:G15) -> 8.93 | H16: =MEDIAN(H3:H15) -> 6.13 | I16: =MEDIAN(I3:I15) -> 13.23
A17: Index | B17: -- | C17: -- | D17: -- | E17: -- | F17: -- | G17: -- | H17: -- | I17: --
A18: Nifty 500 TRI | B18: =Financials!B33 -> -0.48 | C18: =Financials!C33 -> 1.92 | D18: =Financials!D33 -> 4.93 | E18: =Financials!E33 -> 1.85 | F18: =Financials!F33 -> 4.99 | G18: =Financials!G33 -> 13 | H18: =Financials!H33 -> 12.02
A19: Nifty India Digital Index | B19: ='BenchMark Returns'!B21 -> 1.56 | C19: ='BenchMark Returns'!C21 -> 7.69 | D19: ='BenchMark Returns'!D21 -> 15.94 | E19: ='BenchMark Returns'!E21 -> 4.37 | F19: ='BenchMark Returns'!F21 -> -0.31 | G19: ='BenchMark Returns'!G21 -> 12.64 | H19: ='BenchMark Returns'!H21 -> 7.87
A20: Nifty IT | B20: ='BenchMark Returns'!B24 -> -0.6 | C20: ='BenchMark Returns'!C24 -> 9.17 | D20: ='BenchMark Returns'!D24 -> 14.61 | E20: ='BenchMark Returns'!E24 -> -4.03 | F20: ='BenchMark Returns'!F24 -> -9.98 | G20: ='BenchMark Returns'!G24 -> 0.35 | H20: ='BenchMark Returns'!H24 -> -0.82

Sheet Healthcare
A1: ='Small Cap'!A1 -> ( As on 14-08-26 ) | M1: 46082
A2: Scheme Name | B2: 1 Week | C2: 1 Month | D2: 3 Months | E2: 6 Months | F2: 1 Year | G2: 3 Years | H2: 5 Years | I2: Since Inception | K2: AUM ( June 26) | M2: Direct | N2: Regular
A3: Aditya Birla Sun Life Pharma & Healthcare Fund - Dir - Growth | B3: 0.29 | C3: 2.74 | D3: 9.87 | E3: 20.96 | F3: 17.56 | G3: 22.53 | H3: 15.34 | I3: 21.91 | K3: 1010.54 | M3: 1.02 | N3: 2.3
A4: Bajaj Finserv Healthcare Fund - Dir - Growth | B4: 0.3 | C4: 4.76 | D4: 12.83 | E4: 24.7 | F4: 21.42 | G4: -- | H4: -- | I4: 11.7 | K4: 354.03 | M4: 0.74 | N4: 2.39
A5: Bandhan Healthcare Fund - Dir - Growth | B5: 0.54 | C5: 2.78 | D5: 9.76 | E5: 19.58 | F5: -- | G5: -- | H5: -- | I5: 13.68 | K5: 322.43 | M5: 0.71 | N5: 2.41
A6: Baroda BNP Paribas Health and Wellness Fund (BBNPHW) - Dir - Growth | B6: -0.79 | C6: 1.06 | D6: 8.3 | E6: 15.5 | F6: 10.48 | G6: -- | H6: -- | I6: 7.98 | K6: 553.17 | M6: 0.6 | N6: 2.33
A7: DSP Healthcare Fund - Dir - Growth | B7: 2.11 | C7: 3.16 | D7: 13.91 | E7: 23.6 | F7: 16.1 | G7: 22.21 | H7: 16.56 | I7: 23.52 | K7: 3514.02 | M7: 0.62 | N7: 1.94
A8: HDFC Pharma and Healthcare Fund - Dir - Growth | B8: -0.14 | C8: 3.11 | D8: 11.42 | E8: 25.21 | F8: 25.04 | G8: -- | H8: -- | I8: 32.2 | K8: 2611.33 | M8: 0.94 | N8: 2.1
A9: ICICI Prudential Pharma Healthcare and Diagnostics Fund - Dir - Growth | B9: -0.75 | C9: -0.15 | D9: 4.61 | E9: 15.66 | F9: 9.04 | G9: 23.45 | H9: 16.92 | I9: 21.2 | K9: 6624.58 | M9: 1.05 | N9: 1.87
A10: ITI Pharma and Healthcare Fund - Dir - Growth | B10: -0.79 | C10: 2.58 | D10: 8.22 | E10: 20.71 | F10: 12.39 | G10: 20.31 | H10: -- | I10: 15.45 | K10: 251.87 | M10: 0.47 | N10: 2.35
A11: Kotak Healthcare Fund - Dir - Growth | B11: 0.37 | C11: 2.82 | D11: 12.03 | E11: 26.22 | F11: 24.5 | G11: -- | H11: -- | I11: 23.01 | K11: 678.41 | M11: 0.74 | N11: 2.34
A12: LIC MF Healthcare Fund - Dir - Growth | B12: -0.32 | C12: 3.73 | D12: 9.7 | E12: 21.76 | F12: 15.69 | G12: 22.57 | H12: 13.16 | I12: 19.36 | K12: 92.55 | M12: 0.64 | N12: 2.36
A13: Mirae Asset Healthcare Fund - Dir - Growth | B13: -0.46 | C13: 1.77 | D13: 7.94 | E13: 21.47 | F13: 18.56 | G13: 23.22 | H13: 16.25 | I13: 22.35 | K13: 3252.54 | M13: 0.51 | N13: 1.94
A14: Nippon India Pharma Fund - Dir - Growth | B14: 0.39 | C14: 1.59 | D14: 5.85 | E14: 14.47 | F14: 11.3 | G14: 19.16 | H14: 14.41 | I14: 17.75 | K14: 9044.23 | M14: 0.93 | N14: 1.82
A15: PGIM India Healthcare Fund - Dir - Growth | B15: 0.08 | C15: 4.6 | D15: 13.12 | E15: 25.74 | F15: 24.01 | G15: -- | H15: -- | I15: 14.14 | K15: 103.24 | M15: 0.65 | N15: 2.37
A16: Quant Healthcare Fund - Dir - Growth | B16: 0.22 | C16: 2.96 | D16: 9.74 | E16: 21.84 | F16: 20.03 | G16: 21.45 | H16: -- | I16: 22.52 | K16: 391.06 | M16: 0.83 | N16: 2.42
A17: SBI Healthcare Opportunities Fund - Dir - Growth | B17: 0.36 | C17: 3.8 | D17: 12.78 | E17: 25.12 | F17: 21.56 | G17: 24.67 | H17: 19.08 | I17: 18.42 | K17: 4997.72 | M17: 0.92 | N17: 1.93
A18: Tata India Pharma And Healthcare Fund - Dir - Growth | B18: -0.55 | C18: 1.5 | D18: 6.85 | E18: 14.86 | F18: 9.93 | G18: 20.34 | H18: 15.52 | I18: 13.85 | K18: 1455.16 | M18: 0.72 | N18: 2.15
A19: UTI Healthcare Fund - Dir - Growth | B19: 0.79 | C19: 2.78 | D19: 11.37 | E19: 22.63 | F19: 16.87 | G19: 24.64 | H19: 16.76 | I19: 16.65 | K19: 1307.98 | M19: 1.3 | N19: 2.28
A20: WhiteOak Capital Pharma and Healthcare Fund - Dir - Growth | B20: 0.4 | C20: 3.6 | D20: 12.39 | E20: 24.55 | F20: 21.76 | G20: -- | H20: -- | I20: 24.95 | K20: 741.34 | M20: 0.67 | N20: 2.35
A21: Median | B21: =MEDIAN(B3:B20) -> 0.255 | C21: =MEDIAN(C3:C20) -> 2.8 | D21: =MEDIAN(D3:D20) -> 9.815 | E21: =MEDIAN(E3:E20) -> 21.8 | F21: =MEDIAN(F3:F20) -> 17.56 | G21: =MEDIAN(G3:G20) -> 22.53 | H21: =MEDIAN(H3:H20) -> 16.25 | I21: =MEDIAN(I3:I20) -> 18.89
A22: Index | B22: -- | C22: -- | D22: -- | E22: -- | F22: -- | G22: -- | H22: -- | I22: --
A23: Nifty 500 TRI | B23: ='BenchMark Returns'!B10 -> -0.48 | C23: ='BenchMark Returns'!C10 -> 1.92 | D23: ='BenchMark Returns'!D10 -> 4.93 | E23: ='BenchMark Returns'!E10 -> 1.85 | F23: ='BenchMark Returns'!F10 -> 4.99 | G23: ='BenchMark Returns'!G10 -> 13 | H23: ='BenchMark Returns'!H10 -> 12.02
A24: Nifty Healthcare Index | B24: ='BenchMark Returns'!B18 -> -1.22 | C24: ='BenchMark Returns'!C18 -> 0.39 | D24: ='BenchMark Returns'!D18 -> 5.05 | E24: ='BenchMark Returns'!E18 -> 14.67 | F24: ='BenchMark Returns'!F18 -> 12.7 | G24: ='BenchMark Returns'!G18 -> 19.98 | H24: ='BenchMark Returns'!H18 -> 13.32

Sheet Infrastructure
A1: ='Small Cap'!A1 -> ( As on 14-08-26 ) | M1: 46082
A2: Scheme Name | B2: 1 Week | C2: 1 Month | D2: 3 Months | E2: 6 Months | F2: 1 Year | G2: 3 Years | H2: 5 Years | I2: Since Inception | K2: AUM ( June 26) | M2: Direct | N2: Regular
A3: Aditya Birla Sun Life Infrastructure Fund - Dir - Growth | B3: -0.07 | C3: 3.51 | D3: 8.41 | E3: 14.1 | F3: 17.42 | G3: 20.06 | H3: 19.4 | I3: 15.96 | K3: 1233.59 | M3: 1.42 | N3: 2.28
A4: Bandhan Infrastructure Fund - Dir - Growth | B4: -0.49 | C4: -0.49 | D4: 3.87 | E4: 6.01 | F4: 3.09 | G4: 18.38 | H4: 17.93 | I4: 14.91 | K4: 1545.49 | M4: 0.97 | N4: 2.18
A5: Canara Robeco Infrastructure Fund - Dir - Growth | B5: -0.12 | C5: 1.56 | D5: 1.45 | E5: 5.9 | F5: 8.54 | G5: 22.6 | H5: 21.48 | I5: 16.94 | K5: 998.07 | M5: 1.07 | N5: 2.31
A6: Franklin Build India Fund - Dir - Growth | B6: -0.5 | C6: -0.8 | D6: -0.53 | E6: -1.23 | F6: 4.41 | G6: 20.01 | H6: 20.55 | I6: 20.26 | K6: 3255.73 | M6: 0.99 | N6: 2
A7: HDFC Defence Fund - Dir - Growth | B7: 0.65 | C7: 5.49 | D7: 11.37 | E7: 27.28 | F7: 31.22 | G7: 41.91 | H7: -- | I7: 43.25 | K7: 10529.25 | M7: 0.83 | N7: 1.82
A8: HDFC Infrastructure Fund - Dir - Growth | B8: -0.3 | C8: 0.01 | D8: 1.34 | E8: 0.27 | F8: 1.23 | G8: 17.29 | H8: 20.58 | I8: 12.09 | K8: 2444.21 | M8: 1.19 | N8: 2.11
A9: HSBC Infrastructure Fund - Dir - Growth | B9: 0.91 | C9: 3.96 | D9: 2.82 | E9: 10.14 | F9: 13.01 | G9: 18.52 | H9: 20.33 | I9: 17.21 | K9: 2452.94 | M9: 1.02 | N9: 2.09
A10: ICICI Prudential Infrastructure Fund - Dir - Growth | B10: -0.27 | C10: 0.62 | D10: 3.36 | E10: 4.63 | F10: 7.06 | G10: 20.41 | H10: 23.39 | I10: 16.47 | K10: 8549.71 | M10: 1.18 | N10: 1.86
A11: Invesco India Infrastructure Fund - Dir - Growth | B11: 0.26 | C11: 3.24 | D11: 9.38 | E11: 17.55 | F11: 12.1 | G11: 23.44 | H11: 21.15 | I11: 19.25 | K11: 1568.25 | M11: 0.95 | N11: 2.18
A12: Kotak Infrastructure & Economic Reform Fund - Dir - Growth | B12: 0.76 | C12: 3.36 | D12: 7.04 | E12: 9.15 | F12: 12.44 | G12: 18.18 | H12: 20.57 | I12: 17.91 | K12: 2446.83 | M12: 0.69 | N12: 2.04
A13: LIC MF Infrastructure Fund - Dir - Growth | B13: 0.38 | C13: 2.57 | D13: 6.96 | E13: 11.58 | F13: 17.29 | G13: 27.38 | H13: 23.92 | I13: 16.12 | K13: 1137.05 | M13: 1.01 | N13: 2.38
A14: Mirae Asset Infrastructure Fund - Dir - Growth | B14: 0.13 | C14: 3.68 | D14: 7.16 | E14: 12.2 | F14: -- | G14: -- | H14: -- | I14: 15.03 | K14: 446.61 | M14: 0.75 | N14: 2.4
A15: Motilal Oswal Infrastructure Fund - Dir - Growth | B15: 0.19 | C15: 0.96 | D15: 0.26 | E15: 6.23 | F15: 11.69 | G15: -- | H15: -- | I15: 22.28 | K15: 145.87 | M15: 0.81 | N15: 2.36
A16: Nippon India Power & Infra Fund - Dir - Growth | B16: -0.48 | C16: 2.35 | D16: 2.35 | E16: 11.39 | F16: 15.54 | G16: 22.51 | H16: 23.03 | I16: 15.54 | K16: 8043.44 | M16: 0.98 | N16: 1.86
A17: Quant Infrastructure Fund - Dir - Growth | B17: -0.14 | C17: -1.73 | D17: 4.13 | E17: 14.03 | F17: 14.99 | G17: 20.13 | H17: 20.1 | I17: 17.29 | K17: 3205.29 | M17: 0.91 | N17: 2.04
A18: SBI Infrastructure Fund - Dir - Growth | B18: -0.21 | C18: 0.46 | D18: 1.82 | E18: 5.69 | F18: 8.32 | G18: 16.74 | H18: 18.07 | I18: 14.71 | K18: 4852.12 | M18: 1.04 | N18: 1.95
A19: Sundaram Infrastructure Advantage Fund - Dir - Growth | B19: 0.44 | C19: 1.22 | D19: 1.85 | E19: 5.09 | F19: 10.52 | G19: 19.01 | H19: 17.78 | I19: 14.03 | K19: 999.72 | M19: 1.59 | N19: 2.35
A20: Tata Infrastructure Fund - Dir - Growth | B20: -0.34 | C20: -0.45 | D20: 3.86 | E20: 10.15 | F20: 10.17 | G20: 15.48 | H20: 18.02 | I20: 14.98 | K20: 2102.52 | M20: 1.21 | N20: 2.15
A21: Taurus Infrastructure Fund - Dir - Growth | B21: -0.85 | C21: -0.52 | D21: -1.54 | E21: -2.23 | F21: -2.62 | G21: 12.11 | H21: 11.92 | I21: 13.17 | K21: 8.88 | M21: 2.45 | N21: 2.53
A22: UTI Infrastructure Fund - Dir - Growth | B22: -0.08 | C22: 1.37 | D22: 2.53 | E22: 2.05 | F22: 6.17 | G22: 15.91 | H22: 14.9 | I22: 12.69 | K22: 2162.49 | M22: 1.97 | N22: 2.24
A23: Median | B23: =MEDIAN(B3:B22) -> -0.1 | C23: =MEDIAN(C3:C22) -> 1.295 | D23: =MEDIAN(D3:D22) -> 3.09 | E23: =MEDIAN(E3:E22) -> 7.69 | F23: =MEDIAN(F3:F22) -> 10.52 | G23: =MEDIAN(G3:G22) -> 19.51 | H23: =MEDIAN(H3:H22) -> 20.33 | I23: =MEDIAN(I3:I22) -> 16.04
A24: Index | B24: -- | C24: -- | D24: -- | E24: -- | F24: -- | G24: -- | H24: -- | I24: --
A25: Nifty 500 TRI | B25: ='BenchMark Returns'!B10 -> -0.48 | C25: ='BenchMark Returns'!C10 -> 1.92 | D25: ='BenchMark Returns'!D10 -> 4.93 | E25: ='BenchMark Returns'!E10 -> 1.85 | F25: ='BenchMark Returns'!F10 -> 4.99 | G25: ='BenchMark Returns'!G10 -> 13 | H25: ='BenchMark Returns'!H10 -> 12.02
A26: Nifty Infrastructure | B26: ='BenchMark Returns'!B23 -> -0.89 | C26: ='BenchMark Returns'!C23 -> 0.73 | D26: ='BenchMark Returns'!D23 -> 0.54 | E26: ='BenchMark Returns'!E23 -> -1.29 | F26: ='BenchMark Returns'!F23 -> 4.76 | G26: ='BenchMark Returns'!G23 -> 16.24 | H26: ='BenchMark Returns'!H23 -> 15.57

Sheet Manufacturing
A1: ='Small Cap'!A1 -> ( As on 14-08-26 ) | M1: 46082
A2: Scheme Name | B2: 1 Week | C2: 1 Month | D2: 3 Months | E2: 6 Months | F2: 1 Year | G2: 3 Years | H2: 5 Years | I2: Since Inception | K2: AUM ( June 26) | M2: Direct | N2: Regular
A3: Aditya Birla Sun Life Manufacturing Equity Fund - Dir - Growth | B3: 0.72 | C3: 7.78 | D3: 12.3 | E3: 19.61 | F3: 29.97 | G3: 23.12 | H3: 16.56 | I3: 13.84 | K3: 1229.35 | M3: 1.34 | N3: 2.27
A4: Axis India Manufacturing Fund - Dir - Growth | B4: 0.06 | C4: 6.46 | D4: 9.73 | E4: 14.51 | F4: 21.02 | G4: -- | H4: -- | I4: 21.66 | K4: 5377.75 | M4: 0.47 | N4: 1.84
A5: Bank of India Manufacturing & Infrastructure Fund - Dir - Growth | B5: -0.06 | C5: 1.81 | D5: 7.32 | E5: 14.76 | F5: 25.09 | G5: 25.12 | H5: 22.42 | I5: 17.85 | K5: 836.52 | M5: 0.62 | N5: 2.23
A6: Baroda BNP Paribas Manufacturing Fund - Dir - Growth | B6: -0.1 | C6: 4.9 | D6: 5.18 | E6: 11.93 | F6: 21.06 | G6: -- | H6: -- | I6: 7.68 | K6: 858.01 | M6: 1.15 | N6: 2.27
A7: Canara Robeco Manufacturing Fund - Dir - Growth | B7: 1.03 | C7: 4.48 | D7: 7.69 | E7: 15.48 | F7: 17.88 | G7: -- | H7: -- | I7: 17.2 | K7: 1689.17 | M7: 0.9 | N7: 2.14
A8: DSP India Tiger Fund - Dir - Growth | B8: -0.02 | C8: 1.27 | D8: 5.02 | E8: 13.64 | F8: 19.33 | G8: 23.32 | H8: 22.94 | I8: 17.08 | K8: 6263.54 | M8: 0.89 | N8: 1.89
A9: HDFC Manufacturing Fund - Dir - Growth | B9: -0.27 | C9: 5.41 | D9: 7.76 | E9: 9.49 | F9: 14.59 | G9: -- | H9: -- | I9: 9.85 | K9: 10327.97 | M9: 0.84 | N9: 1.79
A10: ICICI Prudential Manufacturing Fund - Dir - Growth | B10: -1.09 | C10: 4.51 | D10: 6.8 | E10: 10.48 | F10: 18.03 | G10: 23.14 | H10: 20.95 | I10: 20.62 | K10: 6842.52 | M10: 0.81 | N10: 1.86
A11: Invesco India Manufacturing Fund - Dir - Growth | B11: 0.16 | C11: 7.78 | D11: 13.82 | E11: 18.94 | F11: 19.04 | G11: -- | H11: -- | I11: 10.41 | K11: 697.9 | M11: 0.79 | N11: 2.36
A12: Kotak Manufacture in India Fund - Dir - Growth | B12: 0.03 | C12: 6.1 | D12: 9.98 | E12: 12.36 | F12: 23.53 | G12: 21.58 | H12: -- | I12: 21.48 | K12: 2803.9 | M12: 0.59 | N12: 1.98
A13: LIC MF Manufacturing Fund - Dir - Growth | B13: -0.01 | C13: 3.96 | D13: 9.08 | E13: 15.52 | F13: 23.22 | G13: -- | H13: -- | I13: 10.5 | K13: 781.52 | M13: 1.66 | N13: 2.47
A14: Mahindra Manulife Manufacturing Fund - Dir - Growth | B14: 0.14 | C14: 3.97 | D14: 6.74 | E14: 9.27 | F14: 15.31 | G14: -- | H14: -- | I14: 5.32 | K14: 677.34 | M14: 0.88 | N14: 2.38
A15: Motilal Oswal Manufacturing Fund - Dir - Growth | B15: 1.16 | C15: 5.8 | D15: 6.12 | E15: 10.52 | F15: 9.83 | G15: -- | H15: -- | I15: 10.37 | K15: 688.04 | M15: 1.12 | N15: 2.39
A16: Quant Manufacturing Fund - Dir - Growth | B16: -0.86 | C16: -0.16 | D16: 7.62 | E16: 21.79 | F16: 22.24 | G16: 20.63 | H16: -- | I16: 20.63 | K16: 743.87 | M16: 1.07 | N16: 2.44
A17: SBI Automotive Opportunities Fund - Dir - Growth | B17: 0.12 | C17: 12.14 | D17: 19.42 | E17: 17.04 | F17: 39.5 | G17: -- | H17: -- | I17: 16.09 | K17: 5380.09 | M17: 0.86 | N17: 1.9
A18: Median | B18: =MEDIAN(B3:B17) -> 0.03 | C18: =MEDIAN(C3:C17) -> 4.9 | D18: =MEDIAN(D3:D17) -> 7.69 | E18: =MEDIAN(E3:E17) -> 14.51 | F18: =MEDIAN(F3:F17) -> 21.02 | G18: =MEDIAN(G3:G17) -> 23.13 | H18: =MEDIAN(H3:H17) -> 21.685 | I18: =MEDIAN(I3:I17) -> 16.09
A19: Index | B19: -- | C19: -- | D19: -- | E19: -- | F19: -- | G19: -- | H19: -- | I19: --
A20: Nifty 500 TRI | B20: ='BenchMark Returns'!B10 -> -0.48 | C20: ='BenchMark Returns'!C10 -> 1.92 | D20: ='BenchMark Returns'!D10 -> 4.93 | E20: ='BenchMark Returns'!E10 -> 1.85 | F20: ='BenchMark Returns'!F10 -> 4.99 | G20: ='BenchMark Returns'!G10 -> 13 | H20: ='BenchMark Returns'!H10 -> 12.02
A21: Nifty India Manufacturing | B21: ='BenchMark Returns'!B22 -> -0.7 | C21: ='BenchMark Returns'!C22 -> 4.38 | D21: ='BenchMark Returns'!D22 -> 4.51 | E21: ='BenchMark Returns'!E22 -> 6.22 | F21: ='BenchMark Returns'!F22 -> 16.91 | G21: ='BenchMark Returns'!G22 -> 19.96 | H21: ='BenchMark Returns'!H22 -> 16.9

Sheet PSU
A1: ='Small Cap'!A1 -> ( As on 14-08-26 ) | M1: 46082
A2: Scheme Name | B2: 1 Week | C2: 1 Month | D2: 3 Months | E2: 6 Months | F2: 1 Year | G2: 3 Years | H2: 5 Years | I2: Since Inception | K2: AUM ( June 26) | M2: Direct | N2: Regular
A3: Aditya Birla Sun Life PSU Equity Fund - Dir - Growth | B3: -0.1 | C3: 1.77 | D3: -0.35 | E3: 0.22 | F3: 15.46 | G3: 24.46 | H3: 24.69 | I3: 23.41 | K3: 6018.74 | M3: 0.59 | N3: 1.82
A4: ICICI Prudential PSU Equity Fund - Dir - Growth | B4: -0.47 | C4: 1.09 | D4: -0.77 | E4: -0.55 | F4: 10.5 | G4: 24.14 | H4: -- | I4: 24.01 | K4: 1886.25 | M4: 0.87 | N4: 2.1
A5: Invesco India PSU Equity Fund - Dir - Growth | B5: 0.7 | C5: 3.36 | D5: 0.84 | E5: -0.02 | F5: 9.02 | G5: 23.97 | H5: 22.98 | I5: 16.25 | K5: 1472.61 | M5: 0.91 | N5: 2.14
A6: Quant PSU Fund - Dir - Growth | B6: -0.9 | C6: 0.03 | D6: -4.42 | E6: 9.31 | F6: 9 | G6: -- | H6: -- | I6: 3.85 | K6: 473.19 | M6: 1.13 | N6: 2.47
A7: SBI PSU Fund - Dir - Growth | B7: -0.08 | C7: 0.84 | D7: -1.86 | E7: -2.99 | F7: 12.11 | G7: 24.78 | H7: 24.69 | I7: 11.85 | K7: 6683.53 | M7: 0.85 | N7: 1.86
A8: Median | B8: =MEDIAN(B3:B7) -> -0.1 | C8: =MEDIAN(C3:C7) -> 1.09 | D8: =MEDIAN(D3:D7) -> -0.77 | E8: =MEDIAN(E3:E7) -> -0.02 | F8: =MEDIAN(F3:F7) -> 10.5 | G8: =MEDIAN(G3:G7) -> 24.3 | H8: =MEDIAN(H3:H7) -> 24.69 | I8: =MEDIAN(I3:I7) -> 16.25
A9: Index | B9: -- | C9: -- | D9: -- | E9: -- | F9: -- | G9: -- | H9: -- | I9: --
A10: Nifty 500 TRI | B10: ='BenchMark Returns'!B10 -> -0.48 | C10: ='BenchMark Returns'!C10 -> 1.92 | D10: ='BenchMark Returns'!D10 -> 4.93 | E10: ='BenchMark Returns'!E10 -> 1.85 | F10: ='BenchMark Returns'!F10 -> 4.99 | G10: ='BenchMark Returns'!G10 -> 13 | H10: ='BenchMark Returns'!H10 -> 12.02

Sheet Energy
A1: ='Small Cap'!A1 -> ( As on 14-08-26 ) | M1: 46082
A2: Scheme Name | B2: 1 Week | C2: 1 Month | D2: 3 Months | E2: 6 Months | F2: 1 Year | G2: 3 Years | H2: 5 Years | I2: Since Inception | K2: AUM ( June 26) | M2: Direct | N2: Regular
A3: Baroda BNP Paribas Energy Opportunities Fund - Dir - Growth | B3: -0.31 | C3: 0.49 | D3: -4.5 | E3: 1.05 | F3: 6.83 | G3: -- | H3: -- | I3: 12.73 | K3: 672.25 | M3: 1.01 | N3: 2.36
A4: DSP Natural Resources & New Energy Fund - Dir - Gth | B4: -0.27 | C4: 2.07 | D4: -3.65 | E4: 2.21 | F4: 24.58 | G4: 21.53 | H4: 16.62 | I4: 17.53 | K4: 2400.8 | M4: 0.81 | N4: 1.98
A5: ICICI Prudential Energy Opportunities Fund - Dir - Growth | B5: 0.59 | C5: 1.54 | D5: 1.02 | E5: 9.44 | F5: 18.44 | G5: -- | H5: -- | I5: 8.71 | K5: 8351.56 | M5: 0.61 | N5: 1.76
A6: Kotak Energy Opportunities Fund - Dir - Growth | B6: -0.68 | C6: 1.8 | D6: 0.54 | E6: 4.27 | F6: 8.05 | G6: -- | H6: -- | I6: 6.73 | K6: 273.46 | M6: 0.89 | N6: 2.42
A7: SBI Energy Opportunities Fund - Dir - Growth | B7: -0.33 | C7: 1.32 | D7: 0.51 | E7: 5.32 | F7: 9.16 | G7: -- | H7: -- | I7: 5.69 | K7: 8712.01 | M7: 0.8 | N7: 1.8
A8: Tata Resources & Energy Fund - Dir - Growth | B8: -1 | C8: 0.73 | D8: 0.3 | E8: 6.39 | F8: 12.45 | G8: 18.24 | H8: 13.51 | I8: 18.12 | K8: 1361.2 | M8: 0.57 | N8: 2.1
A9: Median | B9: =MEDIAN(B3:B8) -> -0.32 | C9: =MEDIAN(C3:C8) -> 1.43 | D9: =MEDIAN(D3:D8) -> 0.405 | E9: =MEDIAN(E3:E8) -> 4.795 | F9: =MEDIAN(F3:F8) -> 10.805 | G9: =MEDIAN(G3:G8) -> 19.885 | H9: =MEDIAN(H3:H8) -> 15.065 | I9: =MEDIAN(I3:I8) -> 10.72
A10: Index | B10: -- | C10: -- | D10: -- | E10: -- | F10: -- | G10: -- | H10: -- | I10: --
A11: Nifty 500 TRI | B11: ='BenchMark Returns'!B10 -> -0.48 | C11: ='BenchMark Returns'!C10 -> 1.92 | D11: ='BenchMark Returns'!D10 -> 4.93 | E11: ='BenchMark Returns'!E10 -> 1.85 | F11: ='BenchMark Returns'!F10 -> 4.99 | G11: ='BenchMark Returns'!G10 -> 13 | H11: ='BenchMark Returns'!H10 -> 12.02
A12: Nifty Energy | B12: ='BenchMark Returns'!B16 -> -0.5 | C12: ='BenchMark Returns'!C16 -> -1.66 | D12: ='BenchMark Returns'!D16 -> -3.81 | E12: ='BenchMark Returns'!E16 -> 7.92 | F12: ='BenchMark Returns'!F16 -> 11.85 | G12: ='BenchMark Returns'!G16 -> 13.48 | H12: ='BenchMark Returns'!H16 -> 14.38

Sheet Transportation & Logistics
A1: ='Small Cap'!A1 -> ( As on 14-08-26 ) | M1: 46082
A2: Scheme Name | B2: 1 Week | C2: 1 Month | D2: 3 Months | E2: 6 Months | F2: 1 Year | G2: 3 Years | H2: 5 Years | I2: Since Inception | K2: AUM ( June 26) | M2: Direct | N2: Regular
A3: Aditya Birla Sun Life Transportation and Logistics Fund - Dir - Growth | B3: 1.1 | C3: 12.17 | D3: 23.34 | E3: 14.69 | F3: 27.72 | G3: -- | H3: -- | I3: 24.75 | K3: 1573.52 | M3: 0.79 | N3: 2.11
A4: Bandhan Transportation and Logistics Fund - Dir - Growth | B4: 0.29 | C4: 8.28 | D4: 15.25 | E4: 6.34 | F4: 21.32 | G4: 23.38 | H4: -- | I4: 23.67 | K4: 692.8 | M4: 0.9 | N4: 2.39
A5: HDFC Transportation and Logistics Fund - Dir - Growth | B5: 0.57 | C5: 9.93 | D5: 18.81 | E5: 10.93 | F5: 23.48 | G5: -- | H5: -- | I5: 27.72 | K5: 1792.44 | M5: 1 | N5: 2.15
A6: ICICI Prudential Transportation and Logistics Fund - Dir - Growth | B6: 0.29 | C6: 11.03 | D6: 18.08 | E6: 9.17 | F6: 23.39 | G6: 26.28 | H6: -- | I6: 26.15 | K6: 3490.4 | M6: 0.98 | N6: 2.03
A7: Kotak Transportation & Logistics Fund - Dir - Growth | B7: -0.07 | C7: 8.51 | D7: 12.99 | E7: 4.61 | F7: 13.9 | G7: -- | H7: -- | I7: 13.69 | K7: 510.32 | M7: 0.83 | N7: 2.41
A8: UTI Transportation and Logistics Fund - Dir - Growth | B8: -0.32 | C8: 8.41 | D8: 13.07 | E8: 4.41 | F8: 16.17 | G8: 21.67 | H8: 21.9 | I8: 19.13 | K8: 3962.19 | M8: 0.82 | N8: 1.91
A9: Median | B9: =MEDIAN(B3:B8) -> 0.29 | C9: =MEDIAN(C3:C8) -> 9.22 | D9: =MEDIAN(D3:D8) -> 16.665 | E9: =MEDIAN(E3:E8) -> 7.755 | F9: =MEDIAN(F3:F8) -> 22.355 | G9: =MEDIAN(G3:G8) -> 23.38 | H9: =MEDIAN(H3:H8) -> 21.9 | I9: =MEDIAN(I3:I8) -> 24.21
A10: Index | B10: -- | C10: -- | D10: -- | E10: -- | F10: -- | G10: -- | H10: -- | I10: --
A11: Nifty 500 TRI | B11: ='BenchMark Returns'!B10 -> -0.48 | C11: ='BenchMark Returns'!C10 -> 1.92 | D11: ='BenchMark Returns'!D10 -> 4.93 | E11: ='BenchMark Returns'!E10 -> 1.85 | F11: ='BenchMark Returns'!F10 -> 4.99 | G11: ='BenchMark Returns'!G10 -> 13 | H11: ='BenchMark Returns'!H10 -> 12.02

Sheet Services
A1: ='Small Cap'!A1 -> ( As on 14-08-26 ) | M1: 46082
A2: Scheme Name | B2: 1 Week | C2: 1 Month | D2: 3 Months | E2: 6 Months | F2: 1 Year | G2: 3 Years | H2: 5 Years | I2: Since Inception | K2: AUM ( June 26) | M2: Direct | N2: Regular
A3: Axis Services Opportunities Fund - Dir - Growth | B3: 0 | C3: 0.8 | D3: 7.9 | E3: 3.99 | F3: 1.3 | G3: -- | H3: -- | I3: 1.04 | K3: 1625 | M3: 0.78 | N3: 2.13
A4: Kotak Services Fund - Dir - Growth | B4: -0.05 | C4: 1.3 | D4: 7.36 | E4: -- | F4: -- | G4: -- | H4: -- | I4: 6.29 | K4: 749.06 | M4: 0.92 | N4: 2.35
A5: Motilal Oswal Services Fund - Dir - Growth | B5: 0.53 | C5: 2.43 | D5: 11.81 | E5: 14.37 | F5: 15.67 | G5: -- | H5: -- | I5: 15.26 | K5: 119.63 | M5: 0.81 | N5: 2.36
A6: Sundaram Services Fund - Dir - Growth | B6: 0.42 | C6: 2.31 | D6: 10.91 | E6: 6.97 | F6: 9.41 | G6: 16.64 | H6: 15.75 | I6: 19.47 | K6: 4933.98 | M6: 0.69 | N6: 1.88
A7: Median | B7: =MEDIAN(B3:B6) -> 0.21 | C7: =MEDIAN(C3:C6) -> 1.805 | D7: =MEDIAN(D3:D6) -> 9.405 | E7: =MEDIAN(E3:E6) -> 6.97 | F7: =MEDIAN(F3:F6) -> 9.41 | G7: =MEDIAN(G3:G6) -> 16.64 | H7: =MEDIAN(H3:H6) -> 15.75 | I7: =MEDIAN(I3:I6) -> 10.775
A8: Index | B8: -- | C8: -- | D8: -- | E8: -- | F8: -- | G8: -- | H8: -- | I8: --
A9: Nifty 500 TRI | B9: ='BenchMark Returns'!B10 -> -0.48 | C9: ='BenchMark Returns'!C10 -> 1.92 | D9: ='BenchMark Returns'!D10 -> 4.93 | E9: ='BenchMark Returns'!E10 -> 1.85 | F9: ='BenchMark Returns'!F10 -> 4.99 | G9: ='BenchMark Returns'!G10 -> 13 | H9: ='BenchMark Returns'!H10 -> 12.02

Sheet Exports
A1: ='Small Cap'!A1 -> ( As on 14-08-26 ) | M1: 46082
A2: Scheme Name | B2: 1 Week | C2: 1 Month | D2: 3 Months | E2: 6 Months | F2: 1 Year | G2: 3 Years | H2: 5 Years | I2: Since Inception | K2: AUM ( June 26) | M2: Direct | N2: Regular
A3: HSBC India Export Opportunities Fund - Dir - Growth | B3: 0.64 | C3: 7.3 | D3: 16.17 | E3: 18.75 | F3: 24.72 | G3: -- | H3: -- | I3: 9.87 | K3: 1200.57 | M3: 1.04 | N3: 2.24
A4: ICICI Prudential Exports and Services Fund - Dir - Growth | B4: 0.13 | C4: 3.17 | D4: 7.77 | E4: 3.89 | F4: 6.57 | G4: 16.83 | H4: 15.41 | I4: 18.23 | K4: 1397.12 | M4: 1.67 | N4: 2.29
A5: Median | B5: =MEDIAN(B3:B4) -> 0.385 | C5: =MEDIAN(C3:C4) -> 5.235 | D5: =MEDIAN(D3:D4) -> 11.97 | E5: =MEDIAN(E3:E4) -> 11.32 | F5: =MEDIAN(F3:F4) -> 15.645 | G5: =MEDIAN(G3:G4) -> 16.83 | H5: =MEDIAN(H3:H4) -> 15.41 | I5: =MEDIAN(I3:I4) -> 14.05
A6: Index | B6: -- | C6: -- | D6: -- | E6: -- | F6: -- | G6: -- | H6: -- | I6: --
A7: Nifty 500 TRI | B7: ='BenchMark Returns'!B10 -> -0.48 | C7: ='BenchMark Returns'!C10 -> 1.92 | D7: ='BenchMark Returns'!D10 -> 4.93 | E7: ='BenchMark Returns'!E10 -> 1.85 | F7: ='BenchMark Returns'!F10 -> 4.99 | G7: ='BenchMark Returns'!G10 -> 13 | H7: ='BenchMark Returns'!H10 -> 12.02

Sheet Smart Beta Strategy Funds
A1: ='Small Cap'!A1 -> ( As on 14-08-26 ) | M1: 46082
A2: Scheme Name | B2: 1 Week | C2: 1 Month | D2: 3 Months | E2: 6 Months | F2: 1 Year | G2: 3 Years | H2: 5 Years | I2: Since Inception | K2: AUM ( June 26) | M2: Direct | N2: Regular
A3: Aditya Birla Sun Life Nifty 50 Equal Weight Index Fund - Dir - Growth | B3: -0.99 | C3: 2.54 | D3: 3.75 | E3: 1.09 | F3: 7.88 | G3: 14.2 | H3: 13.34 | I3: 13.6 | K3: 497.72 | M3: 0.42 | N3: 1.04
A4: Angel One Nifty Total Market Momentum Quality 50 Index Fund - Dir - Growth | B4: 1.81 | C4: 3.4 | D4: 2.77 | E4: 7.38 | F4: -- | G4: -- | H4: -- | I4: 4.17 | K4: 35.67 | M4: 0.34 | N4: 1.04
A5: Axis Nifty500 Momentum 50 Index Fund - Dir - Growth | B5: 0.54 | C5: 2.59 | D5: 3.88 | E5: 4.82 | F5: 6.5 | G5: -- | H5: -- | I5: 8.59 | K5: 162.59 | M5: 0.15 | N5: 1.05
A6: Axis Nifty500 Quality 50 Index Fund - Dir - Growth | B6: -0.18 | C6: 1.97 | D6: 3.73 | E6: 8.8 | F6: -- | G6: -- | H6: -- | I6: 3.76 | K6: 77.04 | M6: 0.16 | N6: 1.06
A7: Axis Nifty500 Value 50 Index Fund - Dir - Growth | B7: -2.05 | C7: 0.88 | D7: -2.74 | E7: -0.34 | F7: 18.01 | G7: -- | H7: -- | I7: 8.11 | K7: 218.49 | M7: 0.17 | N7: 1.05
A8: Bandhan Nifty 200 Quality 30 Index Fund - Dir - Growth | B8: -0.57 | C8: 5.01 | D8: 4.67 | E8: 3.81 | F8: 4.87 | G8: -- | H8: -- | I8: -0.37 | K8: 10.92 | M8: 0.37 | N8: 1.02
A9: Bandhan Nifty 500 Momentum 50 Index Fund - Dir - Growth | B9: 0.54 | C9: 2.56 | D9: 3.85 | E9: 4.61 | F9: 6.24 | G9: -- | H9: -- | I9: -4.79 | K9: 35.56 | M9: 0.37 | N9: 1.02
A10: Bandhan Nifty 500 Value 50 Index Fund - Dir - Growth | B10: -2.05 | C10: 0.86 | D10: -2.9 | E10: -0.65 | F10: 17.5 | G10: -- | H10: -- | I10: 7.51 | K10: 36.76 | M10: 0.37 | N10: 1.02
A11: Bandhan Nifty Alpha 50 Index Fund - Dir - Growth | B11: 0.29 | C11: 4.15 | D11: 7.81 | E11: 11.55 | F11: 11.41 | G11: -- | H11: -- | I11: 15.2 | K11: 580.47 | M11: 0.35 | N11: 1.02
A12: Bandhan Nifty Alpha Low Volatility 30 Index Fund - Dir - Growth | B12: -1.01 | C12: 2.88 | D12: 6.44 | E12: 1.11 | F12: 4.91 | G12: -- | H12: -- | I12: 3.16 | K12: 8.76 | M12: 0.28 | N12: 1.03
A13: Bandhan Nifty100 Low Volatility 30 Index Fund - Dir - Growth | B13: -0.93 | C13: 2.9 | D13: 5.19 | E13: 0.45 | F13: 3.47 | G13: 11.72 | H13: -- | I13: 13.3 | K13: 1660.23 | M13: 0.35 | N13: 1.04
A14: Bandhan Nifty200 Momentum 30 Index Fund - Dir - Growth | B14: 0.05 | C14: 1.29 | D14: 2.27 | E14: -1.07 | F14: 2.5 | G14: 12.43 | H14: -- | I14: 12.38 | K14: 124.33 | M14: 0.42 | N14: 1.07
A15: Baroda BNP Paribas Nifty200 Momentum 30 Index Fund - Dir - Growth | B15: 0.05 | C15: 1.27 | D15: 2.28 | E15: -1.14 | F15: 2.2 | G15: -- | H15: -- | I15: -10.23 | K15: 22.35 | M15: 0.47 | N15: 1.1
A16: DSP Nifty 50 Equal Weight Index Fund - Dir - Growth | B16: -0.98 | C16: 2.53 | D16: 3.76 | E16: 1.1 | F16: 7.93 | G16: 14.24 | H16: 13.45 | I16: 12.36 | K16: 2585.02 | M16: 0.4 | N16: 0.93
A17: DSP Nifty Midcap 150 Quality 50 Index Fund - Dir - Growth | B17: 0.01 | C17: 3.41 | D17: 6.05 | E17: 7.18 | F17: 4.73 | G17: 11.46 | H17: -- | I17: 11.01 | K17: 433.74 | M17: 0.29 | N17: 0.87
A18: DSP Nifty Smallcap250 Quality 50 Index Fund - Dir - Growth | B18: 0.29 | C18: 2.36 | D18: 4.96 | E18: 5.85 | F18: -2.33 | G18: -- | H18: -- | I18: 5.07 | K18: 311.12 | M18: 0.16 | N18: 0.82
A19: DSP Nifty Top 10 Equal Weight Index Fund - Dir - Growth | B19: -0.99 | C19: 1.37 | D19: 3.05 | E19: -6.93 | F19: -6.36 | G19: -- | H19: -- | I19: -4.77 | K19: 1116.87 | M19: 0.24 | N19: 0.9
A20: DSP Nifty500 Flexicap Quality 30 Index Fund - Dir - Growth | B20: -0.07 | C20: 4.68 | D20: 8.15 | E20: 2.62 | F20: -- | G20: -- | H20: -- | I20: -0.25 | K20: 184.37 | M20: 0.3 | N20: 0.95
A21: Edelweiss Nifty 100 Quality 30 Index Fund - Dir - Growth | B21: -0.26 | C21: 5.77 | D21: 5.72 | E21: 3.87 | F21: 6.42 | G21: 11.26 | H21: -- | I21: 8.98 | K21: 134.11 | M21: 0.38 | N21: 1.05
A22: Edelweiss Nifty Alpha Low Volatility 30 Index Fund - Dir - Growth | B22: -1.01 | C22: 2.85 | D22: 6.41 | E22: 1.08 | F22: 4.84 | G22: -- | H22: -- | I22: 1.42 | K22: 95.45 | M22: 0.39 | N22: 1.1
A23: Edelweiss Nifty Midcap150 Momentum 50 Index Fund - Dir - Growth | B23: 0.36 | C23: 2.04 | D23: 3.03 | E23: 3.73 | F23: 5.83 | G23: 18.32 | H23: -- | I23: 18.75 | K23: 1723.34 | M23: 0.43 | N23: 1.11
A24: Edelweiss Nifty500 Multicap Momentum Quality 50 Index Fund - Dir - Growth | B24: 1.18 | C24: 2.13 | D24: -0.84 | E24: 2.67 | F24: 3.91 | G24: -- | H24: -- | I24: -4.42 | K24: 596.09 | M24: 0.36 | N24: 1.03
A25: HDFC NIFTY 100 Equal Weight Index Fund - Dir - Growth | B25: -0.65 | C25: 3.2 | D25: 5.43 | E25: 5.26 | F25: 10.23 | G25: 16.61 | H25: -- | I25: 14.01 | K25: 505.08 | M25: 0.4 | N25: 0.87
A26: HDFC Nifty Top 20 Equal Weight Index Fund - Dir - Growth | B26: -0.67 | C26: 3.88 | D26: 6.55 | E26: -3.91 | F26: 1.03 | G26: -- | H26: -- | I26: 2.59 | K26: 90.69 | M26: 0.3 | N26: 0.79
A27: HDFC NIFTY100 Low Volatility 30 Index Fund - Dir - Growth | B27: -0.93 | C27: 2.9 | D27: 5.17 | E27: 0.44 | F27: 3.43 | G27: -- | H27: -- | I27: 3.06 | K27: 221.99 | M27: 0.4 | N27: 0.9
A28: HDFC Nifty100 Quality 30 Index Fund - Dir - Growth | B28: -0.24 | C28: 5.79 | D28: 5.64 | E28: 3.78 | F28: 6.27 | G28: -- | H28: -- | I28: 7.78 | K28: 142.51 | M28: 0.4 | N28: 0.85
A29: HDFC NIFTY200 Momentum 30 Index Fund - Dir - Growth | B29: 0.06 | C29: 1.29 | D29: 2.3 | E29: -1.09 | F29: 2.55 | G29: -- | H29: -- | I29: 1.62 | K29: 620.44 | M29: 0.4 | N29: 0.85
A30: HDFC NIFTY50 Equal Weight Index Fund - Dir - Growth | B30: -0.99 | C30: 2.53 | D30: 3.68 | E30: 1.02 | F30: 7.81 | G30: 14.2 | H30: -- | I30: 13.66 | K30: 1747.33 | M30: 0.4 | N30: 0.86
A31: ICICI Prudential Active Momentum Fund - Dir - Growth | B31: -0.18 | C31: 3.14 | D31: 4 | E31: 4.27 | F31: 12.47 | G31: -- | H31: -- | I31: 11.15 | K31: 2081.15 | M31: 0.82 | N31: 1.75
A32: ICICI Prudential Nifty 200 Momentum 30 Index Fund - Dir - Growth | B32: 0.06 | C32: 1.3 | D32: 2.33 | E32: -1 | F32: 2.65 | G32: 12.61 | H32: -- | I32: 13.91 | K32: 560.91 | M32: 0.32 | N32: 1
A33: ICICI Prudential Nifty200 Quality 30 Index Fund - Dir - Growth | B33: -0.57 | C33: 4.97 | D33: 4.62 | E33: 3.74 | F33: 4.83 | G33: -- | H33: -- | I33: 1.43 | K33: 24.81 | M33: 0.39 | N33: 0.8
A34: ICICI Prudential Nifty200 Value 30 Index Fund - Dir - Growth | B34: -2.05 | C34: 0.7 | D34: -2.95 | E34: -2.23 | F34: 18.97 | G34: -- | H34: -- | I34: 6 | K34: 213.92 | M34: 0.38 | N34: 0.86
A35: ICICI Prudential Nifty50 Equal Weight Index Fund - Dir - Growth | B35: -0.98 | C35: 2.53 | D35: 3.69 | E35: 1.08 | F35: 7.83 | G35: 14.13 | H35: -- | I35: 15.46 | K35: 250.62 | M35: 0.26 | N35: 1
A36: ICICI Prudential Nifty50 Value 20 Index Fund - Dir - Growth | B36: -1.48 | C36: -0.04 | D36: 0.96 | E36: -7.48 | F36: -3.25 | G36: -- | H36: -- | I36: 0.83 | K36: 98.7 | M36: 0.25 | N36: 0.63
A37: Kotak Nifty 100 Equal Weight Index Fund - Dir - Growth | B37: -0.65 | C37: 3.22 | D37: 5.55 | E37: 5.53 | F37: 10.39 | G37: -- | H37: -- | I37: 8.08 | K37: 44.24 | M37: 0.22 | N37: 0.72
A38: Kotak Nifty 100 Low Volatility 30 Index Fund - Dir - Growth | B38: -0.92 | C38: 2.91 | D38: 5.36 | E38: 0.55 | F38: 3.58 | G38: -- | H38: -- | I38: 4.96 | K38: 113.07 | M38: 0.2 | N38: 0.83
A39: Kotak Nifty 200 Momentum 30 Index Fund - Dir - Growth | B39: 0.06 | C39: 1.3 | D39: 2.37 | E39: -0.97 | F39: 2.75 | G39: 12.83 | H39: -- | I39: 13.25 | K39: 575.29 | M39: 0.2 | N39: 0.66
A40: Kotak Nifty 200 Quality 30 Index Fund - Dir - Growth | B40: -0.57 | C40: 5.02 | D40: 4.78 | E40: 3.95 | F40: 5.07 | G40: -- | H40: -- | I40: 1.89 | K40: 16.58 | M40: 0.23 | N40: 0.6
A41: Kotak Nifty 50 Equal Weight Index Fund - Dir - Growth | B41: -0.98 | C41: 2.56 | D41: 3.82 | E41: 1.11 | F41: 7.82 | G41: -- | H41: -- | I41: 8.38 | K41: 60.97 | M41: 0.22 | N41: 0.72
A42: Kotak Nifty Alpha 50 Index Fund - Dir - Growth | B42: 0.29 | C42: 4.15 | D42: 7.7 | E42: 11.54 | F42: -- | G42: -- | H42: -- | I42: 9.01 | K42: 38.31 | M42: 0.35 | N42: 0.94
A43: Kotak NIFTY Midcap 150 Momentum 50 Index Fund - Dir - Growth | B43: 0.37 | C43: 2.04 | D43: 2.79 | E43: 3.55 | F43: 5.84 | G43: -- | H43: -- | I43: -1.74 | K43: 432.08 | M43: 0.28 | N43: 0.93
A44: Kotak Nifty Top 10 Equal Weight Index Fund - Dir - Growth | B44: -0.99 | C44: 1.39 | D44: 3.05 | E44: -6.91 | F44: -6.38 | G44: -- | H44: -- | I44: -6.09 | K44: 40.65 | M44: 0.22 | N44: 0.92
A45: Kotak Nifty200 Value 30 Index Fund - Dir - Growth | B45: -2.06 | C45: 0.61 | D45: -2.91 | E45: -2.57 | F45: -- | G45: -- | H45: -- | I45: -2.81 | K45: 30.84 | M45: 0.21 | N45: 0.52
A46: Kotak Nifty500 Momentum 50 Index Fund - Dir - Growth | B46: 0.54 | C46: 2.59 | D46: 3.9 | E46: 4.67 | F46: -- | G46: -- | H46: -- | I46: 3.47 | K46: 24.3 | M46: 0.19 | N46: 0.52
A47: Mirae Asset Nifty Total Market Index Fund - Dir - Growth | B47: -0.44 | C47: 1.96 | D47: 5.19 | E47: 2.34 | F47: 5.02 | G47: -- | H47: -- | I47: 3.25 | K47: 51.15 | M47: 0.3 | N47: 0.97
A48: Motilal Oswal Nifty 200 Momentum 30 Index Fund - Dir - Growth | B48: 0.05 | C48: 1.29 | D48: 2.28 | E48: -1.07 | F48: 2.4 | G48: 12.79 | H48: -- | I48: 10.19 | K48: 971.62 | M48: 0.32 | N48: 1.01
A49: Motilal Oswal Active Momentum Fund - Dir - Growth | B49: 1.4 | C49: 4.74 | D49: 11.2 | E49: 18.55 | F49: 29.57 | G49: -- | H49: -- | I49: 28.21 | K49: 942.4 | M49: 1.85 | N49: 1.94
A50: Motilal Oswal Nifty 500 Momentum 50 Index Fund - Dir - Growth | B50: 0.54 | C50: 2.58 | D50: 3.83 | E50: 4.57 | F50: 6.07 | G50: -- | H50: -- | I50: -8.33 | K50: 801.48 | M50: 0.44 | N50: 1.11
A51: Navi Nifty Smallcap250 Momentum Quality 100 Index Fund - Dir - Growth | B51: 0.26 | C51: 2.76 | D51: 7.94 | E51: 14.54 | F51: 8.68 | G51: -- | H51: -- | I51: 14.81 | K51: 38.33 | M51: 0.3 | N51: 0.98
A52: Nippon India Nifty 50 Value 20 Index Fund - Dir - Growth | B52: -1.48 | C52: -0.04 | D52: 0.9 | E52: -7.53 | F52: -3.34 | G52: 7.41 | H52: 8.53 | I52: 11.11 | K52: 860.12 | M52: 0.25 | N52: 0.78
A53: Nippon India Nifty 500 Equal Weight Index Fund - Dir - Growth | B53: -0.43 | C53: 1.72 | D53: 6.51 | E53: 9.56 | F53: 8.54 | G53: -- | H53: -- | I53: 0.04 | K53: 505.59 | M53: 0.35 | N53: 0.97
A54: Nippon India Nifty 500 Low Volatility 50 Index Fund - Dir - Growth | B54: -1.07 | C54: 2.34 | D54: 2.92 | E54: -0.56 | F54: 6.17 | G54: -- | H54: -- | I54: 7.33 | K54: 28.96 | M54: 0.35 | N54: 0.95
A55: Nippon India Nifty 500 Momentum 50 Index Fund - Dir - Growth | B55: 0.54 | C55: 2.59 | D55: 4.44 | E55: 5.23 | F55: 7.04 | G55: -- | H55: -- | I55: -7.88 | K55: 1254.8 | M55: 0.25 | N55: 0.88
A56: Nippon India Nifty 500 Quality 50 Index Fund - Dir - Growth | B56: -0.17 | C56: 2.03 | D56: 3.54 | E56: 8.32 | F56: 7.07 | G56: -- | H56: -- | I56: 9.43 | K56: 42.84 | M56: 0.35 | N56: 0.9
A57: Nippon India Nifty Alpha Low Volatility 30 Index Fund - Dir - Growth | B57: -1.01 | C57: 2.86 | D57: 6.45 | E57: 1.19 | F57: 4.92 | G57: 12.8 | H57: -- | I57: 13.43 | K57: 1282.88 | M57: 0.35 | N57: 0.86
A58: SBI Nifty100 Low Volatility 30 Index Fund - Dir - Growth | B58: -0.93 | C58: 2.89 | D58: 5.17 | E58: 0.42 | F58: 3.46 | G58: -- | H58: -- | I58: 3.92 | K58: 59.51 | M58: 0.4 | N58: 0.79
A59: SBI Nifty200 Momentum 30 Index Fund - Dir - Growth | B59: 0.05 | C59: 1.29 | D59: 2.25 | E59: -1.1 | F59: 2.51 | G59: -- | H59: -- | I59: -1.33 | K59: 127.59 | M59: 0.41 | N59: 0.79
A60: SBI Nifty200 Quality 30 Index Fund - Dir - Growth | B60: -0.57 | C60: 5 | D60: 4.66 | E60: 3.8 | F60: 4.89 | G60: -- | H60: -- | I60: 2.76 | K60: 312.47 | M60: 0.35 | N60: 0.82
A61: SBI Nifty50 Equal Weight Index Fund - Dir - Growth | B61: -0.99 | C61: 2.52 | D61: 3.67 | E61: 1.01 | F61: 7.8 | G61: -- | H61: -- | I61: 9.1 | K61: 1050.87 | M61: 0.45 | N61: 0.94
A62: Sundaram Nifty 100 Equal Weight Fund - Dir - Growth | B62: -0.65 | C62: 3.17 | D62: 5.56 | E62: 5.53 | F62: 10.43 | G62: 16.49 | H62: 13.2 | I62: 12.38 | K62: 142.37 | M62: 0.49 | N62: 1.05
A63: Tata BSE Quality Index Fund - Dir - Growth | B63: -0.97 | C63: 2.56 | D63: 2.19 | E63: 6.49 | F63: 9.36 | G63: -- | H63: -- | I63: 12.3 | K63: 57.63 | M63: 0.3 | N63: 1.06
A64: Tata Nifty Midcap 150 Momentum 50 Index Fund - Dir - Growth | B64: 0.36 | C64: 2.03 | D64: 2.64 | E64: 3.35 | F64: 5.45 | G64: 17.74 | H64: -- | I64: 17.99 | K64: 1201.66 | M64: 0.44 | N64: 1.05
A65: UTI BSE Low Volatility Index Fund - Dir - Growth | B65: -1.05 | C65: 1.32 | D65: 1.72 | E65: -2.68 | F65: 0.44 | G65: 9.34 | H65: -- | I65: 12.04 | K65: 479.19 | M65: 0.43 | N65: 0.9
A66: UTI Nifty 50 Equal Weight Index Fund - Dir - Growth | B66: -0.99 | C66: 2.53 | D66: 3.75 | E66: 1.11 | F66: 7.96 | G66: 14.07 | H66: -- | I66: 14.66 | K66: 147.83 | M66: 0.32 | N66: 0.78
A67: UTI Nifty 500 Value 50 Index Fund - Dir - Growth | B67: -2.06 | C67: 0.84 | D67: -2.84 | E67: -0.63 | F67: 17.5 | G67: 25.62 | H67: -- | I67: 27.96 | K67: 774.96 | M67: 0.63 | N67: 1.09
A68: UTI Nifty Alpha Low-Volatility 30 Index Fund - Dir - Growth | B68: -1.02 | C68: 2.83 | D68: 6.38 | E68: 1.06 | F68: 4.74 | G68: -- | H68: -- | I68: 0.02 | K68: 73.51 | M68: 0.78 | N68: 1.12
A69: UTI Nifty Midcap 150 Quality 50 Index Fund - Dir - Growth | B69: 0.02 | C69: 3.42 | D69: 6.03 | E69: 7.12 | F69: 4.54 | G69: 11.32 | H69: -- | I69: 9.4 | K69: 244.72 | M69: 0.59 | N69: 1.04
A70: UTI Nifty Midsmallcap 400 Momentum Quality 100 Index Fund - Dir - Growth | B70: 0.2 | C70: 2.83 | D70: 3.66 | E70: 10.36 | F70: 9.44 | G70: -- | H70: -- | I70: 12.37 | K70: 120.14 | M70: 0.65 | N70: 1.1
A71: UTI Nifty200 Momentum 30 Index Fund - Dir - Growth | B71: 0.05 | C71: 1.3 | D71: 2.45 | E71: -0.87 | F71: 2.79 | G71: 13.12 | H71: 10.89 | I71: 15.17 | K71: 8541.21 | M71: 0.43 | N71: 0.9
A72: UTI Nifty200 Quality 30 Index Fund - Dir - Growth | B72: -0.57 | C72: 5.01 | D72: 4.67 | E72: 3.78 | F72: 4.82 | G72: -- | H72: -- | I72: -4.26 | K72: 542.95 | M72: 0.7 | N72: 1.1
A73: Median | B73: =MEDIAN(B3:B72) -> -0.57 | C73: =MEDIAN(C3:C72) -> 2.56 | D73: =MEDIAN(D3:D72) -> 3.825 | E73: =MEDIAN(E3:E72) -> 1.765 | F73: =MEDIAN(F3:F72) -> 5.26 | G73: =MEDIAN(G3:G72) -> 12.975 | H73: =MEDIAN(H3:H72) -> 13.2 | I73: =MEDIAN(I3:I72) -> 7.93
